Workbook

Sheet Read me
B1: Portfolio workbook · Full (Example)
B2: A record of every program and project in one portfolio, kept by hand. Six tabs: Read me, Portfolio, Register, Funding, Steering and Checks.
A3: Example. Wexbridge Quill Software and everyone in it are made up. Clear the white cells to start your own.
A5: Filling it in
A6: 1 | B6: On Portfolio, type the portfolio's name, director, manager and status. If a steering group meets, pick how often, and add a First review date if it hasn't met yet.
A7: 2 | B7: On Register, add a row for every program and every project, with Sits under, Status and Owner. On projects, pick an Approach in the last column, after Check.
A8: 3 | B8: Type Planned finish, Latest forecast and Forecast spend, and Budget on programs and on projects directly under Portfolio. On Funding, type the envelope, its currency and where it came from.
A9: 4 | B9: Read Health and Check on Register, and the Checks tab for every result. Write a Variance note on every Amber or Red row, ending with your name.
A10: 5 | B10: After each steering meeting, add it under Meetings on Steering. Then log its decisions, each with one accountable person and who recorded it, and any actions with an owner and a due date.
A12: YOUR LOGO
B13: The FRQZ logo is in cell A1 on every tab. To use your own, delete it and insert your logo in A1, on each tab.
A15: NAMES
B16: Type each person's name the same way every time, with a role in brackets if you like: Priya (CTO). Names are matched exactly as typed, so Priya and Priya (CTO) count as two people.
A18: READING THE MARKS
A19: ■ Red | B19: Late, or over budget, by more than your limit. The limits are on the Checks tab, and you can change them.
A20: ◧ Amber | B20: Late, or over budget, within your limit.
A21: □ On track | B21: A date or a budget was read, and nothing is late or over.
A22: Not read | B22: Nothing to judge from yet. A project with a Planned finish and no Latest forecast reads Not read; if the date hasn't moved, type it again as the forecast. A Sprint project always reads Not read.
A23: Not counted | B23: Proposed, Completed or Terminated. Left out of every count.
A24: △ | B24: A check found something, and the words say what. Filter the Check column on △ to list them all.
A25: ○ Clear | B25: The check found nothing.
A27: HOW HEALTH IS WORKED OUT
B28: Dates: a project is Red once its Planned finish has passed while it's still Active or Paused. Otherwise a Latest forecast past the plan by more than your limit is Red, and a smaller slip is Amber.
B29: Money: spend over Budget by more than your limit is Red, and a smaller overrun is Amber. A program's spend is its projects' Forecast spend added up.
B30: Health is the worse of the two. A program with no Latest forecast uses the latest among its projects. Its colour never hides theirs: Projects inside counts its Red and Amber projects beside it.
A32: GREY COLUMNS
B33: Grey cells are worked out from what you type. Don't type over them: a typed value replaces the formula.
B34: Owner's current rows counts the Active and Paused rows that carry each owner's name, so you can see who's spread thin. It sets no limit.
A36: THE STARTER WORKBOOK
B37: A small team that wants fewer tabs can use the Starter workbook. Its Register columns A to L match this one, so rows paste across.
A39: ABOUT THIS EXAMPLE
B40: Wexbridge Quill Software is made up, and so is everyone in it.
B41: Four checks fail on purpose. Billing and Payments Program has no sponsor. Support Tooling Replacement sits under a program that isn't on the sheet, and Internal Wiki Cleanup is paused, so still current, outside the portfolio. The budgets add up to 30,000 USD more than the envelope. And the 15 Oct 2026 decision was recorded by the manager, where decisions are the director's to record.
B42: Support Tooling Replacement is a Sprint project, so its Health reads Not read. The other eight checks are clear. The dates are in 2026 and 2027, so the marks will change as time passes.

Sheet Portfolio
B1: Portfolio (Example)
A2: One portfolio per workbook. Type in the white cells; the grey ones are worked out.
A3: Example. Wexbridge Quill Software and everyone in it are made up. Clear the white cells to start your own.
A5: THE PORTFOLIO
A6: PORTFOLIO NAME | B6: Product and Platform | C6: What you call the work this workbook covers. Required.
A7: DIRECTOR | B7: Priya (CTO) | C7: The person accountable for the portfolio's direction and benefits. A name, with a role in brackets if you like. Required.
A8: MANAGER | B8: Tomasz (PMO Head) | C8: The person who runs it day to day and keeps the register. Can be the director. Required.
A9: STATUS | B9: Active | C9: Where the portfolio is in its life. Blank counts as Active. Reviews are checked only while it's Active.
A10: REVIEW CADENCE | B10: Quarterly | C10: How often the steering group reviews the portfolio. Leave blank if there isn't one.
A11: FIRST REVIEW | B11: 46037 | C11: The date of the first review, while no meeting is logged on Steering. Optional.
A12: LAST REVIEW | B12: =IF(COUNT(Steering!$G$6:$G$55)=0,"",MAX(Steering!$G$6:$G$55)) | C12: Worked out: the latest meeting date on Steering.
A13: NEXT REVIEW | B13: =IF($B$10="","No review date",IF($B$12<>"",IF($B$10="Monthly",EDATE($B$12,1),IF($B$10="Quarterly",EDATE($B$12,3),IF($B$10="Twice a year",EDATE($B$12,6),EDATE($B$12,12)))),IF($B$11<>"",$B$11,"No review date"))) | C13: Worked out: Last review plus the cadence, or First review until a meeting is logged.
A14: PEOPLE CHECK | B14: =IF(AND($B$7<>"",$B$8<>""),"○ Clear","△ "&IF(AND($B$7="",$B$8=""),"Director and manager not named",IF($B$7="","Director not named","Manager not named"))) | C14: Shows △ when the director or the manager isn't named.
A15: REVIEW CHECK | B15: =IF(OR($B$10="",AND($B$9<>"",$B$9<>"Active")),"○ Clear",IF($B$13="No review date","△ No review date",IF($B$13<TODAY(),"△ Review overdue since "&TEXT($B$13,"d mmm yyyy"),"○ Clear"))) | C15: Shows △ when the next review has passed, or a cadence is set with no review date.
A17: COUNTS BY HEALTH | C17: Programs and projects directly under Portfolio, one count each. A program's own projects are counted beside it on Register.
A18: ■ Red | B18: =COUNTIFS(Register!$C$6:$C$305,"Portfolio",Register!$M$6:$M$305,"■ Red")
A19: ◧ Amber | B19: =COUNTIFS(Register!$C$6:$C$305,"Portfolio",Register!$M$6:$M$305,"◧ Amber")
A20: □ On track | B20: =COUNTIFS(Register!$C$6:$C$305,"Portfolio",Register!$M$6:$M$305,"□ On track")
A21: Not read | B21: =COUNTIFS(Register!$C$6:$C$305,"Portfolio",Register!$M$6:$M$305,"Not read")
A22: CURRENT ROWS OUTSIDE THE PORTFOLIO | B22: =COUNTIFS(Register!$C$6:$C$305,"Outside the portfolio",Register!$Q$6:$Q$305,1) | C22: Active or Paused rows with Sits under set to Outside the portfolio. Left out of the counts above.
A24: CHECKS | B24: =Checks!$B$10 | C24: Every result is on the Checks tab.
A26: OBJECTIVES
A27: Objective | B27: Owner | C27: Measure and target | D27: Target date | E27: Linked rows
A28: Cut the time to bring on a new customer | B28: Priya (CTO) | C28: Days from signed order to first live use: 21 | D28: 46568 | E28: =IF($A28="","",COUNTIF(Register!$G$6:$G$305,$A28))
A29: Pass the annual audit with no major findings | B29: Imani (Security Lead) | C29: Major findings at audit: 0 | D29: 46444 | E29: =IF($A29="","",COUNTIF(Register!$G$6:$G$305,$A29))
A30: Move all billing to the new engine before renewals | B30: Hugo (Program Manager) | C30: Share of invoices from the new engine: 100% | D30: 46660 | E30: =IF($A30="","",COUNTIF(Register!$G$6:$G$305,$A30))
E31: =IF($A31="","",COUNTIF(Register!$G$6:$G$305,$A31))
E32: =IF($A32="","",COUNTIF(Register!$G$6:$G$305,$A32))
E33: =IF($A33="","",COUNTIF(Register!$G$6:$G$305,$A33))
E34: =IF($A34="","",COUNTIF(Register!$G$6:$G$305,$A34))
E35: =IF($A35="","",COUNTIF(Register!$G$6:$G$305,$A35))
E36: =IF($A36="","",COUNTIF(Register!$G$6:$G$305,$A36))
E37: =IF($A37="","",COUNTIF(Register!$G$6:$G$305,$A37))

Sheet Register
B1: Register (Example)
A2: =IF(Portfolio!$B$6="","","Portfolio: "&Portfolio!$B$6)
A3: Example. Wexbridge Quill Software and everyone in it are made up. Clear the white cells to start your own.
A5: Name | B5: Level | C5: Sits under | D5: Status | E5: Owner | F5: Sponsor | G5: Objective | H5: Planned finish | I5: Latest forecast | J5: Forecast spend | K5: Budget | L5: Variance note | M5: Health | N5: Projects inside | O5: Owner's current rows | P5: Check | Q5: Helper, worked out | R5: Helper, worked out | S5: Helper, worked out | T5: Helper, worked out | U5: Helper, worked out | V5: Helper, worked out | W5: Helper, worked out | X5: Helper, worked out | Y5: Helper, worked out | Z5: Helper, worked out | AA5: Helper, worked out | AB5: Helper, worked out | AC5: Helper, worked out | AD5: Helper, worked out | AE5: Helper, worked out | AF5: Approach | AG5: Helper, worked out | AH5: Helper, worked out | AI5: Helper, worked out
A6: Customer Platform Modernisation | B6: Program | C6: Portfolio | D6: Active | E6: Dara (Program Manager) | F6: Priya (CTO) | G6: Cut the time to bring on a new customer | H6: 46507 | K6: 1100000 | M6: =IF($A6="","",IF($D6="","Not read",IF($Q6=0,"Not counted",IF(MAX($X6,$Y6)=3,"■ Red",IF(MAX($X6,$Y6)=2,"◧ Amber",IF(MAX($X6,$Y6)=1,"□ On track","Not read")))))) | N6: =IF(OR($A6="",$B6<>"Program"),"","■ "&COUNTIFS($C$6:$C$305,$A6,$M$6:$M$305,"■ Red")&" Red, ◧ "&COUNTIFS($C$6:$C$305,$A6,$M$6:$M$305,"◧ Amber")&" Amber") | O6: =IF(OR($A6="",$E6=""),"",COUNTIFS($E$6:$E$305,$E6,$D$6:$D$305,"Active")+COUNTIFS($E$6:$E$305,$E6,$D$6:$D$305,"Paused")) | P6: =IF($A6="","",IF($AE6=0,"○ Clear",IF($AA6=1,"△ No owner",IF($AC6=1,"△ Check Sits under",IF($AC6=2,"△ Outside the portfolio",IF($AB6=1,"△ No sponsor",IF($AH6=1,"△ Name used twice",IF($AG6=1,"△ Budget only counts under Portfolio","△ No variance note"))))))&IF($AE6>1," (+"&($AE6-1)&" more)",""))) | Q6: =IF(AND($A6<>"",OR($D6="Active",$D6="Paused")),1,0) | R6: Portfolio | S6: =IF(AND($A6<>"",$B6="Program"),COUNTIFS($B$6:$B6,"Program",$A$6:$A6,"<>"),"") | T6: =IF(AND($A6<>"",$B6="Program"),SUMPRODUCT(MAX(($C$6:$C$305=$A6)*($B$6:$B$305="Project")*($D$6:$D$305<>"Proposed")*$I$6:$I$305)),0) | U6: =IF($I6<>"",$I6,IF($T6>0,$T6,"")) | V6: =IF(AND($A6<>"",$B6="Program"),SUMIFS($J$6:$J$305,$C$6:$C$305,$A6,$B$6:$B$305,"Project",$D$6:$D$305,"<>Proposed"),0) | W6: =IF(AND($A6<>"",$B6="Program"),COUNTIFS($C$6:$C$305,$A6,$B$6:$B$305,"Project",$D$6:$D$305,"<>Proposed")-COUNTIFS($C$6:$C$305,$A6,$B$6:$B$305,"Project",$D$6:$D$305,"<>Proposed",$J$6:$J$305,">=0"),0) | X6: =IF(OR($Q6=0,$H6="",$AF6="Sprint"),0,IF(AND($B6="Project",$H6<TODAY()),3,IF($U6="",0,IF($U6<=$H6,1,IF(NETWORKDAYS($H6,$U6)-1>IF($B6="Program",Checks!$B$7,Checks!$B$6),3,2))))) | Y6: =IF(OR($Q6=0,$K6="",$K6=0,$AF6="Sprint"),0,IF(AND($B6="Project",$J6=""),0,IF(IF($B6="Program",$V6,$J6)>$K6*(1+Checks!$B$8),3,IF(IF($B6="Program",$V6,$J6)>$K6,2,IF(AND($B6="Program",OR($W6>0,$V6=0)),0,1))))) | Z6: =IF($A6="",0,IF($C6="Portfolio",1,IF(AND($B6="Project",$C6<>"",$C6<>"Outside the portfolio"),IFERROR(IF(AND(INDEX($B$6:$B$305,MATCH($C6,$A$6:$A$305,0))="Program",INDEX($C$6:$C$305,MATCH($C6,$A$6:$A$305,0))="Portfolio"),1,0),0),0))) | AA6: =IF(AND($A6<>"",$E6="",OR($Q6=1,$D6="Proposed")),1,0) | AB6: =IF(AND($A6<>"",$B6="Program",$F6="",$Q6=1),1,0) | AC6: =IF(OR($A6="",$D6="Completed",$D6="Terminated"),0,IF($C6="",1,IF($C6="Portfolio",0,IF($C6="Outside the portfolio",IF($Q6=1,2,0),IF($B6="Project",IF(IFERROR(INDEX($B$6:$B$305,MATCH($C6,$A$6:$A$305,0)),"")="Program",0,1),1))))) | AD6: =IF(AND($A6<>"",OR($M6="■ Red",$M6="◧ Amber"),$L6=""),1,0) | AE6: =$AA6+$AB6+IF($AC6>0,1,0)+$AD6+$AG6+$AH6 | AG6: =IF(AND($A6<>"",$K6<>"",$C6<>"Portfolio",$D6<>"Completed",$D6<>"Terminated"),1,0) | AH6: =IF(AND($A6<>"",COUNTIF($A$6:$A$305,$A6)>1),1,0) | AI6: =IF(AND($A6<>"",$C6="Portfolio"),COUNTIFS($C$6:$C6,"Portfolio",$A$6:$A6,"<>"),"")
A7: Data Migration Wave 2 | B7: Project | C7: Customer Platform Modernisation | D7: Active | E7: Kofi (Delivery Lead) | G7: Cut the time to bring on a new customer | H7: 46444 | I7: 46458 | J7: 520000 | L7: Schema fix agreed with the vendor; the new date holds only if it lands by 5 Nov. Kofi | M7: =IF($A7="","",IF($D7="","Not read",IF($Q7=0,"Not counted",IF(MAX($X7,$Y7)=3,"■ Red",IF(MAX($X7,$Y7)=2,"◧ Amber",IF(MAX($X7,$Y7)=1,"□ On track","Not read")))))) | N7: =IF(OR($A7="",$B7<>"Program"),"","■ "&COUNTIFS($C$6:$C$305,$A7,$M$6:$M$305,"■ Red")&" Red, ◧ "&COUNTIFS($C$6:$C$305,$A7,$M$6:$M$305,"◧ Amber")&" Amber") | O7: =IF(OR($A7="",$E7=""),"",COUNTIFS($E$6:$E$305,$E7,$D$6:$D$305,"Active")+COUNTIFS($E$6:$E$305,$E7,$D$6:$D$305,"Paused")) | P7: =IF($A7="","",IF($AE7=0,"○ Clear",IF($AA7=1,"△ No owner",IF($AC7=1,"△ Check Sits under",IF($AC7=2,"△ Outside the portfolio",IF($AB7=1,"△ No sponsor",IF($AH7=1,"△ Name used twice",IF($AG7=1,"△ Budget only counts under Portfolio","△ No variance note"))))))&IF($AE7>1," (+"&($AE7-1)&" more)",""))) | Q7: =IF(AND($A7<>"",OR($D7="Active",$D7="Paused")),1,0) | R7: Outside the portfolio | S7: =IF(AND($A7<>"",$B7="Program"),COUNTIFS($B$6:$B7,"Program",$A$6:$A7,"<>"),"") | T7: =IF(AND($A7<>"",$B7="Program"),SUMPRODUCT(MAX(($C$6:$C$305=$A7)*($B$6:$B$305="Project")*($D$6:$D$305<>"Proposed")*$I$6:$I$305)),0) | U7: =IF($I7<>"",$I7,IF($T7>0,$T7,"")) | V7: =IF(AND($A7<>"",$B7="Program"),SUMIFS($J$6:$J$305,$C$6:$C$305,$A7,$B$6:$B$305,"Project",$D$6:$D$305,"<>Proposed"),0) | W7: =IF(AND($A7<>"",$B7="Program"),COUNTIFS($C$6:$C$305,$A7,$B$6:$B$305,"Project",$D$6:$D$305,"<>Proposed")-COUNTIFS($C$6:$C$305,$A7,$B$6:$B$305,"Project",$D$6:$D$305,"<>Proposed",$J$6:$J$305,">=0"),0) | X7: =IF(OR($Q7=0,$H7="",$AF7="Sprint"),0,IF(AND($B7="Project",$H7<TODAY()),3,IF($U7="",0,IF($U7<=$H7,1,IF(NETWORKDAYS($H7,$U7)-1>IF($B7="Program",Checks!$B$7,Checks!$B$6),3,2))))) | Y7: =IF(OR($Q7=0,$K7="",$K7=0,$AF7="Sprint"),0,IF(AND($B7="Project",$J7=""),0,IF(IF($B7="Program",$V7,$J7)>$K7*(1+Checks!$B$8),3,IF(IF($B7="Program",$V7,$J7)>$K7,2,IF(AND($B7="Program",OR($W7>0,$V7=0)),0,1))))) | Z7: =IF($A7="",0,IF($C7="Portfolio",1,IF(AND($B7="Project",$C7<>"",$C7<>"Outside the portfolio"),IFERROR(IF(AND(INDEX($B$6:$B$305,MATCH($C7,$A$6:$A$305,0))="Program",INDEX($C$6:$C$305,MATCH($C7,$A$6:$A$305,0))="Portfolio"),1,0),0),0))) | AA7: =IF(AND($A7<>"",$E7="",OR($Q7=1,$D7="Proposed")),1,0) | AB7: =IF(AND($A7<>"",$B7="Program",$F7="",$Q7=1),1,0) | AC7: =IF(OR($A7="",$D7="Completed",$D7="Terminated"),0,IF($C7="",1,IF($C7="Portfolio",0,IF($C7="Outside the portfolio",IF($Q7=1,2,0),IF($B7="Project",IF(IFERROR(INDEX($B$6:$B$305,MATCH($C7,$A$6:$A$305,0)),"")="Program",0,1),1))))) | AD7: =IF(AND($A7<>"",OR($M7="■ Red",$M7="◧ Amber"),$L7=""),1,0) | AE7: =$AA7+$AB7+IF($AC7>0,1,0)+$AD7+$AG7+$AH7 | AF7: Waterfall | AG7: =IF(AND($A7<>"",$K7<>"",$C7<>"Portfolio",$D7<>"Completed",$D7<>"Terminated"),1,0) | AH7: =IF(AND($A7<>"",COUNTIF($A$6:$A$305,$A7)>1),1,0) | AI7: =IF(AND($A7<>"",$C7="Portfolio"),COUNTIFS($C$6:$C7,"Portfolio",$A$6:$A7,"<>"),"")
A8: Billing and Payments Program | B8: Program | C8: Portfolio | D8: Active | E8: Hugo (Program Manager) | G8: Move all billing to the new engine before renewals | H8: 46568 | K8: 900000 | M8: =IF($A8="","",IF($D8="","Not read",IF($Q8=0,"Not counted",IF(MAX($X8,$Y8)=3,"■ Red",IF(MAX($X8,$Y8)=2,"◧ Amber",IF(MAX($X8,$Y8)=1,"□ On track","Not read")))))) | N8: =IF(OR($A8="",$B8<>"Program"),"","■ "&COUNTIFS($C$6:$C$305,$A8,$M$6:$M$305,"■ Red")&" Red, ◧ "&COUNTIFS($C$6:$C$305,$A8,$M$6:$M$305,"◧ Amber")&" Amber") | O8: =IF(OR($A8="",$E8=""),"",COUNTIFS($E$6:$E$305,$E8,$D$6:$D$305,"Active")+COUNTIFS($E$6:$E$305,$E8,$D$6:$D$305,"Paused")) | P8: =IF($A8="","",IF($AE8=0,"○ Clear",IF($AA8=1,"△ No owner",IF($AC8=1,"△ Check Sits under",IF($AC8=2,"△ Outside the portfolio",IF($AB8=1,"△ No sponsor",IF($AH8=1,"△ Name used twice",IF($AG8=1,"△ Budget only counts under Portfolio","△ No variance note"))))))&IF($AE8>1," (+"&($AE8-1)&" more)",""))) | Q8: =IF(AND($A8<>"",OR($D8="Active",$D8="Paused")),1,0) | R8: =IFERROR(INDEX($A$6:$A$305,MATCH(1,$S$6:$S$305,0)),"") | S8: =IF(AND($A8<>"",$B8="Program"),COUNTIFS($B$6:$B8,"Program",$A$6:$A8,"<>"),"") | T8: =IF(AND($A8<>"",$B8="Program"),SUMPRODUCT(MAX(($C$6:$C$305=$A8)*($B$6:$B$305="Project")*($D$6:$D$305<>"Proposed")*$I$6:$I$305)),0) | U8: =IF($I8<>"",$I8,IF($T8>0,$T8,"")) | V8: =IF(AND($A8<>"",$B8="Program"),SUMIFS($J$6:$J$305,$C$6:$C$305,$A8,$B$6:$B$305,"Project",$D$6:$D$305,"<>Proposed"),0) | W8: =IF(AND($A8<>"",$B8="Program"),COUNTIFS($C$6:$C$305,$A8,$B$6:$B$305,"Project",$D$6:$D$305,"<>Proposed")-COUNTIFS($C$6:$C$305,$A8,$B$6:$B$305,"Project",$D$6:$D$305,"<>Proposed",$J$6:$J$305,">=0"),0) | X8: =IF(OR($Q8=0,$H8="",$AF8="Sprint"),0,IF(AND($B8="Project",$H8<TODAY()),3,IF($U8="",0,IF($U8<=$H8,1,IF(NETWORKDAYS($H8,$U8)-1>IF($B8="Program",Checks!$B$7,Checks!$B$6),3,2))))) | Y8: =IF(OR($Q8=0,$K8="",$K8=0,$AF8="Sprint"),0,IF(AND($B8="Project",$J8=""),0,IF(IF($B8="Program",$V8,$J8)>$K8*(1+Checks!$B$8),3,IF(IF($B8="Program",$V8,$J8)>$K8,2,IF(AND($B8="Program",OR($W8>0,$V8=0)),0,1))))) | Z8: =IF($A8="",0,IF($C8="Portfolio",1,IF(AND($B8="Project",$C8<>"",$C8<>"Outside the portfolio"),IFERROR(IF(AND(INDEX($B$6:$B$305,MATCH($C8,$A$6:$A$305,0))="Program",INDEX($C$6:$C$305,MATCH($C8,$A$6:$A$305,0))="Portfolio"),1,0),0),0))) | AA8: =IF(AND($A8<>"",$E8="",OR($Q8=1,$D8="Proposed")),1,0) | AB8: =IF(AND($A8<>"",$B8="Program",$F8="",$Q8=1),1,0) | AC8: =IF(OR($A8="",$D8="Completed",$D8="Terminated"),0,IF($C8="",1,IF($C8="Portfolio",0,IF($C8="Outside the portfolio",IF($Q8=1,2,0),IF($B8="Project",IF(IFERROR(INDEX($B$6:$B$305,MATCH($C8,$A$6:$A$305,0)),"")="Program",0,1),1))))) | AD8: =IF(AND($A8<>"",OR($M8="■ Red",$M8="◧ Amber"),$L8=""),1,0) | AE8: =$AA8+$AB8+IF($AC8>0,1,0)+$AD8+$AG8+$AH8 | AG8: =IF(AND($A8<>"",$K8<>"",$C8<>"Portfolio",$D8<>"Completed",$D8<>"Terminated"),1,0) | AH8: =IF(AND($A8<>"",COUNTIF($A$6:$A$305,$A8)>1),1,0) | AI8: =IF(AND($A8<>"",$C8="Portfolio"),COUNTIFS($C$6:$C8,"Portfolio",$A$6:$A8,"<>"),"")
A9: Billing Engine Rewrite | B9: Project | C9: Billing and Payments Program | D9: Active | E9: Anders (Engineering Manager) | G9: Move all billing to the new engine before renewals | H9: 46568 | I9: 46568 | J9: 780000 | M9: =IF($A9="","",IF($D9="","Not read",IF($Q9=0,"Not counted",IF(MAX($X9,$Y9)=3,"■ Red",IF(MAX($X9,$Y9)=2,"◧ Amber",IF(MAX($X9,$Y9)=1,"□ On track","Not read")))))) | N9: =IF(OR($A9="",$B9<>"Program"),"","■ "&COUNTIFS($C$6:$C$305,$A9,$M$6:$M$305,"■ Red")&" Red, ◧ "&COUNTIFS($C$6:$C$305,$A9,$M$6:$M$305,"◧ Amber")&" Amber") | O9: =IF(OR($A9="",$E9=""),"",COUNTIFS($E$6:$E$305,$E9,$D$6:$D$305,"Active")+COUNTIFS($E$6:$E$305,$E9,$D$6:$D$305,"Paused")) | P9: =IF($A9="","",IF($AE9=0,"○ Clear",IF($AA9=1,"△ No owner",IF($AC9=1,"△ Check Sits under",IF($AC9=2,"△ Outside the portfolio",IF($AB9=1,"△ No sponsor",IF($AH9=1,"△ Name used twice",IF($AG9=1,"△ Budget only counts under Portfolio","△ No variance note"))))))&IF($AE9>1," (+"&($AE9-1)&" more)",""))) | Q9: =IF(AND($A9<>"",OR($D9="Active",$D9="Paused")),1,0) | R9: =IFERROR(INDEX($A$6:$A$305,MATCH(2,$S$6:$S$305,0)),"") | S9: =IF(AND($A9<>"",$B9="Program"),COUNTIFS($B$6:$B9,"Program",$A$6:$A9,"<>"),"") | T9: =IF(AND($A9<>"",$B9="Program"),SUMPRODUCT(MAX(($C$6:$C$305=$A9)*($B$6:$B$305="Project")*($D$6:$D$305<>"Proposed")*$I$6:$I$305)),0) | U9: =IF($I9<>"",$I9,IF($T9>0,$T9,"")) | V9: =IF(AND($A9<>"",$B9="Program"),SUMIFS($J$6:$J$305,$C$6:$C$305,$A9,$B$6:$B$305,"Project",$D$6:$D$305,"<>Proposed"),0) | W9: =IF(AND($A9<>"",$B9="Program"),COUNTIFS($C$6:$C$305,$A9,$B$6:$B$305,"Project",$D$6:$D$305,"<>Proposed")-COUNTIFS($C$6:$C$305,$A9,$B$6:$B$305,"Project",$D$6:$D$305,"<>Proposed",$J$6:$J$305,">=0"),0) | X9: =IF(OR($Q9=0,$H9="",$AF9="Sprint"),0,IF(AND($B9="Project",$H9<TODAY()),3,IF($U9="",0,IF($U9<=$H9,1,IF(NETWORKDAYS($H9,$U9)-1>IF($B9="Program",Checks!$B$7,Checks!$B$6),3,2))))) | Y9: =IF(OR($Q9=0,$K9="",$K9=0,$AF9="Sprint"),0,IF(AND($B9="Project",$J9=""),0,IF(IF($B9="Program",$V9,$J9)>$K9*(1+Checks!$B$8),3,IF(IF($B9="Program",$V9,$J9)>$K9,2,IF(AND($B9="Program",OR($W9>0,$V9=0)),0,1))))) | Z9: =IF($A9="",0,IF($C9="Portfolio",1,IF(AND($B9="Project",$C9<>"",$C9<>"Outside the portfolio"),IFERROR(IF(AND(INDEX($B$6:$B$305,MATCH($C9,$A$6:$A$305,0))="Program",INDEX($C$6:$C$305,MATCH($C9,$A$6:$A$305,0))="Portfolio"),1,0),0),0))) | AA9: =IF(AND($A9<>"",$E9="",OR($Q9=1,$D9="Proposed")),1,0) | AB9: =IF(AND($A9<>"",$B9="Program",$F9="",$Q9=1),1,0) | AC9: =IF(OR($A9="",$D9="Completed",$D9="Terminated"),0,IF($C9="",1,IF($C9="Portfolio",0,IF($C9="Outside the portfolio",IF($Q9=1,2,0),IF($B9="Project",IF(IFERROR(INDEX($B$6:$B$305,MATCH($C9,$A$6:$A$305,0)),"")="Program",0,1),1))))) | AD9: =IF(AND($A9<>"",OR($M9="■ Red",$M9="◧ Amber"),$L9=""),1,0) | AE9: =$AA9+$AB9+IF($AC9>0,1,0)+$AD9+$AG9+$AH9 | AF9: Waterfall | AG9: =IF(AND($A9<>"",$K9<>"",$C9<>"Portfolio",$D9<>"Completed",$D9<>"Terminated"),1,0) | AH9: =IF(AND($A9<>"",COUNTIF($A$6:$A$305,$A9)>1),1,0) | AI9: =IF(AND($A9<>"",$C9="Portfolio"),COUNTIFS($C$6:$C9,"Portfolio",$A$6:$A9,"<>"),"")
A10: Invoice Tax Rules | B10: Project | C10: Billing and Payments Program | D10: Proposed | E10: Hugo (Program Manager) | M10: =IF($A10="","",IF($D10="","Not read",IF($Q10=0,"Not counted",IF(MAX($X10,$Y10)=3,"■ Red",IF(MAX($X10,$Y10)=2,"◧ Amber",IF(MAX($X10,$Y10)=1,"□ On track","Not read")))))) | N10: =IF(OR($A10="",$B10<>"Program"),"","■ "&COUNTIFS($C$6:$C$305,$A10,$M$6:$M$305,"■ Red")&" Red, ◧ "&COUNTIFS($C$6:$C$305,$A10,$M$6:$M$305,"◧ Amber")&" Amber") | O10: =IF(OR($A10="",$E10=""),"",COUNTIFS($E$6:$E$305,$E10,$D$6:$D$305,"Active")+COUNTIFS($E$6:$E$305,$E10,$D$6:$D$305,"Paused")) | P10: =IF($A10="","",IF($AE10=0,"○ Clear",IF($AA10=1,"△ No owner",IF($AC10=1,"△ Check Sits under",IF($AC10=2,"△ Outside the portfolio",IF($AB10=1,"△ No sponsor",IF($AH10=1,"△ Name used twice",IF($AG10=1,"△ Budget only counts under Portfolio","△ No variance note"))))))&IF($AE10>1," (+"&($AE10-1)&" more)",""))) | Q10: =IF(AND($A10<>"",OR($D10="Active",$D10="Paused")),1,0) | R10: =IFERROR(INDEX($A$6:$A$305,MATCH(3,$S$6:$S$305,0)),"") | S10: =IF(AND($A10<>"",$B10="Program"),COUNTIFS($B$6:$B10,"Program",$A$6:$A10,"<>"),"") | T10: =IF(AND($A10<>"",$B10="Program"),SUMPRODUCT(MAX(($C$6:$C$305=$A10)*($B$6:$B$305="Project")*($D$6:$D$305<>"Proposed")*$I$6:$I$305)),0) | U10: =IF($I10<>"",$I10,IF($T10>0,$T10,"")) | V10: =IF(AND($A10<>"",$B10="Program"),SUMIFS($J$6:$J$305,$C$6:$C$305,$A10,$B$6:$B$305,"Project",$D$6:$D$305,"<>Proposed"),0) | W10: =IF(AND($A10<>"",$B10="Program"),COUNTIFS($C$6:$C$305,$A10,$B$6:$B$305,"Project",$D$6:$D$305,"<>Proposed")-COUNTIFS($C$6:$C$305,$A10,$B$6:$B$305,"Project",$D$6:$D$305,"<>Proposed",$J$6:$J$305,">=0"),0) | X10: =IF(OR($Q10=0,$H10="",$AF10="Sprint"),0,IF(AND($B10="Project",$H10<TODAY()),3,IF($U10="",0,IF($U10<=$H10,1,IF(NETWORKDAYS($H10,$U10)-1>IF($B10="Program",Checks!$B$7,Checks!$B$6),3,2))))) | Y10: =IF(OR($Q10=0,$K10="",$K10=0,$AF10="Sprint"),0,IF(AND($B10="Project",$J10=""),0,IF(IF($B10="Program",$V10,$J10)>$K10*(1+Checks!$B$8),3,IF(IF($B10="Program",$V10,$J10)>$K10,2,IF(AND($B10="Program",OR($W10>0,$V10=0)),0,1))))) | Z10: =IF($A10="",0,IF($C10="Portfolio",1,IF(AND($B10="Project",$C10<>"",$C10<>"Outside the portfolio"),IFERROR(IF(AND(INDEX($B$6:$B$305,MATCH($C10,$A$6:$A$305,0))="Program",INDEX($C$6:$C$305,MATCH($C10,$A$6:$A$305,0))="Portfolio"),1,0),0),0))) | AA10: =IF(AND($A10<>"",$E10="",OR($Q10=1,$D10="Proposed")),1,0) | AB10: =IF(AND($A10<>"",$B10="Program",$F10="",$Q10=1),1,0) | AC10: =IF(OR($A10="",$D10="Completed",$D10="Terminated"),0,IF($C10="",1,IF($C10="Portfolio",0,IF($C10="Outside the portfolio",IF($Q10=1,2,0),IF($B10="Project",IF(IFERROR(INDEX($B$6:$B$305,MATCH($C10,$A$6:$A$305,0)),"")="Program",0,1),1))))) | AD10: =IF(AND($A10<>"",OR($M10="■ Red",$M10="◧ Amber"),$L10=""),1,0) | AE10: =$AA10+$AB10+IF($AC10>0,1,0)+$AD10+$AG10+$AH10 | AF10: Waterfall | AG10: =IF(AND($A10<>"",$K10<>"",$C10<>"Portfolio",$D10<>"Completed",$D10<>"Terminated"),1,0) | AH10: =IF(AND($A10<>"",COUNTIF($A$6:$A$305,$A10)>1),1,0) | AI10: =IF(AND($A10<>"",$C10="Portfolio"),COUNTIFS($C$6:$C10,"Portfolio",$A$6:$A10,"<>"),"")
A11: Security and Compliance Program | B11: Program | C11: Portfolio | D11: Active | E11: Imani (Security Lead) | F11: Priya (CTO) | G11: Pass the annual audit with no major findings | H11: 46416 | K11: 350000 | M11: =IF($A11="","",IF($D11="","Not read",IF($Q11=0,"Not counted",IF(MAX($X11,$Y11)=3,"■ Red",IF(MAX($X11,$Y11)=2,"◧ Amber",IF(MAX($X11,$Y11)=1,"□ On track","Not read")))))) | N11: =IF(OR($A11="",$B11<>"Program"),"","■ "&COUNTIFS($C$6:$C$305,$A11,$M$6:$M$305,"■ Red")&" Red, ◧ "&COUNTIFS($C$6:$C$305,$A11,$M$6:$M$305,"◧ Amber")&" Amber") | O11: =IF(OR($A11="",$E11=""),"",COUNTIFS($E$6:$E$305,$E11,$D$6:$D$305,"Active")+COUNTIFS($E$6:$E$305,$E11,$D$6:$D$305,"Paused")) | P11: =IF($A11="","",IF($AE11=0,"○ Clear",IF($AA11=1,"△ No owner",IF($AC11=1,"△ Check Sits under",IF($AC11=2,"△ Outside the portfolio",IF($AB11=1,"△ No sponsor",IF($AH11=1,"△ Name used twice",IF($AG11=1,"△ Budget only counts under Portfolio","△ No variance note"))))))&IF($AE11>1," (+"&($AE11-1)&" more)",""))) | Q11: =IF(AND($A11<>"",OR($D11="Active",$D11="Paused")),1,0) | R11: =IFERROR(INDEX($A$6:$A$305,MATCH(4,$S$6:$S$305,0)),"") | S11: =IF(AND($A11<>"",$B11="Program"),COUNTIFS($B$6:$B11,"Program",$A$6:$A11,"<>"),"") | T11: =IF(AND($A11<>"",$B11="Program"),SUMPRODUCT(MAX(($C$6:$C$305=$A11)*($B$6:$B$305="Project")*($D$6:$D$305<>"Proposed")*$I$6:$I$305)),0) | U11: =IF($I11<>"",$I11,IF($T11>0,$T11,"")) | V11: =IF(AND($A11<>"",$B11="Program"),SUMIFS($J$6:$J$305,$C$6:$C$305,$A11,$B$6:$B$305,"Project",$D$6:$D$305,"<>Proposed"),0) | W11: =IF(AND($A11<>"",$B11="Program"),COUNTIFS($C$6:$C$305,$A11,$B$6:$B$305,"Project",$D$6:$D$305,"<>Proposed")-COUNTIFS($C$6:$C$305,$A11,$B$6:$B$305,"Project",$D$6:$D$305,"<>Proposed",$J$6:$J$305,">=0"),0) | X11: =IF(OR($Q11=0,$H11="",$AF11="Sprint"),0,IF(AND($B11="Project",$H11<TODAY()),3,IF($U11="",0,IF($U11<=$H11,1,IF(NETWORKDAYS($H11,$U11)-1>IF($B11="Program",Checks!$B$7,Checks!$B$6),3,2))))) | Y11: =IF(OR($Q11=0,$K11="",$K11=0,$AF11="Sprint"),0,IF(AND($B11="Project",$J11=""),0,IF(IF($B11="Program",$V11,$J11)>$K11*(1+Checks!$B$8),3,IF(IF($B11="Program",$V11,$J11)>$K11,2,IF(AND($B11="Program",OR($W11>0,$V11=0)),0,1))))) | Z11: =IF($A11="",0,IF($C11="Portfolio",1,IF(AND($B11="Project",$C11<>"",$C11<>"Outside the portfolio"),IFERROR(IF(AND(INDEX($B$6:$B$305,MATCH($C11,$A$6:$A$305,0))="Program",INDEX($C$6:$C$305,MATCH($C11,$A$6:$A$305,0))="Portfolio"),1,0),0),0))) | AA11: =IF(AND($A11<>"",$E11="",OR($Q11=1,$D11="Proposed")),1,0) | AB11: =IF(AND($A11<>"",$B11="Program",$F11="",$Q11=1),1,0) | AC11: =IF(OR($A11="",$D11="Completed",$D11="Terminated"),0,IF($C11="",1,IF($C11="Portfolio",0,IF($C11="Outside the portfolio",IF($Q11=1,2,0),IF($B11="Project",IF(IFERROR(INDEX($B$6:$B$305,MATCH($C11,$A$6:$A$305,0)),"")="Program",0,1),1))))) | AD11: =IF(AND($A11<>"",OR($M11="■ Red",$M11="◧ Amber"),$L11=""),1,0) | AE11: =$AA11+$AB11+IF($AC11>0,1,0)+$AD11+$AG11+$AH11 | AG11: =IF(AND($A11<>"",$K11<>"",$C11<>"Portfolio",$D11<>"Completed",$D11<>"Terminated"),1,0) | AH11: =IF(AND($A11<>"",COUNTIF($A$6:$A$305,$A11)>1),1,0) | AI11: =IF(AND($A11<>"",$C11="Portfolio"),COUNTIFS($C$6:$C11,"Portfolio",$A$6:$A11,"<>"),"")
A12: Penetration Test Remediation | B12: Project | C12: Security and Compliance Program | D12: Active | E12: Imani (Security Lead) | G12: Pass the annual audit with no major findings | H12: 46304 | I12: 46325 | J12: 40000 | L12: Two criticals closed; the third needs a vendor patch. Imani | M12: =IF($A12="","",IF($D12="","Not read",IF($Q12=0,"Not counted",IF(MAX($X12,$Y12)=3,"■ Red",IF(MAX($X12,$Y12)=2,"◧ Amber",IF(MAX($X12,$Y12)=1,"□ On track","Not read")))))) | N12: =IF(OR($A12="",$B12<>"Program"),"","■ "&COUNTIFS($C$6:$C$305,$A12,$M$6:$M$305,"■ Red")&" Red, ◧ "&COUNTIFS($C$6:$C$305,$A12,$M$6:$M$305,"◧ Amber")&" Amber") | O12: =IF(OR($A12="",$E12=""),"",COUNTIFS($E$6:$E$305,$E12,$D$6:$D$305,"Active")+COUNTIFS($E$6:$E$305,$E12,$D$6:$D$305,"Paused")) | P12: =IF($A12="","",IF($AE12=0,"○ Clear",IF($AA12=1,"△ No owner",IF($AC12=1,"△ Check Sits under",IF($AC12=2,"△ Outside the portfolio",IF($AB12=1,"△ No sponsor",IF($AH12=1,"△ Name used twice",IF($AG12=1,"△ Budget only counts under Portfolio","△ No variance note"))))))&IF($AE12>1," (+"&($AE12-1)&" more)",""))) | Q12: =IF(AND($A12<>"",OR($D12="Active",$D12="Paused")),1,0) | R12: =IFERROR(INDEX($A$6:$A$305,MATCH(5,$S$6:$S$305,0)),"") | S12: =IF(AND($A12<>"",$B12="Program"),COUNTIFS($B$6:$B12,"Program",$A$6:$A12,"<>"),"") | T12: =IF(AND($A12<>"",$B12="Program"),SUMPRODUCT(MAX(($C$6:$C$305=$A12)*($B$6:$B$305="Project")*($D$6:$D$305<>"Proposed")*$I$6:$I$305)),0) | U12: =IF($I12<>"",$I12,IF($T12>0,$T12,"")) | V12: =IF(AND($A12<>"",$B12="Program"),SUMIFS($J$6:$J$305,$C$6:$C$305,$A12,$B$6:$B$305,"Project",$D$6:$D$305,"<>Proposed"),0) | W12: =IF(AND($A12<>"",$B12="Program"),COUNTIFS($C$6:$C$305,$A12,$B$6:$B$305,"Project",$D$6:$D$305,"<>Proposed")-COUNTIFS($C$6:$C$305,$A12,$B$6:$B$305,"Project",$D$6:$D$305,"<>Proposed",$J$6:$J$305,">=0"),0) | X12: =IF(OR($Q12=0,$H12="",$AF12="Sprint"),0,IF(AND($B12="Project",$H12<TODAY()),3,IF($U12="",0,IF($U12<=$H12,1,IF(NETWORKDAYS($H12,$U12)-1>IF($B12="Program",Checks!$B$7,Checks!$B$6),3,2))))) | Y12: =IF(OR($Q12=0,$K12="",$K12=0,$AF12="Sprint"),0,IF(AND($B12="Project",$J12=""),0,IF(IF($B12="Program",$V12,$J12)>$K12*(1+Checks!$B$8),3,IF(IF($B12="Program",$V12,$J12)>$K12,2,IF(AND($B12="Program",OR($W12>0,$V12=0)),0,1))))) | Z12: =IF($A12="",0,IF($C12="Portfolio",1,IF(AND($B12="Project",$C12<>"",$C12<>"Outside the portfolio"),IFERROR(IF(AND(INDEX($B$6:$B$305,MATCH($C12,$A$6:$A$305,0))="Program",INDEX($C$6:$C$305,MATCH($C12,$A$6:$A$305,0))="Portfolio"),1,0),0),0))) | AA12: =IF(AND($A12<>"",$E12="",OR($Q12=1,$D12="Proposed")),1,0) | AB12: =IF(AND($A12<>"",$B12="Program",$F12="",$Q12=1),1,0) | AC12: =IF(OR($A12="",$D12="Completed",$D12="Terminated"),0,IF($C12="",1,IF($C12="Portfolio",0,IF($C12="Outside the portfolio",IF($Q12=1,2,0),IF($B12="Project",IF(IFERROR(INDEX($B$6:$B$305,MATCH($C12,$A$6:$A$305,0)),"")="Program",0,1),1))))) | AD12: =IF(AND($A12<>"",OR($M12="■ Red",$M12="◧ Amber"),$L12=""),1,0) | AE12: =$AA12+$AB12+IF($AC12>0,1,0)+$AD12+$AG12+$AH12 | AF12: Waterfall | AG12: =IF(AND($A12<>"",$K12<>"",$C12<>"Portfolio",$D12<>"Completed",$D12<>"Terminated"),1,0) | AH12: =IF(AND($A12<>"",COUNTIF($A$6:$A$305,$A12)>1),1,0) | AI12: =IF(AND($A12<>"",$C12="Portfolio"),COUNTIFS($C$6:$C12,"Portfolio",$A$6:$A12,"<>"),"")
A13: Laptop Encryption Rollout | B13: Project | C13: Security and Compliance Program | D13: Active | E13: Imani (Security Lead) | H13: 46367 | I13: 46372 | J13: 120000 | L13: Last two offices wait on courier delivery. Imani | M13: =IF($A13="","",IF($D13="","Not read",IF($Q13=0,"Not counted",IF(MAX($X13,$Y13)=3,"■ Red",IF(MAX($X13,$Y13)=2,"◧ Amber",IF(MAX($X13,$Y13)=1,"□ On track","Not read")))))) | N13: =IF(OR($A13="",$B13<>"Program"),"","■ "&COUNTIFS($C$6:$C$305,$A13,$M$6:$M$305,"■ Red")&" Red, ◧ "&COUNTIFS($C$6:$C$305,$A13,$M$6:$M$305,"◧ Amber")&" Amber") | O13: =IF(OR($A13="",$E13=""),"",COUNTIFS($E$6:$E$305,$E13,$D$6:$D$305,"Active")+COUNTIFS($E$6:$E$305,$E13,$D$6:$D$305,"Paused")) | P13: =IF($A13="","",IF($AE13=0,"○ Clear",IF($AA13=1,"△ No owner",IF($AC13=1,"△ Check Sits under",IF($AC13=2,"△ Outside the portfolio",IF($AB13=1,"△ No sponsor",IF($AH13=1,"△ Name used twice",IF($AG13=1,"△ Budget only counts under Portfolio","△ No variance note"))))))&IF($AE13>1," (+"&($AE13-1)&" more)",""))) | Q13: =IF(AND($A13<>"",OR($D13="Active",$D13="Paused")),1,0) | R13: =IFERROR(INDEX($A$6:$A$305,MATCH(6,$S$6:$S$305,0)),"") | S13: =IF(AND($A13<>"",$B13="Program"),COUNTIFS($B$6:$B13,"Program",$A$6:$A13,"<>"),"") | T13: =IF(AND($A13<>"",$B13="Program"),SUMPRODUCT(MAX(($C$6:$C$305=$A13)*($B$6:$B$305="Project")*($D$6:$D$305<>"Proposed")*$I$6:$I$305)),0) | U13: =IF($I13<>"",$I13,IF($T13>0,$T13,"")) | V13: =IF(AND($A13<>"",$B13="Program"),SUMIFS($J$6:$J$305,$C$6:$C$305,$A13,$B$6:$B$305,"Project",$D$6:$D$305,"<>Proposed"),0) | W13: =IF(AND($A13<>"",$B13="Program"),COUNTIFS($C$6:$C$305,$A13,$B$6:$B$305,"Project",$D$6:$D$305,"<>Proposed")-COUNTIFS($C$6:$C$305,$A13,$B$6:$B$305,"Project",$D$6:$D$305,"<>Proposed",$J$6:$J$305,">=0"),0) | X13: =IF(OR($Q13=0,$H13="",$AF13="Sprint"),0,IF(AND($B13="Project",$H13<TODAY()),3,IF($U13="",0,IF($U13<=$H13,1,IF(NETWORKDAYS($H13,$U13)-1>IF($B13="Program",Checks!$B$7,Checks!$B$6),3,2))))) | Y13: =IF(OR($Q13=0,$K13="",$K13=0,$AF13="Sprint"),0,IF(AND($B13="Project",$J13=""),0,IF(IF($B13="Program",$V13,$J13)>$K13*(1+Checks!$B$8),3,IF(IF($B13="Program",$V13,$J13)>$K13,2,IF(AND($B13="Program",OR($W13>0,$V13=0)),0,1))))) | Z13: =IF($A13="",0,IF($C13="Portfolio",1,IF(AND($B13="Project",$C13<>"",$C13<>"Outside the portfolio"),IFERROR(IF(AND(INDEX($B$6:$B$305,MATCH($C13,$A$6:$A$305,0))="Program",INDEX($C$6:$C$305,MATCH($C13,$A$6:$A$305,0))="Portfolio"),1,0),0),0))) | AA13: =IF(AND($A13<>"",$E13="",OR($Q13=1,$D13="Proposed")),1,0) | AB13: =IF(AND($A13<>"",$B13="Program",$F13="",$Q13=1),1,0) | AC13: =IF(OR($A13="",$D13="Completed",$D13="Terminated"),0,IF($C13="",1,IF($C13="Portfolio",0,IF($C13="Outside the portfolio",IF($Q13=1,2,0),IF($B13="Project",IF(IFERROR(INDEX($B$6:$B$305,MATCH($C13,$A$6:$A$305,0)),"")="Program",0,1),1))))) | AD13: =IF(AND($A13<>"",OR($M13="■ Red",$M13="◧ Amber"),$L13=""),1,0) | AE13: =$AA13+$AB13+IF($AC13>0,1,0)+$AD13+$AG13+$AH13 | AF13: Waterfall | AG13: =IF(AND($A13<>"",$K13<>"",$C13<>"Portfolio",$D13<>"Completed",$D13<>"Terminated"),1,0) | AH13: =IF(AND($A13<>"",COUNTIF($A$6:$A$305,$A13)>1),1,0) | AI13: =IF(AND($A13<>"",$C13="Portfolio"),COUNTIFS($C$6:$C13,"Portfolio",$A$6:$A13,"<>"),"")
A14: Partner Portal Launch | B14: Project | C14: Portfolio | D14: Active | E14: Mei (Product Manager) | H14: 46507 | I14: 46507 | J14: 85000 | K14: 80000 | L14: Contract testers cost more than planned; still within 10 percent. Mei | M14: =IF($A14="","",IF($D14="","Not read",IF($Q14=0,"Not counted",IF(MAX($X14,$Y14)=3,"■ Red",IF(MAX($X14,$Y14)=2,"◧ Amber",IF(MAX($X14,$Y14)=1,"□ On track","Not read")))))) | N14: =IF(OR($A14="",$B14<>"Program"),"","■ "&COUNTIFS($C$6:$C$305,$A14,$M$6:$M$305,"■ Red")&" Red, ◧ "&COUNTIFS($C$6:$C$305,$A14,$M$6:$M$305,"◧ Amber")&" Amber") | O14: =IF(OR($A14="",$E14=""),"",COUNTIFS($E$6:$E$305,$E14,$D$6:$D$305,"Active")+COUNTIFS($E$6:$E$305,$E14,$D$6:$D$305,"Paused")) | P14: =IF($A14="","",IF($AE14=0,"○ Clear",IF($AA14=1,"△ No owner",IF($AC14=1,"△ Check Sits under",IF($AC14=2,"△ Outside the portfolio",IF($AB14=1,"△ No sponsor",IF($AH14=1,"△ Name used twice",IF($AG14=1,"△ Budget only counts under Portfolio","△ No variance note"))))))&IF($AE14>1," (+"&($AE14-1)&" more)",""))) | Q14: =IF(AND($A14<>"",OR($D14="Active",$D14="Paused")),1,0) | R14: =IFERROR(INDEX($A$6:$A$305,MATCH(7,$S$6:$S$305,0)),"") | S14: =IF(AND($A14<>"",$B14="Program"),COUNTIFS($B$6:$B14,"Program",$A$6:$A14,"<>"),"") | T14: =IF(AND($A14<>"",$B14="Program"),SUMPRODUCT(MAX(($C$6:$C$305=$A14)*($B$6:$B$305="Project")*($D$6:$D$305<>"Proposed")*$I$6:$I$305)),0) | U14: =IF($I14<>"",$I14,IF($T14>0,$T14,"")) | V14: =IF(AND($A14<>"",$B14="Program"),SUMIFS($J$6:$J$305,$C$6:$C$305,$A14,$B$6:$B$305,"Project",$D$6:$D$305,"<>Proposed"),0) | W14: =IF(AND($A14<>"",$B14="Program"),COUNTIFS($C$6:$C$305,$A14,$B$6:$B$305,"Project",$D$6:$D$305,"<>Proposed")-COUNTIFS($C$6:$C$305,$A14,$B$6:$B$305,"Project",$D$6:$D$305,"<>Proposed",$J$6:$J$305,">=0"),0) | X14: =IF(OR($Q14=0,$H14="",$AF14="Sprint"),0,IF(AND($B14="Project",$H14<TODAY()),3,IF($U14="",0,IF($U14<=$H14,1,IF(NETWORKDAYS($H14,$U14)-1>IF($B14="Program",Checks!$B$7,Checks!$B$6),3,2))))) | Y14: =IF(OR($Q14=0,$K14="",$K14=0,$AF14="Sprint"),0,IF(AND($B14="Project",$J14=""),0,IF(IF($B14="Program",$V14,$J14)>$K14*(1+Checks!$B$8),3,IF(IF($B14="Program",$V14,$J14)>$K14,2,IF(AND($B14="Program",OR($W14>0,$V14=0)),0,1))))) | Z14: =IF($A14="",0,IF($C14="Portfolio",1,IF(AND($B14="Project",$C14<>"",$C14<>"Outside the portfolio"),IFERROR(IF(AND(INDEX($B$6:$B$305,MATCH($C14,$A$6:$A$305,0))="Program",INDEX($C$6:$C$305,MATCH($C14,$A$6:$A$305,0))="Portfolio"),1,0),0),0))) | AA14: =IF(AND($A14<>"",$E14="",OR($Q14=1,$D14="Proposed")),1,0) | AB14: =IF(AND($A14<>"",$B14="Program",$F14="",$Q14=1),1,0) | AC14: =IF(OR($A14="",$D14="Completed",$D14="Terminated"),0,IF($C14="",1,IF($C14="Portfolio",0,IF($C14="Outside the portfolio",IF($Q14=1,2,0),IF($B14="Project",IF(IFERROR(INDEX($B$6:$B$305,MATCH($C14,$A$6:$A$305,0)),"")="Program",0,1),1))))) | AD14: =IF(AND($A14<>"",OR($M14="■ Red",$M14="◧ Amber"),$L14=""),1,0) | AE14: =$AA14+$AB14+IF($AC14>0,1,0)+$AD14+$AG14+$AH14 | AF14: Waterfall | AG14: =IF(AND($A14<>"",$K14<>"",$C14<>"Portfolio",$D14<>"Completed",$D14<>"Terminated"),1,0) | AH14: =IF(AND($A14<>"",COUNTIF($A$6:$A$305,$A14)>1),1,0) | AI14: =IF(AND($A14<>"",$C14="Portfolio"),COUNTIFS($C$6:$C14,"Portfolio",$A$6:$A14,"<>"),"")
A15: Support Tooling Replacement | B15: Project | C15: Support Ops Program | D15: Active | E15: Noor (Support Lead) | H15: 46430 | I15: 46430 | J15: 70000 | M15: =IF($A15="","",IF($D15="","Not read",IF($Q15=0,"Not counted",IF(MAX($X15,$Y15)=3,"■ Red",IF(MAX($X15,$Y15)=2,"◧ Amber",IF(MAX($X15,$Y15)=1,"□ On track","Not read")))))) | N15: =IF(OR($A15="",$B15<>"Program"),"","■ "&COUNTIFS($C$6:$C$305,$A15,$M$6:$M$305,"■ Red")&" Red, ◧ "&COUNTIFS($C$6:$C$305,$A15,$M$6:$M$305,"◧ Amber")&" Amber") | O15: =IF(OR($A15="",$E15=""),"",COUNTIFS($E$6:$E$305,$E15,$D$6:$D$305,"Active")+COUNTIFS($E$6:$E$305,$E15,$D$6:$D$305,"Paused")) | P15: =IF($A15="","",IF($AE15=0,"○ Clear",IF($AA15=1,"△ No owner",IF($AC15=1,"△ Check Sits under",IF($AC15=2,"△ Outside the portfolio",IF($AB15=1,"△ No sponsor",IF($AH15=1,"△ Name used twice",IF($AG15=1,"△ Budget only counts under Portfolio","△ No variance note"))))))&IF($AE15>1," (+"&($AE15-1)&" more)",""))) | Q15: =IF(AND($A15<>"",OR($D15="Active",$D15="Paused")),1,0) | R15: =IFERROR(INDEX($A$6:$A$305,MATCH(8,$S$6:$S$305,0)),"") | S15: =IF(AND($A15<>"",$B15="Program"),COUNTIFS($B$6:$B15,"Program",$A$6:$A15,"<>"),"") | T15: =IF(AND($A15<>"",$B15="Program"),SUMPRODUCT(MAX(($C$6:$C$305=$A15)*($B$6:$B$305="Project")*($D$6:$D$305<>"Proposed")*$I$6:$I$305)),0) | U15: =IF($I15<>"",$I15,IF($T15>0,$T15,"")) | V15: =IF(AND($A15<>"",$B15="Program"),SUMIFS($J$6:$J$305,$C$6:$C$305,$A15,$B$6:$B$305,"Project",$D$6:$D$305,"<>Proposed"),0) | W15: =IF(AND($A15<>"",$B15="Program"),COUNTIFS($C$6:$C$305,$A15,$B$6:$B$305,"Project",$D$6:$D$305,"<>Proposed")-COUNTIFS($C$6:$C$305,$A15,$B$6:$B$305,"Project",$D$6:$D$305,"<>Proposed",$J$6:$J$305,">=0"),0) | X15: =IF(OR($Q15=0,$H15="",$AF15="Sprint"),0,IF(AND($B15="Project",$H15<TODAY()),3,IF($U15="",0,IF($U15<=$H15,1,IF(NETWORKDAYS($H15,$U15)-1>IF($B15="Program",Checks!$B$7,Checks!$B$6),3,2))))) | Y15: =IF(OR($Q15=0,$K15="",$K15=0,$AF15="Sprint"),0,IF(AND($B15="Project",$J15=""),0,IF(IF($B15="Program",$V15,$J15)>$K15*(1+Checks!$B$8),3,IF(IF($B15="Program",$V15,$J15)>$K15,2,IF(AND($B15="Program",OR($W15>0,$V15=0)),0,1))))) | Z15: =IF($A15="",0,IF($C15="Portfolio",1,IF(AND($B15="Project",$C15<>"",$C15<>"Outside the portfolio"),IFERROR(IF(AND(INDEX($B$6:$B$305,MATCH($C15,$A$6:$A$305,0))="Program",INDEX($C$6:$C$305,MATCH($C15,$A$6:$A$305,0))="Portfolio"),1,0),0),0))) | AA15: =IF(AND($A15<>"",$E15="",OR($Q15=1,$D15="Proposed")),1,0) | AB15: =IF(AND($A15<>"",$B15="Program",$F15="",$Q15=1),1,0) | AC15: =IF(OR($A15="",$D15="Completed",$D15="Terminated"),0,IF($C15="",1,IF($C15="Portfolio",0,IF($C15="Outside the portfolio",IF($Q15=1,2,0),IF($B15="Project",IF(IFERROR(INDEX($B$6:$B$305,MATCH($C15,$A$6:$A$305,0)),"")="Program",0,1),1))))) | AD15: =IF(AND($A15<>"",OR($M15="■ Red",$M15="◧ Amber"),$L15=""),1,0) | AE15: =$AA15+$AB15+IF($AC15>0,1,0)+$AD15+$AG15+$AH15 | AF15: Sprint | AG15: =IF(AND($A15<>"",$K15<>"",$C15<>"Portfolio",$D15<>"Completed",$D15<>"Terminated"),1,0) | AH15: =IF(AND($A15<>"",COUNTIF($A$6:$A$305,$A15)>1),1,0) | AI15: =IF(AND($A15<>"",$C15="Portfolio"),COUNTIFS($C$6:$C15,"Portfolio",$A$6:$A15,"<>"),"")
A16: Internal Wiki Cleanup | B16: Project | C16: Outside the portfolio | D16: Paused | E16: Noor (Support Lead) | M16: =IF($A16="","",IF($D16="","Not read",IF($Q16=0,"Not counted",IF(MAX($X16,$Y16)=3,"■ Red",IF(MAX($X16,$Y16)=2,"◧ Amber",IF(MAX($X16,$Y16)=1,"□ On track","Not read")))))) | N16: =IF(OR($A16="",$B16<>"Program"),"","■ "&COUNTIFS($C$6:$C$305,$A16,$M$6:$M$305,"■ Red")&" Red, ◧ "&COUNTIFS($C$6:$C$305,$A16,$M$6:$M$305,"◧ Amber")&" Amber") | O16: =IF(OR($A16="",$E16=""),"",COUNTIFS($E$6:$E$305,$E16,$D$6:$D$305,"Active")+COUNTIFS($E$6:$E$305,$E16,$D$6:$D$305,"Paused")) | P16: =IF($A16="","",IF($AE16=0,"○ Clear",IF($AA16=1,"△ No owner",IF($AC16=1,"△ Check Sits under",IF($AC16=2,"△ Outside the portfolio",IF($AB16=1,"△ No sponsor",IF($AH16=1,"△ Name used twice",IF($AG16=1,"△ Budget only counts under Portfolio","△ No variance note"))))))&IF($AE16>1," (+"&($AE16-1)&" more)",""))) | Q16: =IF(AND($A16<>"",OR($D16="Active",$D16="Paused")),1,0) | R16: =IFERROR(INDEX($A$6:$A$305,MATCH(9,$S$6:$S$305,0)),"") | S16: =IF(AND($A16<>"",$B16="Program"),COUNTIFS($B$6:$B16,"Program",$A$6:$A16,"<>"),"") | T16: =IF(AND($A16<>"",$B16="Program"),SUMPRODUCT(MAX(($C$6:$C$305=$A16)*($B$6:$B$305="Project")*($D$6:$D$305<>"Proposed")*$I$6:$I$305)),0) | U16: =IF($I16<>"",$I16,IF($T16>0,$T16,"")) | V16: =IF(AND($A16<>"",$B16="Program"),SUMIFS($J$6:$J$305,$C$6:$C$305,$A16,$B$6:$B$305,"Project",$D$6:$D$305,"<>Proposed"),0) | W16: =IF(AND($A16<>"",$B16="Program"),COUNTIFS($C$6:$C$305,$A16,$B$6:$B$305,"Project",$D$6:$D$305,"<>Proposed")-COUNTIFS($C$6:$C$305,$A16,$B$6:$B$305,"Project",$D$6:$D$305,"<>Proposed",$J$6:$J$305,">=0"),0) | X16: =IF(OR($Q16=0,$H16="",$AF16="Sprint"),0,IF(AND($B16="Project",$H16<TODAY()),3,IF($U16="",0,IF($U16<=$H16,1,IF(NETWORKDAYS($H16,$U16)-1>IF($B16="Program",Checks!$B$7,Checks!$B$6),3,2))))) | Y16: =IF(OR($Q16=0,$K16="",$K16=0,$AF16="Sprint"),0,IF(AND($B16="Project",$J16=""),0,IF(IF($B16="Program",$V16,$J16)>$K16*(1+Checks!$B$8),3,IF(IF($B16="Program",$V16,$J16)>$K16,2,IF(AND($B16="Program",OR($W16>0,$V16=0)),0,1))))) | Z16: =IF($A16="",0,IF($C16="Portfolio",1,IF(AND($B16="Project",$C16<>"",$C16<>"Outside the portfolio"),IFERROR(IF(AND(INDEX($B$6:$B$305,MATCH($C16,$A$6:$A$305,0))="Program",INDEX($C$6:$C$305,MATCH($C16,$A$6:$A$305,0))="Portfolio"),1,0),0),0))) | AA16: =IF(AND($A16<>"",$E16="",OR($Q16=1,$D16="Proposed")),1,0) | AB16: =IF(AND($A16<>"",$B16="Program",$F16="",$Q16=1),1,0) | AC16: =IF(OR($A16="",$D16="Completed",$D16="Terminated"),0,IF($C16="",1,IF($C16="Portfolio",0,IF($C16="Outside the portfolio",IF($Q16=1,2,0),IF($B16="Project",IF(IFERROR(INDEX($B$6:$B$305,MATCH($C16,$A$6:$A$305,0)),"")="Program",0,1),1))))) | AD16: =IF(AND($A16<>"",OR($M16="■ Red",$M16="◧ Amber"),$L16=""),1,0) | AE16: =$AA16+$AB16+IF($AC16>0,1,0)+$AD16+$AG16+$AH16 | AF16: Waterfall | AG16: =IF(AND($A16<>"",$K16<>"",$C16<>"Portfolio",$D16<>"Completed",$D16<>"Terminated"),1,0) | AH16: =IF(AND($A16<>"",COUNTIF($A$6:$A$305,$A16)>1),1,0) | AI16: =IF(AND($A16<>"",$C16="Portfolio"),COUNTIFS($C$6:$C16,"Portfolio",$A$6:$A16,"<>"),"")
M17: =IF($A17="","",IF($D17="","Not read",IF($Q17=0,"Not counted",IF(MAX($X17,$Y17)=3,"■ Red",IF(MAX($X17,$Y17)=2,"◧ Amber",IF(MAX($X17,$Y17)=1,"□ On track","Not read")))))) | N17: =IF(OR($A17="",$B17<>"Program"),"","■ "&COUNTIFS($C$6:$C$305,$A17,$M$6:$M$305,"■ Red")&" Red, ◧ "&COUNTIFS($C$6:$C$305,$A17,$M$6:$M$305,"◧ Amber")&" Amber") | O17: =IF(OR($A17="",$E17=""),"",COUNTIFS($E$6:$E$305,$E17,$D$6:$D$305,"Active")+COUNTIFS($E$6:$E$305,$E17,$D$6:$D$305,"Paused")) | P17: =IF($A17="","",IF($AE17=0,"○ Clear",IF($AA17=1,"△ No owner",IF($AC17=1,"△ Check Sits under",IF($AC17=2,"△ Outside the portfolio",IF($AB17=1,"△ No sponsor",IF($AH17=1,"△ Name used twice",IF($AG17=1,"△ Budget only counts under Portfolio","△ No variance note"))))))&IF($AE17>1," (+"&($AE17-1)&" more)",""))) | Q17: =IF(AND($A17<>"",OR($D17="Active",$D17="Paused")),1,0) | R17: =IFERROR(INDEX($A$6:$A$305,MATCH(10,$S$6:$S$305,0)),"") | S17: =IF(AND($A17<>"",$B17="Program"),COUNTIFS($B$6:$B17,"Program",$A$6:$A17,"<>"),"") | T17: =IF(AND($A17<>"",$B17="Program"),SUMPRODUCT(MAX(($C$6:$C$305=$A17)*($B$6:$B$305="Project")*($D$6:$D$305<>"Proposed")*$I$6:$I$305)),0) | U17: =IF($I17<>"",$I17,IF($T17>0,$T17,"")) | V17: =IF(AND($A17<>"",$B17="Program"),SUMIFS($J$6:$J$305,$C$6:$C$305,$A17,$B$6:$B$305,"Project",$D$6:$D$305,"<>Proposed"),0) | W17: =IF(AND($A17<>"",$B17="Program"),COUNTIFS($C$6:$C$305,$A17,$B$6:$B$305,"Project",$D$6:$D$305,"<>Proposed")-COUNTIFS($C$6:$C$305,$A17,$B$6:$B$305,"Project",$D$6:$D$305,"<>Proposed",$J$6:$J$305,">=0"),0) | X17: =IF(OR($Q17=0,$H17="",$AF17="Sprint"),0,IF(AND($B17="Project",$H17<TODAY()),3,IF($U17="",0,IF($U17<=$H17,1,IF(NETWORKDAYS($H17,$U17)-1>IF($B17="Program",Checks!$B$7,Checks!$B$6),3,2))))) | Y17: =IF(OR($Q17=0,$K17="",$K17=0,$AF17="Sprint"),0,IF(AND($B17="Project",$J17=""),0,IF(IF($B17="Program",$V17,$J17)>$K17*(1+Checks!$B$8),3,IF(IF($B17="Program",$V17,$J17)>$K17,2,IF(AND($B17="Program",OR($W17>0,$V17=0)),0,1))))) | Z17: =IF($A17="",0,IF($C17="Portfolio",1,IF(AND($B17="Project",$C17<>"",$C17<>"Outside the portfolio"),IFERROR(IF(AND(INDEX($B$6:$B$305,MATCH($C17,$A$6:$A$305,0))="Program",INDEX($C$6:$C$305,MATCH($C17,$A$6:$A$305,0))="Portfolio"),1,0),0),0))) | AA17: =IF(AND($A17<>"",$E17="",OR($Q17=1,$D17="Proposed")),1,0) | AB17: =IF(AND($A17<>"",$B17="Program",$F17="",$Q17=1),1,0) | AC17: =IF(OR($A17="",$D17="Completed",$D17="Terminated"),0,IF($C17="",1,IF($C17="Portfolio",0,IF($C17="Outside the portfolio",IF($Q17=1,2,0),IF($B17="Project",IF(IFERROR(INDEX($B$6:$B$305,MATCH($C17,$A$6:$A$305,0)),"")="Program",0,1),1))))) | AD17: =IF(AND($A17<>"",OR($M17="■ Red",$M17="◧ Amber"),$L17=""),1,0) | AE17: =$AA17+$AB17+IF($AC17>0,1,0)+$AD17+$AG17+$AH17 | AG17: =IF(AND($A17<>"",$K17<>"",$C17<>"Portfolio",$D17<>"Completed",$D17<>"Terminated"),1,0) | AH17: =IF(AND($A17<>"",COUNTIF($A$6:$A$305,$A17)>1),1,0) | AI17: =IF(AND($A17<>"",$C17="Portfolio"),COUNTIFS($C$6:$C17,"Portfolio",$A$6:$A17,"<>"),"")
M18: =IF($A18="","",IF($D18="","Not read",IF($Q18=0,"Not counted",IF(MAX($X18,$Y18)=3,"■ Red",IF(MAX($X18,$Y18)=2,"◧ Amber",IF(MAX($X18,$Y18)=1,"□ On track","Not read")))))) | N18: =IF(OR($A18="",$B18<>"Program"),"","■ "&COUNTIFS($C$6:$C$305,$A18,$M$6:$M$305,"■ Red")&" Red, ◧ "&COUNTIFS($C$6:$C$305,$A18,$M$6:$M$305,"◧ Amber")&" Amber") | O18: =IF(OR($A18="",$E18=""),"",COUNTIFS($E$6:$E$305,$E18,$D$6:$D$305,"Active")+COUNTIFS($E$6:$E$305,$E18,$D$6:$D$305,"Paused")) | P18: =IF($A18="","",IF($AE18=0,"○ Clear",IF($AA18=1,"△ No owner",IF($AC18=1,"△ Check Sits under",IF($AC18=2,"△ Outside the portfolio",IF($AB18=1,"△ No sponsor",IF($AH18=1,"△ Name used twice",IF($AG18=1,"△ Budget only counts under Portfolio","△ No variance note"))))))&IF($AE18>1," (+"&($AE18-1)&" more)",""))) | Q18: =IF(AND($A18<>"",OR($D18="Active",$D18="Paused")),1,0) | R18: =IFERROR(INDEX($A$6:$A$305,MATCH(11,$S$6:$S$305,0)),"") | S18: =IF(AND($A18<>"",$B18="Program"),COUNTIFS($B$6:$B18,"Program",$A$6:$A18,"<>"),"") | T18: =IF(AND($A18<>"",$B18="Program"),SUMPRODUCT(MAX(($C$6:$C$305=$A18)*($B$6:$B$305="Project")*($D$6:$D$305<>"Proposed")*$I$6:$I$305)),0) | U18: =IF($I18<>"",$I18,IF($T18>0,$T18,"")) | V18: =IF(AND($A18<>"",$B18="Program"),SUMIFS($J$6:$J$305,$C$6:$C$305,$A18,$B$6:$B$305,"Project",$D$6:$D$305,"<>Proposed"),0) | W18: =IF(AND($A18<>"",$B18="Program"),COUNTIFS($C$6:$C$305,$A18,$B$6:$B$305,"Project",$D$6:$D$305,"<>Proposed")-COUNTIFS($C$6:$C$305,$A18,$B$6:$B$305,"Project",$D$6:$D$305,"<>Proposed",$J$6:$J$305,">=0"),0) | X18: =IF(OR($Q18=0,$H18="",$AF18="Sprint"),0,IF(AND($B18="Project",$H18<TODAY()),3,IF($U18="",0,IF($U18<=$H18,1,IF(NETWORKDAYS($H18,$U18)-1>IF($B18="Program",Checks!$B$7,Checks!$B$6),3,2))))) | Y18: =IF(OR($Q18=0,$K18="",$K18=0,$AF18="Sprint"),0,IF(AND($B18="Project",$J18=""),0,IF(IF($B18="Program",$V18,$J18)>$K18*(1+Checks!$B$8),3,IF(IF($B18="Program",$V18,$J18)>$K18,2,IF(AND($B18="Program",OR($W18>0,$V18=0)),0,1))))) | Z18: =IF($A18="",0,IF($C18="Portfolio",1,IF(AND($B18="Project",$C18<>"",$C18<>"Outside the portfolio"),IFERROR(IF(AND(INDEX($B$6:$B$305,MATCH($C18,$A$6:$A$305,0))="Program",INDEX($C$6:$C$305,MATCH($C18,$A$6:$A$305,0))="Portfolio"),1,0),0),0))) | AA18: =IF(AND($A18<>"",$E18="",OR($Q18=1,$D18="Proposed")),1,0) | AB18: =IF(AND($A18<>"",$B18="Program",$F18="",$Q18=1),1,0) | AC18: =IF(OR($A18="",$D18="Completed",$D18="Terminated"),0,IF($C18="",1,IF($C18="Portfolio",0,IF($C18="Outside the portfolio",IF($Q18=1,2,0),IF($B18="Project",IF(IFERROR(INDEX($B$6:$B$305,MATCH($C18,$A$6:$A$305,0)),"")="Program",0,1),1))))) | AD18: =IF(AND($A18<>"",OR($M18="■ Red",$M18="◧ Amber"),$L18=""),1,0) | AE18: =$AA18+$AB18+IF($AC18>0,1,0)+$AD18+$AG18+$AH18 | AG18: =IF(AND($A18<>"",$K18<>"",$C18<>"Portfolio",$D18<>"Completed",$D18<>"Terminated"),1,0) | AH18: =IF(AND($A18<>"",COUNTIF($A$6:$A$305,$A18)>1),1,0) | AI18: =IF(AND($A18<>"",$C18="Portfolio"),COUNTIFS($C$6:$C18,"Portfolio",$A$6:$A18,"<>"),"")
M19: =IF($A19="","",IF($D19="","Not read",IF($Q19=0,"Not counted",IF(MAX($X19,$Y19)=3,"■ Red",IF(MAX($X19,$Y19)=2,"◧ Amber",IF(MAX($X19,$Y19)=1,"□ On track","Not read")))))) | N19: =IF(OR($A19="",$B19<>"Program"),"","■ "&COUNTIFS($C$6:$C$305,$A19,$M$6:$M$305,"■ Red")&" Red, ◧ "&COUNTIFS($C$6:$C$305,$A19,$M$6:$M$305,"◧ Amber")&" Amber") | O19: =IF(OR($A19="",$E19=""),"",COUNTIFS($E$6:$E$305,$E19,$D$6:$D$305,"Active")+COUNTIFS($E$6:$E$305,$E19,$D$6:$D$305,"Paused")) | P19: =IF($A19="","",IF($AE19=0,"○ Clear",IF($AA19=1,"△ No owner",IF($AC19=1,"△ Check Sits under",IF($AC19=2,"△ Outside the portfolio",IF($AB19=1,"△ No sponsor",IF($AH19=1,"△ Name used twice",IF($AG19=1,"△ Budget only counts under Portfolio","△ No variance note"))))))&IF($AE19>1," (+"&($AE19-1)&" more)",""))) | Q19: =IF(AND($A19<>"",OR($D19="Active",$D19="Paused")),1,0) | R19: =IFERROR(INDEX($A$6:$A$305,MATCH(12,$S$6:$S$305,0)),"") | S19: =IF(AND($A19<>"",$B19="Program"),COUNTIFS($B$6:$B19,"Program",$A$6:$A19,"<>"),"") | T19: =IF(AND($A19<>"",$B19="Program"),SUMPRODUCT(MAX(($C$6:$C$305=$A19)*($B$6:$B$305="Project")*($D$6:$D$305<>"Proposed")*$I$6:$I$305)),0) | U19: =IF($I19<>"",$I19,IF($T19>0,$T19,"")) | V19: =IF(AND($A19<>"",$B19="Program"),SUMIFS($J$6:$J$305,$C$6:$C$305,$A19,$B$6:$B$305,"Project",$D$6:$D$305,"<>Proposed"),0) | W19: =IF(AND($A19<>"",$B19="Program"),COUNTIFS($C$6:$C$305,$A19,$B$6:$B$305,"Project",$D$6:$D$305,"<>Proposed")-COUNTIFS($C$6:$C$305,$A19,$B$6:$B$305,"Project",$D$6:$D$305,"<>Proposed",$J$6:$J$305,">=0"),0) | X19: =IF(OR($Q19=0,$H19="",$AF19="Sprint"),0,IF(AND($B19="Project",$H19<TODAY()),3,IF($U19="",0,IF($U19<=$H19,1,IF(NETWORKDAYS($H19,$U19)-1>IF($B19="Program",Checks!$B$7,Checks!$B$6),3,2))))) | Y19: =IF(OR($Q19=0,$K19="",$K19=0,$AF19="Sprint"),0,IF(AND($B19="Project",$J19=""),0,IF(IF($B19="Program",$V19,$J19)>$K19*(1+Checks!$B$8),3,IF(IF($B19="Program",$V19,$J19)>$K19,2,IF(AND($B19="Program",OR($W19>0,$V19=0)),0,1))))) | Z19: =IF($A19="",0,IF($C19="Portfolio",1,IF(AND($B19="Project",$C19<>"",$C19<>"Outside the portfolio"),IFERROR(IF(AND(INDEX($B$6:$B$305,MATCH($C19,$A$6:$A$305,0))="Program",INDEX($C$6:$C$305,MATCH($C19,$A$6:$A$305,0))="Portfolio"),1,0),0),0))) | AA19: =IF(AND($A19<>"",$E19="",OR($Q19=1,$D19="Proposed")),1,0) | AB19: =IF(AND($A19<>"",$B19="Program",$F19="",$Q19=1),1,0) | AC19: =IF(OR($A19="",$D19="Completed",$D19="Terminated"),0,IF($C19="",1,IF($C19="Portfolio",0,IF($C19="Outside the portfolio",IF($Q19=1,2,0),IF($B19="Project",IF(IFERROR(INDEX($B$6:$B$305,MATCH($C19,$A$6:$A$305,0)),"")="Program",0,1),1))))) | AD19: =IF(AND($A19<>"",OR($M19="■ Red",$M19="◧ Amber"),$L19=""),1,0) | AE19: =$AA19+$AB19+IF($AC19>0,1,0)+$AD19+$AG19+$AH19 | AG19: =IF(AND($A19<>"",$K19<>"",$C19<>"Portfolio",$D19<>"Completed",$D19<>"Terminated"),1,0) | AH19: =IF(AND($A19<>"",COUNTIF($A$6:$A$305,$A19)>1),1,0) | AI19: =IF(AND($A19<>"",$C19="Portfolio"),COUNTIFS($C$6:$C19,"Portfolio",$A$6:$A19,"<>"),"")
M20: =IF($A20="","",IF($D20="","Not read",IF($Q20=0,"Not counted",IF(MAX($X20,$Y20)=3,"■ Red",IF(MAX($X20,$Y20)=2,"◧ Amber",IF(MAX($X20,$Y20)=1,"□ On track","Not read")))))) | N20: =IF(OR($A20="",$B20<>"Program"),"","■ "&COUNTIFS($C$6:$C$305,$A20,$M$6:$M$305,"■ Red")&" Red, ◧ "&COUNTIFS($C$6:$C$305,$A20,$M$6:$M$305,"◧ Amber")&" Amber") | O20: =IF(OR($A20="",$E20=""),"",COUNTIFS($E$6:$E$305,$E20,$D$6:$D$305,"Active")+COUNTIFS($E$6:$E$305,$E20,$D$6:$D$305,"Paused")) | P20: =IF($A20="","",IF($AE20=0,"○ Clear",IF($AA20=1,"△ No owner",IF($AC20=1,"△ Check Sits under",IF($AC20=2,"△ Outside the portfolio",IF($AB20=1,"△ No sponsor",IF($AH20=1,"△ Name used twice",IF($AG20=1,"△ Budget only counts under Portfolio","△ No variance note"))))))&IF($AE20>1," (+"&($AE20-1)&" more)",""))) | Q20: =IF(AND($A20<>"",OR($D20="Active",$D20="Paused")),1,0) | R20: =IFERROR(INDEX($A$6:$A$305,MATCH(13,$S$6:$S$305,0)),"") | S20: =IF(AND($A20<>"",$B20="Program"),COUNTIFS($B$6:$B20,"Program",$A$6:$A20,"<>"),"") | T20: =IF(AND($A20<>"",$B20="Program"),SUMPRODUCT(MAX(($C$6:$C$305=$A20)*($B$6:$B$305="Project")*($D$6:$D$305<>"Proposed")*$I$6:$I$305)),0) | U20: =IF($I20<>"",$I20,IF($T20>0,$T20,"")) | V20: =IF(AND($A20<>"",$B20="Program"),SUMIFS($J$6:$J$305,$C$6:$C$305,$A20,$B$6:$B$305,"Project",$D$6:$D$305,"<>Proposed"),0) | W20: =IF(AND($A20<>"",$B20="Program"),COUNTIFS($C$6:$C$305,$A20,$B$6:$B$305,"Project",$D$6:$D$305,"<>Proposed")-COUNTIFS($C$6:$C$305,$A20,$B$6:$B$305,"Project",$D$6:$D$305,"<>Proposed",$J$6:$J$305,">=0"),0) | X20: =IF(OR($Q20=0,$H20="",$AF20="Sprint"),0,IF(AND($B20="Project",$H20<TODAY()),3,IF($U20="",0,IF($U20<=$H20,1,IF(NETWORKDAYS($H20,$U20)-1>IF($B20="Program",Checks!$B$7,Checks!$B$6),3,2))))) | Y20: =IF(OR($Q20=0,$K20="",$K20=0,$AF20="Sprint"),0,IF(AND($B20="Project",$J20=""),0,IF(IF($B20="Program",$V20,$J20)>$K20*(1+Checks!$B$8),3,IF(IF($B20="Program",$V20,$J20)>$K20,2,IF(AND($B20="Program",OR($W20>0,$V20=0)),0,1))))) | Z20: =IF($A20="",0,IF($C20="Portfolio",1,IF(AND($B20="Project",$C20<>"",$C20<>"Outside the portfolio"),IFERROR(IF(AND(INDEX($B$6:$B$305,MATCH($C20,$A$6:$A$305,0))="Program",INDEX($C$6:$C$305,MATCH($C20,$A$6:$A$305,0))="Portfolio"),1,0),0),0))) | AA20: =IF(AND($A20<>"",$E20="",OR($Q20=1,$D20="Proposed")),1,0) | AB20: =IF(AND($A20<>"",$B20="Program",$F20="",$Q20=1),1,0) | AC20: =IF(OR($A20="",$D20="Completed",$D20="Terminated"),0,IF($C20="",1,IF($C20="Portfolio",0,IF($C20="Outside the portfolio",IF($Q20=1,2,0),IF($B20="Project",IF(IFERROR(INDEX($B$6:$B$305,MATCH($C20,$A$6:$A$305,0)),"")="Program",0,1),1))))) | AD20: =IF(AND($A20<>"",OR($M20="■ Red",$M20="◧ Amber"),$L20=""),1,0) | AE20: =$AA20+$AB20+IF($AC20>0,1,0)+$AD20+$AG20+$AH20 | AG20: =IF(AND($A20<>"",$K20<>"",$C20<>"Portfolio",$D20<>"Completed",$D20<>"Terminated"),1,0) | AH20: =IF(AND($A20<>"",COUNTIF($A$6:$A$305,$A20)>1),1,0) | AI20: =IF(AND($A20<>"",$C20="Portfolio"),COUNTIFS($C$6:$C20,"Portfolio",$A$6:$A20,"<>"),"")
M21: =IF($A21="","",IF($D21="","Not read",IF($Q21=0,"Not counted",IF(MAX($X21,$Y21)=3,"■ Red",IF(MAX($X21,$Y21)=2,"◧ Amber",IF(MAX($X21,$Y21)=1,"□ On track","Not read")))))) | N21: =IF(OR($A21="",$B21<>"Program"),"","■ "&COUNTIFS($C$6:$C$305,$A21,$M$6:$M$305,"■ Red")&" Red, ◧ "&COUNTIFS($C$6:$C$305,$A21,$M$6:$M$305,"◧ Amber")&" Amber") | O21: =IF(OR($A21="",$E21=""),"",COUNTIFS($E$6:$E$305,$E21,$D$6:$D$305,"Active")+COUNTIFS($E$6:$E$305,$E21,$D$6:$D$305,"Paused")) | P21: =IF($A21="","",IF($AE21=0,"○ Clear",IF($AA21=1,"△ No owner",IF($AC21=1,"△ Check Sits under",IF($AC21=2,"△ Outside the portfolio",IF($AB21=1,"△ No sponsor",IF($AH21=1,"△ Name used twice",IF($AG21=1,"△ Budget only counts under Portfolio","△ No variance note"))))))&IF($AE21>1," (+"&($AE21-1)&" more)",""))) | Q21: =IF(AND($A21<>"",OR($D21="Active",$D21="Paused")),1,0) | R21: =IFERROR(INDEX($A$6:$A$305,MATCH(14,$S$6:$S$305,0)),"") | S21: =IF(AND($A21<>"",$B21="Program"),COUNTIFS($B$6:$B21,"Program",$A$6:$A21,"<>"),"") | T21: =IF(AND($A21<>"",$B21="Program"),SUMPRODUCT(MAX(($C$6:$C$305=$A21)*($B$6:$B$305="Project")*($D$6:$D$305<>"Proposed")*$I$6:$I$305)),0) | U21: =IF($I21<>"",$I21,IF($T21>0,$T21,"")) | V21: =IF(AND($A21<>"",$B21="Program"),SUMIFS($J$6:$J$305,$C$6:$C$305,$A21,$B$6:$B$305,"Project",$D$6:$D$305,"<>Proposed"),0) | W21: =IF(AND($A21<>"",$B21="Program"),COUNTIFS($C$6:$C$305,$A21,$B$6:$B$305,"Project",$D$6:$D$305,"<>Proposed")-COUNTIFS($C$6:$C$305,$A21,$B$6:$B$305,"Project",$D$6:$D$305,"<>Proposed",$J$6:$J$305,">=0"),0) | X21: =IF(OR($Q21=0,$H21="",$AF21="Sprint"),0,IF(AND($B21="Project",$H21<TODAY()),3,IF($U21="",0,IF($U21<=$H21,1,IF(NETWORKDAYS($H21,$U21)-1>IF($B21="Program",Checks!$B$7,Checks!$B$6),3,2))))) | Y21: =IF(OR($Q21=0,$K21="",$K21=0,$AF21="Sprint"),0,IF(AND($B21="Project",$J21=""),0,IF(IF($B21="Program",$V21,$J21)>$K21*(1+Checks!$B$8),3,IF(IF($B21="Program",$V21,$J21)>$K21,2,IF(AND($B21="Program",OR($W21>0,$V21=0)),0,1))))) | Z21: =IF($A21="",0,IF($C21="Portfolio",1,IF(AND($B21="Project",$C21<>"",$C21<>"Outside the portfolio"),IFERROR(IF(AND(INDEX($B$6:$B$305,MATCH($C21,$A$6:$A$305,0))="Program",INDEX($C$6:$C$305,MATCH($C21,$A$6:$A$305,0))="Portfolio"),1,0),0),0))) | AA21: =IF(AND($A21<>"",$E21="",OR($Q21=1,$D21="Proposed")),1,0) | AB21: =IF(AND($A21<>"",$B21="Program",$F21="",$Q21=1),1,0) | AC21: =IF(OR($A21="",$D21="Completed",$D21="Terminated"),0,IF($C21="",1,IF($C21="Portfolio",0,IF($C21="Outside the portfolio",IF($Q21=1,2,0),IF($B21="Project",IF(IFERROR(INDEX($B$6:$B$305,MATCH($C21,$A$6:$A$305,0)),"")="Program",0,1),1))))) | AD21: =IF(AND($A21<>"",OR($M21="■ Red",$M21="◧ Amber"),$L21=""),1,0) | AE21: =$AA21+$AB21+IF($AC21>0,1,0)+$AD21+$AG21+$AH21 | AG21: =IF(AND($A21<>"",$K21<>"",$C21<>"Portfolio",$D21<>"Completed",$D21<>"Terminated"),1,0) | AH21: =IF(AND($A21<>"",COUNTIF($A$6:$A$305,$A21)>1),1,0) | AI21: =IF(AND($A21<>"",$C21="Portfolio"),COUNTIFS($C$6:$C21,"Portfolio",$A$6:$A21,"<>"),"")
M22: =IF($A22="","",IF($D22="","Not read",IF($Q22=0,"Not counted",IF(MAX($X22,$Y22)=3,"■ Red",IF(MAX($X22,$Y22)=2,"◧ Amber",IF(MAX($X22,$Y22)=1,"□ On track","Not read")))))) | N22: =IF(OR($A22="",$B22<>"Program"),"","■ "&COUNTIFS($C$6:$C$305,$A22,$M$6:$M$305,"■ Red")&" Red, ◧ "&COUNTIFS($C$6:$C$305,$A22,$M$6:$M$305,"◧ Amber")&" Amber") | O22: =IF(OR($A22="",$E22=""),"",COUNTIFS($E$6:$E$305,$E22,$D$6:$D$305,"Active")+COUNTIFS($E$6:$E$305,$E22,$D$6:$D$305,"Paused")) | P22: =IF($A22="","",IF($AE22=0,"○ Clear",IF($AA22=1,"△ No owner",IF($AC22=1,"△ Check Sits under",IF($AC22=2,"△ Outside the portfolio",IF($AB22=1,"△ No sponsor",IF($AH22=1,"△ Name used twice",IF($AG22=1,"△ Budget only counts under Portfolio","△ No variance note"))))))&IF($AE22>1," (+"&($AE22-1)&" more)",""))) | Q22: =IF(AND($A22<>"",OR($D22="Active",$D22="Paused")),1,0) | R22: =IFERROR(INDEX($A$6:$A$305,MATCH(15,$S$6:$S$305,0)),"") | S22: =IF(AND($A22<>"",$B22="Program"),COUNTIFS($B$6:$B22,"Program",$A$6:$A22,"<>"),"") | T22: =IF(AND($A22<>"",$B22="Program"),SUMPRODUCT(MAX(($C$6:$C$305=$A22)*($B$6:$B$305="Project")*($D$6:$D$305<>"Proposed")*$I$6:$I$305)),0) | U22: =IF($I22<>"",$I22,IF($T22>0,$T22,"")) | V22: =IF(AND($A22<>"",$B22="Program"),SUMIFS($J$6:$J$305,$C$6:$C$305,$A22,$B$6:$B$305,"Project",$D$6:$D$305,"<>Proposed"),0) | W22: =IF(AND($A22<>"",$B22="Program"),COUNTIFS($C$6:$C$305,$A22,$B$6:$B$305,"Project",$D$6:$D$305,"<>Proposed")-COUNTIFS($C$6:$C$305,$A22,$B$6:$B$305,"Project",$D$6:$D$305,"<>Proposed",$J$6:$J$305,">=0"),0) | X22: =IF(OR($Q22=0,$H22="",$AF22="Sprint"),0,IF(AND($B22="Project",$H22<TODAY()),3,IF($U22="",0,IF($U22<=$H22,1,IF(NETWORKDAYS($H22,$U22)-1>IF($B22="Program",Checks!$B$7,Checks!$B$6),3,2))))) | Y22: =IF(OR($Q22=0,$K22="",$K22=0,$AF22="Sprint"),0,IF(AND($B22="Project",$J22=""),0,IF(IF($B22="Program",$V22,$J22)>$K22*(1+Checks!$B$8),3,IF(IF($B22="Program",$V22,$J22)>$K22,2,IF(AND($B22="Program",OR($W22>0,$V22=0)),0,1))))) | Z22: =IF($A22="",0,IF($C22="Portfolio",1,IF(AND($B22="Project",$C22<>"",$C22<>"Outside the portfolio"),IFERROR(IF(AND(INDEX($B$6:$B$305,MATCH($C22,$A$6:$A$305,0))="Program",INDEX($C$6:$C$305,MATCH($C22,$A$6:$A$305,0))="Portfolio"),1,0),0),0))) | AA22: =IF(AND($A22<>"",$E22="",OR($Q22=1,$D22="Proposed")),1,0) | AB22: =IF(AND($A22<>"",$B22="Program",$F22="",$Q22=1),1,0) | AC22: =IF(OR($A22="",$D22="Completed",$D22="Terminated"),0,IF($C22="",1,IF($C22="Portfolio",0,IF($C22="Outside the portfolio",IF($Q22=1,2,0),IF($B22="Project",IF(IFERROR(INDEX($B$6:$B$305,MATCH($C22,$A$6:$A$305,0)),"")="Program",0,1),1))))) | AD22: =IF(AND($A22<>"",OR($M22="■ Red",$M22="◧ Amber"),$L22=""),1,0) | AE22: =$AA22+$AB22+IF($AC22>0,1,0)+$AD22+$AG22+$AH22 | AG22: =IF(AND($A22<>"",$K22<>"",$C22<>"Portfolio",$D22<>"Completed",$D22<>"Terminated"),1,0) | AH22: =IF(AND($A22<>"",COUNTIF($A$6:$A$305,$A22)>1),1,0) | AI22: =IF(AND($A22<>"",$C22="Portfolio"),COUNTIFS($C$6:$C22,"Portfolio",$A$6:$A22,"<>"),"")
M23: =IF($A23="","",IF($D23="","Not read",IF($Q23=0,"Not counted",IF(MAX($X23,$Y23)=3,"■ Red",IF(MAX($X23,$Y23)=2,"◧ Amber",IF(MAX($X23,$Y23)=1,"□ On track","Not read")))))) | N23: =IF(OR($A23="",$B23<>"Program"),"","■ "&COUNTIFS($C$6:$C$305,$A23,$M$6:$M$305,"■ Red")&" Red, ◧ "&COUNTIFS($C$6:$C$305,$A23,$M$6:$M$305,"◧ Amber")&" Amber") | O23: =IF(OR($A23="",$E23=""),"",COUNTIFS($E$6:$E$305,$E23,$D$6:$D$305,"Active")+COUNTIFS($E$6:$E$305,$E23,$D$6:$D$305,"Paused")) | P23: =IF($A23="","",IF($AE23=0,"○ Clear",IF($AA23=1,"△ No owner",IF($AC23=1,"△ Check Sits under",IF($AC23=2,"△ Outside the portfolio",IF($AB23=1,"△ No sponsor",IF($AH23=1,"△ Name used twice",IF($AG23=1,"△ Budget only counts under Portfolio","△ No variance note"))))))&IF($AE23>1," (+"&($AE23-1)&" more)",""))) | Q23: =IF(AND($A23<>"",OR($D23="Active",$D23="Paused")),1,0) | R23: =IFERROR(INDEX($A$6:$A$305,MATCH(16,$S$6:$S$305,0)),"") | S23: =IF(AND($A23<>"",$B23="Program"),COUNTIFS($B$6:$B23,"Program",$A$6:$A23,"<>"),"") | T23: =IF(AND($A23<>"",$B23="Program"),SUMPRODUCT(MAX(($C$6:$C$305=$A23)*($B$6:$B$305="Project")*($D$6:$D$305<>"Proposed")*$I$6:$I$305)),0) | U23: =IF($I23<>"",$I23,IF($T23>0,$T23,"")) | V23: =IF(AND($A23<>"",$B23="Program"),SUMIFS($J$6:$J$305,$C$6:$C$305,$A23,$B$6:$B$305,"Project",$D$6:$D$305,"<>Proposed"),0) | W23: =IF(AND($A23<>"",$B23="Program"),COUNTIFS($C$6:$C$305,$A23,$B$6:$B$305,"Project",$D$6:$D$305,"<>Proposed")-COUNTIFS($C$6:$C$305,$A23,$B$6:$B$305,"Project",$D$6:$D$305,"<>Proposed",$J$6:$J$305,">=0"),0) | X23: =IF(OR($Q23=0,$H23="",$AF23="Sprint"),0,IF(AND($B23="Project",$H23<TODAY()),3,IF($U23="",0,IF($U23<=$H23,1,IF(NETWORKDAYS($H23,$U23)-1>IF($B23="Program",Checks!$B$7,Checks!$B$6),3,2))))) | Y23: =IF(OR($Q23=0,$K23="",$K23=0,$AF23="Sprint"),0,IF(AND($B23="Project",$J23=""),0,IF(IF($B23="Program",$V23,$J23)>$K23*(1+Checks!$B$8),3,IF(IF($B23="Program",$V23,$J23)>$K23,2,IF(AND($B23="Program",OR($W23>0,$V23=0)),0,1))))) | Z23: =IF($A23="",0,IF($C23="Portfolio",1,IF(AND($B23="Project",$C23<>"",$C23<>"Outside the portfolio"),IFERROR(IF(AND(INDEX($B$6:$B$305,MATCH($C23,$A$6:$A$305,0))="Program",INDEX($C$6:$C$305,MATCH($C23,$A$6:$A$305,0))="Portfolio"),1,0),0),0))) | AA23: =IF(AND($A23<>"",$E23="",OR($Q23=1,$D23="Proposed")),1,0) | AB23: =IF(AND($A23<>"",$B23="Program",$F23="",$Q23=1),1,0) | AC23: =IF(OR($A23="",$D23="Completed",$D23="Terminated"),0,IF($C23="",1,IF($C23="Portfolio",0,IF($C23="Outside the portfolio",IF($Q23=1,2,0),IF($B23="Project",IF(IFERROR(INDEX($B$6:$B$305,MATCH($C23,$A$6:$A$305,0)),"")="Program",0,1),1))))) | AD23: =IF(AND($A23<>"",OR($M23="■ Red",$M23="◧ Amber"),$L23=""),1,0) | AE23: =$AA23+$AB23+IF($AC23>0,1,0)+$AD23+$AG23+$AH23 | AG23: =IF(AND($A23<>"",$K23<>"",$C23<>"Portfolio",$D23<>"Completed",$D23<>"Terminated"),1,0) | AH23: =IF(AND($A23<>"",COUNTIF($A$6:$A$305,$A23)>1),1,0) | AI23: =IF(AND($A23<>"",$C23="Portfolio"),COUNTIFS($C$6:$C23,"Portfolio",$A$6:$A23,"<>"),"")
M24: =IF($A24="","",IF($D24="","Not read",IF($Q24=0,"Not counted",IF(MAX($X24,$Y24)=3,"■ Red",IF(MAX($X24,$Y24)=2,"◧ Amber",IF(MAX($X24,$Y24)=1,"□ On track","Not read")))))) | N24: =IF(OR($A24="",$B24<>"Program"),"","■ "&COUNTIFS($C$6:$C$305,$A24,$M$6:$M$305,"■ Red")&" Red, ◧ "&COUNTIFS($C$6:$C$305,$A24,$M$6:$M$305,"◧ Amber")&" Amber") | O24: =IF(OR($A24="",$E24=""),"",COUNTIFS($E$6:$E$305,$E24,$D$6:$D$305,"Active")+COUNTIFS($E$6:$E$305,$E24,$D$6:$D$305,"Paused")) | P24: =IF($A24="","",IF($AE24=0,"○ Clear",IF($AA24=1,"△ No owner",IF($AC24=1,"△ Check Sits under",IF($AC24=2,"△ Outside the portfolio",IF($AB24=1,"△ No sponsor",IF($AH24=1,"△ Name used twice",IF($AG24=1,"△ Budget only counts under Portfolio","△ No variance note"))))))&IF($AE24>1," (+"&($AE24-1)&" more)",""))) | Q24: =IF(AND($A24<>"",OR($D24="Active",$D24="Paused")),1,0) | R24: =IFERROR(INDEX($A$6:$A$305,MATCH(17,$S$6:$S$305,0)),"") | S24: =IF(AND($A24<>"",$B24="Program"),COUNTIFS($B$6:$B24,"Program",$A$6:$A24,"<>"),"") | T24: =IF(AND($A24<>"",$B24="Program"),SUMPRODUCT(MAX(($C$6:$C$305=$A24)*($B$6:$B$305="Project")*($D$6:$D$305<>"Proposed")*$I$6:$I$305)),0) | U24: =IF($I24<>"",$I24,IF($T24>0,$T24,"")) | V24: =IF(AND($A24<>"",$B24="Program"),SUMIFS($J$6:$J$305,$C$6:$C$305,$A24,$B$6:$B$305,"Project",$D$6:$D$305,"<>Proposed"),0) | W24: =IF(AND($A24<>"",$B24="Program"),COUNTIFS($C$6:$C$305,$A24,$B$6:$B$305,"Project",$D$6:$D$305,"<>Proposed")-COUNTIFS($C$6:$C$305,$A24,$B$6:$B$305,"Project",$D$6:$D$305,"<>Proposed",$J$6:$J$305,">=0"),0) | X24: =IF(OR($Q24=0,$H24="",$AF24="Sprint"),0,IF(AND($B24="Project",$H24<TODAY()),3,IF($U24="",0,IF($U24<=$H24,1,IF(NETWORKDAYS($H24,$U24)-1>IF($B24="Program",Checks!$B$7,Checks!$B$6),3,2))))) | Y24: =IF(OR($Q24=0,$K24="",$K24=0,$AF24="Sprint"),0,IF(AND($B24="Project",$J24=""),0,IF(IF($B24="Program",$V24,$J24)>$K24*(1+Checks!$B$8),3,IF(IF($B24="Program",$V24,$J24)>$K24,2,IF(AND($B24="Program",OR($W24>0,$V24=0)),0,1))))) | Z24: =IF($A24="",0,IF($C24="Portfolio",1,IF(AND($B24="Project",$C24<>"",$C24<>"Outside the portfolio"),IFERROR(IF(AND(INDEX($B$6:$B$305,MATCH($C24,$A$6:$A$305,0))="Program",INDEX($C$6:$C$305,MATCH($C24,$A$6:$A$305,0))="Portfolio"),1,0),0),0))) | AA24: =IF(AND($A24<>"",$E24="",OR($Q24=1,$D24="Proposed")),1,0) | AB24: =IF(AND($A24<>"",$B24="Program",$F24="",$Q24=1),1,0) | AC24: =IF(OR($A24="",$D24="Completed",$D24="Terminated"),0,IF($C24="",1,IF($C24="Portfolio",0,IF($C24="Outside the portfolio",IF($Q24=1,2,0),IF($B24="Project",IF(IFERROR(INDEX($B$6:$B$305,MATCH($C24,$A$6:$A$305,0)),"")="Program",0,1),1))))) | AD24: =IF(AND($A24<>"",OR($M24="■ Red",$M24="◧ Amber"),$L24=""),1,0) | AE24: =$AA24+$AB24+IF($AC24>0,1,0)+$AD24+$AG24+$AH24 | AG24: =IF(AND($A24<>"",$K24<>"",$C24<>"Portfolio",$D24<>"Completed",$D24<>"Terminated"),1,0) | AH24: =IF(AND($A24<>"",COUNTIF($A$6:$A$305,$A24)>1),1,0) | AI24: =IF(AND($A24<>"",$C24="Portfolio"),COUNTIFS($C$6:$C24,"Portfolio",$A$6:$A24,"<>"),"")
M25: =IF($A25="","",IF($D25="","Not read",IF($Q25=0,"Not counted",IF(MAX($X25,$Y25)=3,"■ Red",IF(MAX($X25,$Y25)=2,"◧ Amber",IF(MAX($X25,$Y25)=1,"□ On track","Not read")))))) | N25: =IF(OR($A25="",$B25<>"Program"),"","■ "&COUNTIFS($C$6:$C$305,$A25,$M$6:$M$305,"■ Red")&" Red, ◧ "&COUNTIFS($C$6:$C$305,$A25,$M$6:$M$305,"◧ Amber")&" Amber") | O25: =IF(OR($A25="",$E25=""),"",COUNTIFS($E$6:$E$305,$E25,$D$6:$D$305,"Active")+COUNTIFS($E$6:$E$305,$E25,$D$6:$D$305,"Paused")) | P25: =IF($A25="","",IF($AE25=0,"○ Clear",IF($AA25=1,"△ No owner",IF($AC25=1,"△ Check Sits under",IF($AC25=2,"△ Outside the portfolio",IF($AB25=1,"△ No sponsor",IF($AH25=1,"△ Name used twice",IF($AG25=1,"△ Budget only counts under Portfolio","△ No variance note"))))))&IF($AE25>1," (+"&($AE25-1)&" more)",""))) | Q25: =IF(AND($A25<>"",OR($D25="Active",$D25="Paused")),1,0) | R25: =IFERROR(INDEX($A$6:$A$305,MATCH(18,$S$6:$S$305,0)),"") | S25: =IF(AND($A25<>"",$B25="Program"),COUNTIFS($B$6:$B25,"Program",$A$6:$A25,"<>"),"") | T25: =IF(AND($A25<>"",$B25="Program"),SUMPRODUCT(MAX(($C$6:$C$305=$A25)*($B$6:$B$305="Project")*($D$6:$D$305<>"Proposed")*$I$6:$I$305)),0) | U25: =IF($I25<>"",$I25,IF($T25>0,$T25,"")) | V25: =IF(AND($A25<>"",$B25="Program"),SUMIFS($J$6:$J$305,$C$6:$C$305,$A25,$B$6:$B$305,"Project",$D$6:$D$305,"<>Proposed"),0) | W25: =IF(AND($A25<>"",$B25="Program"),COUNTIFS($C$6:$C$305,$A25,$B$6:$B$305,"Project",$D$6:$D$305,"<>Proposed")-COUNTIFS($C$6:$C$305,$A25,$B$6:$B$305,"Project",$D$6:$D$305,"<>Proposed",$J$6:$J$305,">=0"),0) | X25: =IF(OR($Q25=0,$H25="",$AF25="Sprint"),0,IF(AND($B25="Project",$H25<TODAY()),3,IF($U25="",0,IF($U25<=$H25,1,IF(NETWORKDAYS($H25,$U25)-1>IF($B25="Program",Checks!$B$7,Checks!$B$6),3,2))))) | Y25: =IF(OR($Q25=0,$K25="",$K25=0,$AF25="Sprint"),0,IF(AND($B25="Project",$J25=""),0,IF(IF($B25="Program",$V25,$J25)>$K25*(1+Checks!$B$8),3,IF(IF($B25="Program",$V25,$J25)>$K25,2,IF(AND($B25="Program",OR($W25>0,$V25=0)),0,1))))) | Z25: =IF($A25="",0,IF($C25="Portfolio",1,IF(AND($B25="Project",$C25<>"",$C25<>"Outside the portfolio"),IFERROR(IF(AND(INDEX($B$6:$B$305,MATCH($C25,$A$6:$A$305,0))="Program",INDEX($C$6:$C$305,MATCH($C25,$A$6:$A$305,0))="Portfolio"),1,0),0),0))) | AA25: =IF(AND($A25<>"",$E25="",OR($Q25=1,$D25="Proposed")),1,0) | AB25: =IF(AND($A25<>"",$B25="Program",$F25="",$Q25=1),1,0) | AC25: =IF(OR($A25="",$D25="Completed",$D25="Terminated"),0,IF($C25="",1,IF($C25="Portfolio",0,IF($C25="Outside the portfolio",IF($Q25=1,2,0),IF($B25="Project",IF(IFERROR(INDEX($B$6:$B$305,MATCH($C25,$A$6:$A$305,0)),"")="Program",0,1),1))))) | AD25: =IF(AND($A25<>"",OR($M25="■ Red",$M25="◧ Amber"),$L25=""),1,0) | AE25: =$AA25+$AB25+IF($AC25>0,1,0)+$AD25+$AG25+$AH25 | AG25: =IF(AND($A25<>"",$K25<>"",$C25<>"Portfolio",$D25<>"Completed",$D25<>"Terminated"),1,0) | AH25: =IF(AND($A25<>"",COUNTIF($A$6:$A$305,$A25)>1),1,0) | AI25: =IF(AND($A25<>"",$C25="Portfolio"),COUNTIFS($C$6:$C25,"Portfolio",$A$6:$A25,"<>"),"")
M26: =IF($A26="","",IF($D26="","Not read",IF($Q26=0,"Not counted",IF(MAX($X26,$Y26)=3,"■ Red",IF(MAX($X26,$Y26)=2,"◧ Amber",IF(MAX($X26,$Y26)=1,"□ On track","Not read")))))) | N26: =IF(OR($A26="",$B26<>"Program"),"","■ "&COUNTIFS($C$6:$C$305,$A26,$M$6:$M$305,"■ Red")&" Red, ◧ "&COUNTIFS($C$6:$C$305,$A26,$M$6:$M$305,"◧ Amber")&" Amber") | O26: =IF(OR($A26="",$E26=""),"",COUNTIFS($E$6:$E$305,$E26,$D$6:$D$305,"Active")+COUNTIFS($E$6:$E$305,$E26,$D$6:$D$305,"Paused")) | P26: =IF($A26="","",IF($AE26=0,"○ Clear",IF($AA26=1,"△ No owner",IF($AC26=1,"△ Check Sits under",IF($AC26=2,"△ Outside the portfolio",IF($AB26=1,"△ No sponsor",IF($AH26=1,"△ Name used twice",IF($AG26=1,"△ Budget only counts under Portfolio","△ No variance note"))))))&IF($AE26>1," (+"&($AE26-1)&" more)",""))) | Q26: =IF(AND($A26<>"",OR($D26="Active",$D26="Paused")),1,0) | R26: =IFERROR(INDEX($A$6:$A$305,MATCH(19,$S$6:$S$305,0)),"") | S26: =IF(AND($A26<>"",$B26="Program"),COUNTIFS($B$6:$B26,"Program",$A$6:$A26,"<>"),"") | T26: =IF(AND($A26<>"",$B26="Program"),SUMPRODUCT(MAX(($C$6:$C$305=$A26)*($B$6:$B$305="Project")*($D$6:$D$305<>"Proposed")*$I$6:$I$305)),0) | U26: =IF($I26<>"",$I26,IF($T26>0,$T26,"")) | V26: =IF(AND($A26<>"",$B26="Program"),SUMIFS($J$6:$J$305,$C$6:$C$305,$A26,$B$6:$B$305,"Project",$D$6:$D$305,"<>Proposed"),0) | W26: =IF(AND($A26<>"",$B26="Program"),COUNTIFS($C$6:$C$305,$A26,$B$6:$B$305,"Project",$D$6:$D$305,"<>Proposed")-COUNTIFS($C$6:$C$305,$A26,$B$6:$B$305,"Project",$D$6:$D$305,"<>Proposed",$J$6:$J$305,">=0"),0) | X26: =IF(OR($Q26=0,$H26="",$AF26="Sprint"),0,IF(AND($B26="Project",$H26<TODAY()),3,IF($U26="",0,IF($U26<=$H26,1,IF(NETWORKDAYS($H26,$U26)-1>IF($B26="Program",Checks!$B$7,Checks!$B$6),3,2))))) | Y26: =IF(OR($Q26=0,$K26="",$K26=0,$AF26="Sprint"),0,IF(AND($B26="Project",$J26=""),0,IF(IF($B26="Program",$V26,$J26)>$K26*(1+Checks!$B$8),3,IF(IF($B26="Program",$V26,$J26)>$K26,2,IF(AND($B26="Program",OR($W26>0,$V26=0)),0,1))))) | Z26: =IF($A26="",0,IF($C26="Portfolio",1,IF(AND($B26="Project",$C26<>"",$C26<>"Outside the portfolio"),IFERROR(IF(AND(INDEX($B$6:$B$305,MATCH($C26,$A$6:$A$305,0))="Program",INDEX($C$6:$C$305,MATCH($C26,$A$6:$A$305,0))="Portfolio"),1,0),0),0))) | AA26: =IF(AND($A26<>"",$E26="",OR($Q26=1,$D26="Proposed")),1,0) | AB26: =IF(AND($A26<>"",$B26="Program",$F26="",$Q26=1),1,0) | AC26: =IF(OR($A26="",$D26="Completed",$D26="Terminated"),0,IF($C26="",1,IF($C26="Portfolio",0,IF($C26="Outside the portfolio",IF($Q26=1,2,0),IF($B26="Project",IF(IFERROR(INDEX($B$6:$B$305,MATCH($C26,$A$6:$A$305,0)),"")="Program",0,1),1))))) | AD26: =IF(AND($A26<>"",OR($M26="■ Red",$M26="◧ Amber"),$L26=""),1,0) | AE26: =$AA26+$AB26+IF($AC26>0,1,0)+$AD26+$AG26+$AH26 | AG26: =IF(AND($A26<>"",$K26<>"",$C26<>"Portfolio",$D26<>"Completed",$D26<>"Terminated"),1,0) | AH26: =IF(AND($A26<>"",COUNTIF($A$6:$A$305,$A26)>1),1,0) | AI26: =IF(AND($A26<>"",$C26="Portfolio"),COUNTIFS($C$6:$C26,"Portfolio",$A$6:$A26,"<>"),"")
M27: =IF($A27="","",IF($D27="","Not read",IF($Q27=0,"Not counted",IF(MAX($X27,$Y27)=3,"■ Red",IF(MAX($X27,$Y27)=2,"◧ Amber",IF(MAX($X27,$Y27)=1,"□ On track","Not read")))))) | N27: =IF(OR($A27="",$B27<>"Program"),"","■ "&COUNTIFS($C$6:$C$305,$A27,$M$6:$M$305,"■ Red")&" Red, ◧ "&COUNTIFS($C$6:$C$305,$A27,$M$6:$M$305,"◧ Amber")&" Amber") | O27: =IF(OR($A27="",$E27=""),"",COUNTIFS($E$6:$E$305,$E27,$D$6:$D$305,"Active")+COUNTIFS($E$6:$E$305,$E27,$D$6:$D$305,"Paused")) | P27: =IF($A27="","",IF($AE27=0,"○ Clear",IF($AA27=1,"△ No owner",IF($AC27=1,"△ Check Sits under",IF($AC27=2,"△ Outside the portfolio",IF($AB27=1,"△ No sponsor",IF($AH27=1,"△ Name used twice",IF($AG27=1,"△ Budget only counts under Portfolio","△ No variance note"))))))&IF($AE27>1," (+"&($AE27-1)&" more)",""))) | Q27: =IF(AND($A27<>"",OR($D27="Active",$D27="Paused")),1,0) | R27: =IFERROR(INDEX($A$6:$A$305,MATCH(20,$S$6:$S$305,0)),"") | S27: =IF(AND($A27<>"",$B27="Program"),COUNTIFS($B$6:$B27,"Program",$A$6:$A27,"<>"),"") | T27: =IF(AND($A27<>"",$B27="Program"),SUMPRODUCT(MAX(($C$6:$C$305=$A27)*($B$6:$B$305="Project")*($D$6:$D$305<>"Proposed")*$I$6:$I$305)),0) | U27: =IF($I27<>"",$I27,IF($T27>0,$T27,"")) | V27: =IF(AND($A27<>"",$B27="Program"),SUMIFS($J$6:$J$305,$C$6:$C$305,$A27,$B$6:$B$305,"Project",$D$6:$D$305,"<>Proposed"),0) | W27: =IF(AND($A27<>"",$B27="Program"),COUNTIFS($C$6:$C$305,$A27,$B$6:$B$305,"Project",$D$6:$D$305,"<>Proposed")-COUNTIFS($C$6:$C$305,$A27,$B$6:$B$305,"Project",$D$6:$D$305,"<>Proposed",$J$6:$J$305,">=0"),0) | X27: =IF(OR($Q27=0,$H27="",$AF27="Sprint"),0,IF(AND($B27="Project",$H27<TODAY()),3,IF($U27="",0,IF($U27<=$H27,1,IF(NETWORKDAYS($H27,$U27)-1>IF($B27="Program",Checks!$B$7,Checks!$B$6),3,2))))) | Y27: =IF(OR($Q27=0,$K27="",$K27=0,$AF27="Sprint"),0,IF(AND($B27="Project",$J27=""),0,IF(IF($B27="Program",$V27,$J27)>$K27*(1+Checks!$B$8),3,IF(IF($B27="Program",$V27,$J27)>$K27,2,IF(AND($B27="Program",OR($W27>0,$V27=0)),0,1))))) | Z27: =IF($A27="",0,IF($C27="Portfolio",1,IF(AND($B27="Project",$C27<>"",$C27<>"Outside the portfolio"),IFERROR(IF(AND(INDEX($B$6:$B$305,MATCH($C27,$A$6:$A$305,0))="Program",INDEX($C$6:$C$305,MATCH($C27,$A$6:$A$305,0))="Portfolio"),1,0),0),0))) | AA27: =IF(AND($A27<>"",$E27="",OR($Q27=1,$D27="Proposed")),1,0) | AB27: =IF(AND($A27<>"",$B27="Program",$F27="",$Q27=1),1,0) | AC27: =IF(OR($A27="",$D27="Completed",$D27="Terminated"),0,IF($C27="",1,IF($C27="Portfolio",0,IF($C27="Outside the portfolio",IF($Q27=1,2,0),IF($B27="Project",IF(IFERROR(INDEX($B$6:$B$305,MATCH($C27,$A$6:$A$305,0)),"")="Program",0,1),1))))) | AD27: =IF(AND($A27<>"",OR($M27="■ Red",$M27="◧ Amber"),$L27=""),1,0) | AE27: =$AA27+$AB27+IF($AC27>0,1,0)+$AD27+$AG27+$AH27 | AG27: =IF(AND($A27<>"",$K27<>"",$C27<>"Portfolio",$D27<>"Completed",$D27<>"Terminated"),1,0) | AH27: =IF(AND($A27<>"",COUNTIF($A$6:$A$305,$A27)>1),1,0) | AI27: =IF(AND($A27<>"",$C27="Portfolio"),COUNTIFS($C$6:$C27,"Portfolio",$A$6:$A27,"<>"),"")
M28: =IF($A28="","",IF($D28="","Not read",IF($Q28=0,"Not counted",IF(MAX($X28,$Y28)=3,"■ Red",IF(MAX($X28,$Y28)=2,"◧ Amber",IF(MAX($X28,$Y28)=1,"□ On track","Not read")))))) | N28: =IF(OR($A28="",$B28<>"Program"),"","■ "&COUNTIFS($C$6:$C$305,$A28,$M$6:$M$305,"■ Red")&" Red, ◧ "&COUNTIFS($C$6:$C$305,$A28,$M$6:$M$305,"◧ Amber")&" Amber") | O28: =IF(OR($A28="",$E28=""),"",COUNTIFS($E$6:$E$305,$E28,$D$6:$D$305,"Active")+COUNTIFS($E$6:$E$305,$E28,$D$6:$D$305,"Paused")) | P28: =IF($A28="","",IF($AE28=0,"○ Clear",IF($AA28=1,"△ No owner",IF($AC28=1,"△ Check Sits under",IF($AC28=2,"△ Outside the portfolio",IF($AB28=1,"△ No sponsor",IF($AH28=1,"△ Name used twice",IF($AG28=1,"△ Budget only counts under Portfolio","△ No variance note"))))))&IF($AE28>1," (+"&($AE28-1)&" more)",""))) | Q28: =IF(AND($A28<>"",OR($D28="Active",$D28="Paused")),1,0) | R28: =IFERROR(INDEX($A$6:$A$305,MATCH(21,$S$6:$S$305,0)),"") | S28: =IF(AND($A28<>"",$B28="Program"),COUNTIFS($B$6:$B28,"Program",$A$6:$A28,"<>"),"") | T28: =IF(AND($A28<>"",$B28="Program"),SUMPRODUCT(MAX(($C$6:$C$305=$A28)*($B$6:$B$305="Project")*($D$6:$D$305<>"Proposed")*$I$6:$I$305)),0) | U28: =IF($I28<>"",$I28,IF($T28>0,$T28,"")) | V28: =IF(AND($A28<>"",$B28="Program"),SUMIFS($J$6:$J$305,$C$6:$C$305,$A28,$B$6:$B$305,"Project",$D$6:$D$305,"<>Proposed"),0) | W28: =IF(AND($A28<>"",$B28="Program"),COUNTIFS($C$6:$C$305,$A28,$B$6:$B$305,"Project",$D$6:$D$305,"<>Proposed")-COUNTIFS($C$6:$C$305,$A28,$B$6:$B$305,"Project",$D$6:$D$305,"<>Proposed",$J$6:$J$305,">=0"),0) | X28: =IF(OR($Q28=0,$H28="",$AF28="Sprint"),0,IF(AND($B28="Project",$H28<TODAY()),3,IF($U28="",0,IF($U28<=$H28,1,IF(NETWORKDAYS($H28,$U28)-1>IF($B28="Program",Checks!$B$7,Checks!$B$6),3,2))))) | Y28: =IF(OR($Q28=0,$K28="",$K28=0,$AF28="Sprint"),0,IF(AND($B28="Project",$J28=""),0,IF(IF($B28="Program",$V28,$J28)>$K28*(1+Checks!$B$8),3,IF(IF($B28="Program",$V28,$J28)>$K28,2,IF(AND($B28="Program",OR($W28>0,$V28=0)),0,1))))) | Z28: =IF($A28="",0,IF($C28="Portfolio",1,IF(AND($B28="Project",$C28<>"",$C28<>"Outside the portfolio"),IFERROR(IF(AND(INDEX($B$6:$B$305,MATCH($C28,$A$6:$A$305,0))="Program",INDEX($C$6:$C$305,MATCH($C28,$A$6:$A$305,0))="Portfolio"),1,0),0),0))) | AA28: =IF(AND($A28<>"",$E28="",OR($Q28=1,$D28="Proposed")),1,0) | AB28: =IF(AND($A28<>"",$B28="Program",$F28="",$Q28=1),1,0) | AC28: =IF(OR($A28="",$D28="Completed",$D28="Terminated"),0,IF($C28="",1,IF($C28="Portfolio",0,IF($C28="Outside the portfolio",IF($Q28=1,2,0),IF($B28="Project",IF(IFERROR(INDEX($B$6:$B$305,MATCH($C28,$A$6:$A$305,0)),"")="Program",0,1),1))))) | AD28: =IF(AND($A28<>"",OR($M28="■ Red",$M28="◧ Amber"),$L28=""),1,0) | AE28: =$AA28+$AB28+IF($AC28>0,1,0)+$AD28+$AG28+$AH28 | AG28: =IF(AND($A28<>"",$K28<>"",$C28<>"Portfolio",$D28<>"Completed",$D28<>"Terminated"),1,0) | AH28: =IF(AND($A28<>"",COUNTIF($A$6:$A$305,$A28)>1),1,0) | AI28: =IF(AND($A28<>"",$C28="Portfolio"),COUNTIFS($C$6:$C28,"Portfolio",$A$6:$A28,"<>"),"")
M29: =IF($A29="","",IF($D29="","Not read",IF($Q29=0,"Not counted",IF(MAX($X29,$Y29)=3,"■ Red",IF(MAX($X29,$Y29)=2,"◧ Amber",IF(MAX($X29,$Y29)=1,"□ On track","Not read")))))) | N29: =IF(OR($A29="",$B29<>"Program"),"","■ "&COUNTIFS($C$6:$C$305,$A29,$M$6:$M$305,"■ Red")&" Red, ◧ "&COUNTIFS($C$6:$C$305,$A29,$M$6:$M$305,"◧ Amber")&" Amber") | O29: =IF(OR($A29="",$E29=""),"",COUNTIFS($E$6:$E$305,$E29,$D$6:$D$305,"Active")+COUNTIFS($E$6:$E$305,$E29,$D$6:$D$305,"Paused")) | P29: =IF($A29="","",IF($AE29=0,"○ Clear",IF($AA29=1,"△ No owner",IF($AC29=1,"△ Check Sits under",IF($AC29=2,"△ Outside the portfolio",IF($AB29=1,"△ No sponsor",IF($AH29=1,"△ Name used twice",IF($AG29=1,"△ Budget only counts under Portfolio","△ No variance note"))))))&IF($AE29>1," (+"&($AE29-1)&" more)",""))) | Q29: =IF(AND($A29<>"",OR($D29="Active",$D29="Paused")),1,0) | R29: =IFERROR(INDEX($A$6:$A$305,MATCH(22,$S$6:$S$305,0)),"") | S29: =IF(AND($A29<>"",$B29="Program"),COUNTIFS($B$6:$B29,"Program",$A$6:$A29,"<>"),"") | T29: =IF(AND($A29<>"",$B29="Program"),SUMPRODUCT(MAX(($C$6:$C$305=$A29)*($B$6:$B$305="Project")*($D$6:$D$305<>"Proposed")*$I$6:$I$305)),0) | U29: =IF($I29<>"",$I29,IF($T29>0,$T29,"")) | V29: =IF(AND($A29<>"",$B29="Program"),SUMIFS($J$6:$J$305,$C$6:$C$305,$A29,$B$6:$B$305,"Project",$D$6:$D$305,"<>Proposed"),0) | W29: =IF(AND($A29<>"",$B29="Program"),COUNTIFS($C$6:$C$305,$A29,$B$6:$B$305,"Project",$D$6:$D$305,"<>Proposed")-COUNTIFS($C$6:$C$305,$A29,$B$6:$B$305,"Project",$D$6:$D$305,"<>Proposed",$J$6:$J$305,">=0"),0) | X29: =IF(OR($Q29=0,$H29="",$AF29="Sprint"),0,IF(AND($B29="Project",$H29<TODAY()),3,IF($U29="",0,IF($U29<=$H29,1,IF(NETWORKDAYS($H29,$U29)-1>IF($B29="Program",Checks!$B$7,Checks!$B$6),3,2))))) | Y29: =IF(OR($Q29=0,$K29="",$K29=0,$AF29="Sprint"),0,IF(AND($B29="Project",$J29=""),0,IF(IF($B29="Program",$V29,$J29)>$K29*(1+Checks!$B$8),3,IF(IF($B29="Program",$V29,$J29)>$K29,2,IF(AND($B29="Program",OR($W29>0,$V29=0)),0,1))))) | Z29: =IF($A29="",0,IF($C29="Portfolio",1,IF(AND($B29="Project",$C29<>"",$C29<>"Outside the portfolio"),IFERROR(IF(AND(INDEX($B$6:$B$305,MATCH($C29,$A$6:$A$305,0))="Program",INDEX($C$6:$C$305,MATCH($C29,$A$6:$A$305,0))="Portfolio"),1,0),0),0))) | AA29: =IF(AND($A29<>"",$E29="",OR($Q29=1,$D29="Proposed")),1,0) | AB29: =IF(AND($A29<>"",$B29="Program",$F29="",$Q29=1),1,0) | AC29: =IF(OR($A29="",$D29="Completed",$D29="Terminated"),0,IF($C29="",1,IF($C29="Portfolio",0,IF($C29="Outside the portfolio",IF($Q29=1,2,0),IF($B29="Project",IF(IFERROR(INDEX($B$6:$B$305,MATCH($C29,$A$6:$A$305,0)),"")="Program",0,1),1))))) | AD29: =IF(AND($A29<>"",OR($M29="■ Red",$M29="◧ Amber"),$L29=""),1,0) | AE29: =$AA29+$AB29+IF($AC29>0,1,0)+$AD29+$AG29+$AH29 | AG29: =IF(AND($A29<>"",$K29<>"",$C29<>"Portfolio",$D29<>"Completed",$D29<>"Terminated"),1,0) | AH29: =IF(AND($A29<>"",COUNTIF($A$6:$A$305,$A29)>1),1,0) | AI29: =IF(AND($A29<>"",$C29="Portfolio"),COUNTIFS($C$6:$C29,"Portfolio",$A$6:$A29,"<>"),"")
M30: =IF($A30="","",IF($D30="","Not read",IF($Q30=0,"Not counted",IF(MAX($X30,$Y30)=3,"■ Red",IF(MAX($X30,$Y30)=2,"◧ Amber",IF(MAX($X30,$Y30)=1,"□ On track","Not read")))))) | N30: =IF(OR($A30="",$B30<>"Program"),"","■ "&COUNTIFS($C$6:$C$305,$A30,$M$6:$M$305,"■ Red")&" Red, ◧ "&COUNTIFS($C$6:$C$305,$A30,$M$6:$M$305,"◧ Amber")&" Amber") | O30: =IF(OR($A30="",$E30=""),"",COUNTIFS($E$6:$E$305,$E30,$D$6:$D$305,"Active")+COUNTIFS($E$6:$E$305,$E30,$D$6:$D$305,"Paused")) | P30: =IF($A30="","",IF($AE30=0,"○ Clear",IF($AA30=1,"△ No owner",IF($AC30=1,"△ Check Sits under",IF($AC30=2,"△ Outside the portfolio",IF($AB30=1,"△ No sponsor",IF($AH30=1,"△ Name used twice",IF($AG30=1,"△ Budget only counts under Portfolio","△ No variance note"))))))&IF($AE30>1," (+"&($AE30-1)&" more)",""))) | Q30: =IF(AND($A30<>"",OR($D30="Active",$D30="Paused")),1,0) | R30: =IFERROR(INDEX($A$6:$A$305,MATCH(23,$S$6:$S$305,0)),"") | S30: =IF(AND($A30<>"",$B30="Program"),COUNTIFS($B$6:$B30,"Program",$A$6:$A30,"<>"),"") | T30: =IF(AND($A30<>"",$B30="Program"),SUMPRODUCT(MAX(($C$6:$C$305=$A30)*($B$6:$B$305="Project")*($D$6:$D$305<>"Proposed")*$I$6:$I$305)),0) | U30: =IF($I30<>"",$I30,IF($T30>0,$T30,"")) | V30: =IF(AND($A30<>"",$B30="Program"),SUMIFS($J$6:$J$305,$C$6:$C$305,$A30,$B$6:$B$305,"Project",$D$6:$D$305,"<>Proposed"),0) | W30: =IF(AND($A30<>"",$B30="Program"),COUNTIFS($C$6:$C$305,$A30,$B$6:$B$305,"Project",$D$6:$D$305,"<>Proposed")-COUNTIFS($C$6:$C$305,$A30,$B$6:$B$305,"Project",$D$6:$D$305,"<>Proposed",$J$6:$J$305,">=0"),0) | X30: =IF(OR($Q30=0,$H30="",$AF30="Sprint"),0,IF(AND($B30="Project",$H30<TODAY()),3,IF($U30="",0,IF($U30<=$H30,1,IF(NETWORKDAYS($H30,$U30)-1>IF($B30="Program",Checks!$B$7,Checks!$B$6),3,2))))) | Y30: =IF(OR($Q30=0,$K30="",$K30=0,$AF30="Sprint"),0,IF(AND($B30="Project",$J30=""),0,IF(IF($B30="Program",$V30,$J30)>$K30*(1+Checks!$B$8),3,IF(IF($B30="Program",$V30,$J30)>$K30,2,IF(AND($B30="Program",OR($W30>0,$V30=0)),0,1))))) | Z30: =IF($A30="",0,IF($C30="Portfolio",1,IF(AND($B30="Project",$C30<>"",$C30<>"Outside the portfolio"),IFERROR(IF(AND(INDEX($B$6:$B$305,MATCH($C30,$A$6:$A$305,0))="Program",INDEX($C$6:$C$305,MATCH($C30,$A$6:$A$305,0))="Portfolio"),1,0),0),0))) | AA30: =IF(AND($A30<>"",$E30="",OR($Q30=1,$D30="Proposed")),1,0) | AB30: =IF(AND($A30<>"",$B30="Program",$F30="",$Q30=1),1,0) | AC30: =IF(OR($A30="",$D30="Completed",$D30="Terminated"),0,IF($C30="",1,IF($C30="Portfolio",0,IF($C30="Outside the portfolio",IF($Q30=1,2,0),IF($B30="Project",IF(IFERROR(INDEX($B$6:$B$305,MATCH($C30,$A$6:$A$305,0)),"")="Program",0,1),1))))) | AD30: =IF(AND($A30<>"",OR($M30="■ Red",$M30="◧ Amber"),$L30=""),1,0) | AE30: =$AA30+$AB30+IF($AC30>0,1,0)+$AD30+$AG30+$AH30 | AG30: =IF(AND($A30<>"",$K30<>"",$C30<>"Portfolio",$D30<>"Completed",$D30<>"Terminated"),1,0) | AH30: =IF(AND($A30<>"",COUNTIF($A$6:$A$305,$A30)>1),1,0) | AI30: =IF(AND($A30<>"",$C30="Portfolio"),COUNTIFS($C$6:$C30,"Portfolio",$A$6:$A30,"<>"),"")
M31: =IF($A31="","",IF($D31="","Not read",IF($Q31=0,"Not counted",IF(MAX($X31,$Y31)=3,"■ Red",IF(MAX($X31,$Y31)=2,"◧ Amber",IF(MAX($X31,$Y31)=1,"□ On track","Not read")))))) | N31: =IF(OR($A31="",$B31<>"Program"),"","■ "&COUNTIFS($C$6:$C$305,$A31,$M$6:$M$305,"■ Red")&" Red, ◧ "&COUNTIFS($C$6:$C$305,$A31,$M$6:$M$305,"◧ Amber")&" Amber") | O31: =IF(OR($A31="",$E31=""),"",COUNTIFS($E$6:$E$305,$E31,$D$6:$D$305,"Active")+COUNTIFS($E$6:$E$305,$E31,$D$6:$D$305,"Paused")) | P31: =IF($A31="","",IF($AE31=0,"○ Clear",IF($AA31=1,"△ No owner",IF($AC31=1,"△ Check Sits under",IF($AC31=2,"△ Outside the portfolio",IF($AB31=1,"△ No sponsor",IF($AH31=1,"△ Name used twice",IF($AG31=1,"△ Budget only counts under Portfolio","△ No variance note"))))))&IF($AE31>1," (+"&($AE31-1)&" more)",""))) | Q31: =IF(AND($A31<>"",OR($D31="Active",$D31="Paused")),1,0) | R31: =IFERROR(INDEX($A$6:$A$305,MATCH(24,$S$6:$S$305,0)),"") | S31: =IF(AND($A31<>"",$B31="Program"),COUNTIFS($B$6:$B31,"Program",$A$6:$A31,"<>"),"") | T31: =IF(AND($A31<>"",$B31="Program"),SUMPRODUCT(MAX(($C$6:$C$305=$A31)*($B$6:$B$305="Project")*($D$6:$D$305<>"Proposed")*$I$6:$I$305)),0) | U31: =IF($I31<>"",$I31,IF($T31>0,$T31,"")) | V31: =IF(AND($A31<>"",$B31="Program"),SUMIFS($J$6:$J$305,$C$6:$C$305,$A31,$B$6:$B$305,"Project",$D$6:$D$305,"<>Proposed"),0) | W31: =IF(AND($A31<>"",$B31="Program"),COUNTIFS($C$6:$C$305,$A31,$B$6:$B$305,"Project",$D$6:$D$305,"<>Proposed")-COUNTIFS($C$6:$C$305,$A31,$B$6:$B$305,"Project",$D$6:$D$305,"<>Proposed",$J$6:$J$305,">=0"),0) | X31: =IF(OR($Q31=0,$H31="",$AF31="Sprint"),0,IF(AND($B31="Project",$H31<TODAY()),3,IF($U31="",0,IF($U31<=$H31,1,IF(NETWORKDAYS($H31,$U31)-1>IF($B31="Program",Checks!$B$7,Checks!$B$6),3,2))))) | Y31: =IF(OR($Q31=0,$K31="",$K31=0,$AF31="Sprint"),0,IF(AND($B31="Project",$J31=""),0,IF(IF($B31="Program",$V31,$J31)>$K31*(1+Checks!$B$8),3,IF(IF($B31="Program",$V31,$J31)>$K31,2,IF(AND($B31="Program",OR($W31>0,$V31=0)),0,1))))) | Z31: =IF($A31="",0,IF($C31="Portfolio",1,IF(AND($B31="Project",$C31<>"",$C31<>"Outside the portfolio"),IFERROR(IF(AND(INDEX($B$6:$B$305,MATCH($C31,$A$6:$A$305,0))="Program",INDEX($C$6:$C$305,MATCH($C31,$A$6:$A$305,0))="Portfolio"),1,0),0),0))) | AA31: =IF(AND($A31<>"",$E31="",OR($Q31=1,$D31="Proposed")),1,0) | AB31: =IF(AND($A31<>"",$B31="Program",$F31="",$Q31=1),1,0) | AC31: =IF(OR($A31="",$D31="Completed",$D31="Terminated"),0,IF($C31="",1,IF($C31="Portfolio",0,IF($C31="Outside the portfolio",IF($Q31=1,2,0),IF($B31="Project",IF(IFERROR(INDEX($B$6:$B$305,MATCH($C31,$A$6:$A$305,0)),"")="Program",0,1),1))))) | AD31: =IF(AND($A31<>"",OR($M31="■ Red",$M31="◧ Amber"),$L31=""),1,0) | AE31: =$AA31+$AB31+IF($AC31>0,1,0)+$AD31+$AG31+$AH31 | AG31: =IF(AND($A31<>"",$K31<>"",$C31<>"Portfolio",$D31<>"Completed",$D31<>"Terminated"),1,0) | AH31: =IF(AND($A31<>"",COUNTIF($A$6:$A$305,$A31)>1),1,0) | AI31: =IF(AND($A31<>"",$C31="Portfolio"),COUNTIFS($C$6:$C31,"Portfolio",$A$6:$A31,"<>"),"")
M32: =IF($A32="","",IF($D32="","Not read",IF($Q32=0,"Not counted",IF(MAX($X32,$Y32)=3,"■ Red",IF(MAX($X32,$Y32)=2,"◧ Amber",IF(MAX($X32,$Y32)=1,"□ On track","Not read")))))) | N32: =IF(OR($A32="",$B32<>"Program"),"","■ "&COUNTIFS($C$6:$C$305,$A32,$M$6:$M$305,"■ Red")&" Red, ◧ "&COUNTIFS($C$6:$C$305,$A32,$M$6:$M$305,"◧ Amber")&" Amber") | O32: =IF(OR($A32="",$E32=""),"",COUNTIFS($E$6:$E$305,$E32,$D$6:$D$305,"Active")+COUNTIFS($E$6:$E$305,$E32,$D$6:$D$305,"Paused")) | P32: =IF($A32="","",IF($AE32=0,"○ Clear",IF($AA32=1,"△ No owner",IF($AC32=1,"△ Check Sits under",IF($AC32=2,"△ Outside the portfolio",IF($AB32=1,"△ No sponsor",IF($AH32=1,"△ Name used twice",IF($AG32=1,"△ Budget only counts under Portfolio","△ No variance note"))))))&IF($AE32>1," (+"&($AE32-1)&" more)",""))) | Q32: =IF(AND($A32<>"",OR($D32="Active",$D32="Paused")),1,0) | R32: =IFERROR(INDEX($A$6:$A$305,MATCH(25,$S$6:$S$305,0)),"") | S32: =IF(AND($A32<>"",$B32="Program"),COUNTIFS($B$6:$B32,"Program",$A$6:$A32,"<>"),"") | T32: =IF(AND($A32<>"",$B32="Program"),SUMPRODUCT(MAX(($C$6:$C$305=$A32)*($B$6:$B$305="Project")*($D$6:$D$305<>"Proposed")*$I$6:$I$305)),0) | U32: =IF($I32<>"",$I32,IF($T32>0,$T32,"")) | V32: =IF(AND($A32<>"",$B32="Program"),SUMIFS($J$6:$J$305,$C$6:$C$305,$A32,$B$6:$B$305,"Project",$D$6:$D$305,"<>Proposed"),0) | W32: =IF(AND($A32<>"",$B32="Program"),COUNTIFS($C$6:$C$305,$A32,$B$6:$B$305,"Project",$D$6:$D$305,"<>Proposed")-COUNTIFS($C$6:$C$305,$A32,$B$6:$B$305,"Project",$D$6:$D$305,"<>Proposed",$J$6:$J$305,">=0"),0) | X32: =IF(OR($Q32=0,$H32="",$AF32="Sprint"),0,IF(AND($B32="Project",$H32<TODAY()),3,IF($U32="",0,IF($U32<=$H32,1,IF(NETWORKDAYS($H32,$U32)-1>IF($B32="Program",Checks!$B$7,Checks!$B$6),3,2))))) | Y32: =IF(OR($Q32=0,$K32="",$K32=0,$AF32="Sprint"),0,IF(AND($B32="Project",$J32=""),0,IF(IF($B32="Program",$V32,$J32)>$K32*(1+Checks!$B$8),3,IF(IF($B32="Program",$V32,$J32)>$K32,2,IF(AND($B32="Program",OR($W32>0,$V32=0)),0,1))))) | Z32: =IF($A32="",0,IF($C32="Portfolio",1,IF(AND($B32="Project",$C32<>"",$C32<>"Outside the portfolio"),IFERROR(IF(AND(INDEX($B$6:$B$305,MATCH($C32,$A$6:$A$305,0))="Program",INDEX($C$6:$C$305,MATCH($C32,$A$6:$A$305,0))="Portfolio"),1,0),0),0))) | AA32: =IF(AND($A32<>"",$E32="",OR($Q32=1,$D32="Proposed")),1,0) | AB32: =IF(AND($A32<>"",$B32="Program",$F32="",$Q32=1),1,0) | AC32: =IF(OR($A32="",$D32="Completed",$D32="Terminated"),0,IF($C32="",1,IF($C32="Portfolio",0,IF($C32="Outside the portfolio",IF($Q32=1,2,0),IF($B32="Project",IF(IFERROR(INDEX($B$6:$B$305,MATCH($C32,$A$6:$A$305,0)),"")="Program",0,1),1))))) | AD32: =IF(AND($A32<>"",OR($M32="■ Red",$M32="◧ Amber"),$L32=""),1,0) | AE32: =$AA32+$AB32+IF($AC32>0,1,0)+$AD32+$AG32+$AH32 | AG32: =IF(AND($A32<>"",$K32<>"",$C32<>"Portfolio",$D32<>"Completed",$D32<>"Terminated"),1,0) | AH32: =IF(AND($A32<>"",COUNTIF($A$6:$A$305,$A32)>1),1,0) | AI32: =IF(AND($A32<>"",$C32="Portfolio"),COUNTIFS($C$6:$C32,"Portfolio",$A$6:$A32,"<>"),"")
M33: =IF($A33="","",IF($D33="","Not read",IF($Q33=0,"Not counted",IF(MAX($X33,$Y33)=3,"■ Red",IF(MAX($X33,$Y33)=2,"◧ Amber",IF(MAX($X33,$Y33)=1,"□ On track","Not read")))))) | N33: =IF(OR($A33="",$B33<>"Program"),"","■ "&COUNTIFS($C$6:$C$305,$A33,$M$6:$M$305,"■ Red")&" Red, ◧ "&COUNTIFS($C$6:$C$305,$A33,$M$6:$M$305,"◧ Amber")&" Amber") | O33: =IF(OR($A33="",$E33=""),"",COUNTIFS($E$6:$E$305,$E33,$D$6:$D$305,"Active")+COUNTIFS($E$6:$E$305,$E33,$D$6:$D$305,"Paused")) | P33: =IF($A33="","",IF($AE33=0,"○ Clear",IF($AA33=1,"△ No owner",IF($AC33=1,"△ Check Sits under",IF($AC33=2,"△ Outside the portfolio",IF($AB33=1,"△ No sponsor",IF($AH33=1,"△ Name used twice",IF($AG33=1,"△ Budget only counts under Portfolio","△ No variance note"))))))&IF($AE33>1," (+"&($AE33-1)&" more)",""))) | Q33: =IF(AND($A33<>"",OR($D33="Active",$D33="Paused")),1,0) | R33: =IFERROR(INDEX($A$6:$A$305,MATCH(26,$S$6:$S$305,0)),"") | S33: =IF(AND($A33<>"",$B33="Program"),COUNTIFS($B$6:$B33,"Program",$A$6:$A33,"<>"),"") | T33: =IF(AND($A33<>"",$B33="Program"),SUMPRODUCT(MAX(($C$6:$C$305=$A33)*($B$6:$B$305="Project")*($D$6:$D$305<>"Proposed")*$I$6:$I$305)),0) | U33: =IF($I33<>"",$I33,IF($T33>0,$T33,"")) | V33: =IF(AND($A33<>"",$B33="Program"),SUMIFS($J$6:$J$305,$C$6:$C$305,$A33,$B$6:$B$305,"Project",$D$6:$D$305,"<>Proposed"),0) | W33: =IF(AND($A33<>"",$B33="Program"),COUNTIFS($C$6:$C$305,$A33,$B$6:$B$305,"Project",$D$6:$D$305,"<>Proposed")-COUNTIFS($C$6:$C$305,$A33,$B$6:$B$305,"Project",$D$6:$D$305,"<>Proposed",$J$6:$J$305,">=0"),0) | X33: =IF(OR($Q33=0,$H33="",$AF33="Sprint"),0,IF(AND($B33="Project",$H33<TODAY()),3,IF($U33="",0,IF($U33<=$H33,1,IF(NETWORKDAYS($H33,$U33)-1>IF($B33="Program",Checks!$B$7,Checks!$B$6),3,2))))) | Y33: =IF(OR($Q33=0,$K33="",$K33=0,$AF33="Sprint"),0,IF(AND($B33="Project",$J33=""),0,IF(IF($B33="Program",$V33,$J33)>$K33*(1+Checks!$B$8),3,IF(IF($B33="Program",$V33,$J33)>$K33,2,IF(AND($B33="Program",OR($W33>0,$V33=0)),0,1))))) | Z33: =IF($A33="",0,IF($C33="Portfolio",1,IF(AND($B33="Project",$C33<>"",$C33<>"Outside the portfolio"),IFERROR(IF(AND(INDEX($B$6:$B$305,MATCH($C33,$A$6:$A$305,0))="Program",INDEX($C$6:$C$305,MATCH($C33,$A$6:$A$305,0))="Portfolio"),1,0),0),0))) | AA33: =IF(AND($A33<>"",$E33="",OR($Q33=1,$D33="Proposed")),1,0) | AB33: =IF(AND($A33<>"",$B33="Program",$F33="",$Q33=1),1,0) | AC33: =IF(OR($A33="",$D33="Completed",$D33="Terminated"),0,IF($C33="",1,IF($C33="Portfolio",0,IF($C33="Outside the portfolio",IF($Q33=1,2,0),IF($B33="Project",IF(IFERROR(INDEX($B$6:$B$305,MATCH($C33,$A$6:$A$305,0)),"")="Program",0,1),1))))) | AD33: =IF(AND($A33<>"",OR($M33="■ Red",$M33="◧ Amber"),$L33=""),1,0) | AE33: =$AA33+$AB33+IF($AC33>0,1,0)+$AD33+$AG33+$AH33 | AG33: =IF(AND($A33<>"",$K33<>"",$C33<>"Portfolio",$D33<>"Completed",$D33<>"Terminated"),1,0) | AH33: =IF(AND($A33<>"",COUNTIF($A$6:$A$305,$A33)>1),1,0) | AI33: =IF(AND($A33<>"",$C33="Portfolio"),COUNTIFS($C$6:$C33,"Portfolio",$A$6:$A33,"<>"),"")
M34: =IF($A34="","",IF($D34="","Not read",IF($Q34=0,"Not counted",IF(MAX($X34,$Y34)=3,"■ Red",IF(MAX($X34,$Y34)=2,"◧ Amber",IF(MAX($X34,$Y34)=1,"□ On track","Not read")))))) | N34: =IF(OR($A34="",$B34<>"Program"),"","■ "&COUNTIFS($C$6:$C$305,$A34,$M$6:$M$305,"■ Red")&" Red, ◧ "&COUNTIFS($C$6:$C$305,$A34,$M$6:$M$305,"◧ Amber")&" Amber") | O34: =IF(OR($A34="",$E34=""),"",COUNTIFS($E$6:$E$305,$E34,$D$6:$D$305,"Active")+COUNTIFS($E$6:$E$305,$E34,$D$6:$D$305,"Paused")) | P34: =IF($A34="","",IF($AE34=0,"○ Clear",IF($AA34=1,"△ No owner",IF($AC34=1,"△ Check Sits under",IF($AC34=2,"△ Outside the portfolio",IF($AB34=1,"△ No sponsor",IF($AH34=1,"△ Name used twice",IF($AG34=1,"△ Budget only counts under Portfolio","△ No variance note"))))))&IF($AE34>1," (+"&($AE34-1)&" more)",""))) | Q34: =IF(AND($A34<>"",OR($D34="Active",$D34="Paused")),1,0) | R34: =IFERROR(INDEX($A$6:$A$305,MATCH(27,$S$6:$S$305,0)),"") | S34: =IF(AND($A34<>"",$B34="Program"),COUNTIFS($B$6:$B34,"Program",$A$6:$A34,"<>"),"") | T34: =IF(AND($A34<>"",$B34="Program"),SUMPRODUCT(MAX(($C$6:$C$305=$A34)*($B$6:$B$305="Project")*($D$6:$D$305<>"Proposed")*$I$6:$I$305)),0) | U34: =IF($I34<>"",$I34,IF($T34>0,$T34,"")) | V34: =IF(AND($A34<>"",$B34="Program"),SUMIFS($J$6:$J$305,$C$6:$C$305,$A34,$B$6:$B$305,"Project",$D$6:$D$305,"<>Proposed"),0) | W34: =IF(AND($A34<>"",$B34="Program"),COUNTIFS($C$6:$C$305,$A34,$B$6:$B$305,"Project",$D$6:$D$305,"<>Proposed")-COUNTIFS($C$6:$C$305,$A34,$B$6:$B$305,"Project",$D$6:$D$305,"<>Proposed",$J$6:$J$305,">=0"),0) | X34: =IF(OR($Q34=0,$H34="",$AF34="Sprint"),0,IF(AND($B34="Project",$H34<TODAY()),3,IF($U34="",0,IF($U34<=$H34,1,IF(NETWORKDAYS($H34,$U34)-1>IF($B34="Program",Checks!$B$7,Checks!$B$6),3,2))))) | Y34: =IF(OR($Q34=0,$K34="",$K34=0,$AF34="Sprint"),0,IF(AND($B34="Project",$J34=""),0,IF(IF($B34="Program",$V34,$J34)>$K34*(1+Checks!$B$8),3,IF(IF($B34="Program",$V34,$J34)>$K34,2,IF(AND($B34="Program",OR($W34>0,$V34=0)),0,1))))) | Z34: =IF($A34="",0,IF($C34="Portfolio",1,IF(AND($B34="Project",$C34<>"",$C34<>"Outside the portfolio"),IFERROR(IF(AND(INDEX($B$6:$B$305,MATCH($C34,$A$6:$A$305,0))="Program",INDEX($C$6:$C$305,MATCH($C34,$A$6:$A$305,0))="Portfolio"),1,0),0),0))) | AA34: =IF(AND($A34<>"",$E34="",OR($Q34=1,$D34="Proposed")),1,0) | AB34: =IF(AND($A34<>"",$B34="Program",$F34="",$Q34=1),1,0) | AC34: =IF(OR($A34="",$D34="Completed",$D34="Terminated"),0,IF($C34="",1,IF($C34="Portfolio",0,IF($C34="Outside the portfolio",IF($Q34=1,2,0),IF($B34="Project",IF(IFERROR(INDEX($B$6:$B$305,MATCH($C34,$A$6:$A$305,0)),"")="Program",0,1),1))))) | AD34: =IF(AND($A34<>"",OR($M34="■ Red",$M34="◧ Amber"),$L34=""),1,0) | AE34: =$AA34+$AB34+IF($AC34>0,1,0)+$AD34+$AG34+$AH34 | AG34: =IF(AND($A34<>"",$K34<>"",$C34<>"Portfolio",$D34<>"Completed",$D34<>"Terminated"),1,0) | AH34: =IF(AND($A34<>"",COUNTIF($A$6:$A$305,$A34)>1),1,0) | AI34: =IF(AND($A34<>"",$C34="Portfolio"),COUNTIFS($C$6:$C34,"Portfolio",$A$6:$A34,"<>"),"")
M35: =IF($A35="","",IF($D35="","Not read",IF($Q35=0,"Not counted",IF(MAX($X35,$Y35)=3,"■ Red",IF(MAX($X35,$Y35)=2,"◧ Amber",IF(MAX($X35,$Y35)=1,"□ On track","Not read")))))) | N35: =IF(OR($A35="",$B35<>"Program"),"","■ "&COUNTIFS($C$6:$C$305,$A35,$M$6:$M$305,"■ Red")&" Red, ◧ "&COUNTIFS($C$6:$C$305,$A35,$M$6:$M$305,"◧ Amber")&" Amber") | O35: =IF(OR($A35="",$E35=""),"",COUNTIFS($E$6:$E$305,$E35,$D$6:$D$305,"Active")+COUNTIFS($E$6:$E$305,$E35,$D$6:$D$305,"Paused")) | P35: =IF($A35="","",IF($AE35=0,"○ Clear",IF($AA35=1,"△ No owner",IF($AC35=1,"△ Check Sits under",IF($AC35=2,"△ Outside the portfolio",IF($AB35=1,"△ No sponsor",IF($AH35=1,"△ Name used twice",IF($AG35=1,"△ Budget only counts under Portfolio","△ No variance note"))))))&IF($AE35>1," (+"&($AE35-1)&" more)",""))) | Q35: =IF(AND($A35<>"",OR($D35="Active",$D35="Paused")),1,0) | R35: =IFERROR(INDEX($A$6:$A$305,MATCH(28,$S$6:$S$305,0)),"") | S35: =IF(AND($A35<>"",$B35="Program"),COUNTIFS($B$6:$B35,"Program",$A$6:$A35,"<>"),"") | T35: =IF(AND($A35<>"",$B35="Program"),SUMPRODUCT(MAX(($C$6:$C$305=$A35)*($B$6:$B$305="Project")*($D$6:$D$305<>"Proposed")*$I$6:$I$305)),0) | U35: =IF($I35<>"",$I35,IF($T35>0,$T35,"")) | V35: =IF(AND($A35<>"",$B35="Program"),SUMIFS($J$6:$J$305,$C$6:$C$305,$A35,$B$6:$B$305,"Project",$D$6:$D$305,"<>Proposed"),0) | W35: =IF(AND($A35<>"",$B35="Program"),COUNTIFS($C$6:$C$305,$A35,$B$6:$B$305,"Project",$D$6:$D$305,"<>Proposed")-COUNTIFS($C$6:$C$305,$A35,$B$6:$B$305,"Project",$D$6:$D$305,"<>Proposed",$J$6:$J$305,">=0"),0) | X35: =IF(OR($Q35=0,$H35="",$AF35="Sprint"),0,IF(AND($B35="Project",$H35<TODAY()),3,IF($U35="",0,IF($U35<=$H35,1,IF(NETWORKDAYS($H35,$U35)-1>IF($B35="Program",Checks!$B$7,Checks!$B$6),3,2))))) | Y35: =IF(OR($Q35=0,$K35="",$K35=0,$AF35="Sprint"),0,IF(AND($B35="Project",$J35=""),0,IF(IF($B35="Program",$V35,$J35)>$K35*(1+Checks!$B$8),3,IF(IF($B35="Program",$V35,$J35)>$K35,2,IF(AND($B35="Program",OR($W35>0,$V35=0)),0,1))))) | Z35: =IF($A35="",0,IF($C35="Portfolio",1,IF(AND($B35="Project",$C35<>"",$C35<>"Outside the portfolio"),IFERROR(IF(AND(INDEX($B$6:$B$305,MATCH($C35,$A$6:$A$305,0))="Program",INDEX($C$6:$C$305,MATCH($C35,$A$6:$A$305,0))="Portfolio"),1,0),0),0))) | AA35: =IF(AND($A35<>"",$E35="",OR($Q35=1,$D35="Proposed")),1,0) | AB35: =IF(AND($A35<>"",$B35="Program",$F35="",$Q35=1),1,0) | AC35: =IF(OR($A35="",$D35="Completed",$D35="Terminated"),0,IF($C35="",1,IF($C35="Portfolio",0,IF($C35="Outside the portfolio",IF($Q35=1,2,0),IF($B35="Project",IF(IFERROR(INDEX($B$6:$B$305,MATCH($C35,$A$6:$A$305,0)),"")="Program",0,1),1))))) | AD35: =IF(AND($A35<>"",OR($M35="■ Red",$M35="◧ Amber"),$L35=""),1,0) | AE35: =$AA35+$AB35+IF($AC35>0,1,0)+$AD35+$AG35+$AH35 | AG35: =IF(AND($A35<>"",$K35<>"",$C35<>"Portfolio",$D35<>"Completed",$D35<>"Terminated"),1,0) | AH35: =IF(AND($A35<>"",COUNTIF($A$6:$A$305,$A35)>1),1,0) | AI35: =IF(AND($A35<>"",$C35="Portfolio"),COUNTIFS($C$6:$C35,"Portfolio",$A$6:$A35,"<>"),"")
M36: =IF($A36="","",IF($D36="","Not read",IF($Q36=0,"Not counted",IF(MAX($X36,$Y36)=3,"■ Red",IF(MAX($X36,$Y36)=2,"◧ Amber",IF(MAX($X36,$Y36)=1,"□ On track","Not read")))))) | N36: =IF(OR($A36="",$B36<>"Program"),"","■ "&COUNTIFS($C$6:$C$305,$A36,$M$6:$M$305,"■ Red")&" Red, ◧ "&COUNTIFS($C$6:$C$305,$A36,$M$6:$M$305,"◧ Amber")&" Amber") | O36: =IF(OR($A36="",$E36=""),"",COUNTIFS($E$6:$E$305,$E36,$D$6:$D$305,"Active")+COUNTIFS($E$6:$E$305,$E36,$D$6:$D$305,"Paused")) | P36: =IF($A36="","",IF($AE36=0,"○ Clear",IF($AA36=1,"△ No owner",IF($AC36=1,"△ Check Sits under",IF($AC36=2,"△ Outside the portfolio",IF($AB36=1,"△ No sponsor",IF($AH36=1,"△ Name used twice",IF($AG36=1,"△ Budget only counts under Portfolio","△ No variance note"))))))&IF($AE36>1," (+"&($AE36-1)&" more)",""))) | Q36: =IF(AND($A36<>"",OR($D36="Active",$D36="Paused")),1,0) | R36: =IFERROR(INDEX($A$6:$A$305,MATCH(29,$S$6:$S$305,0)),"") | S36: =IF(AND($A36<>"",$B36="Program"),COUNTIFS($B$6:$B36,"Program",$A$6:$A36,"<>"),"") | T36: =IF(AND($A36<>"",$B36="Program"),SUMPRODUCT(MAX(($C$6:$C$305=$A36)*($B$6:$B$305="Project")*($D$6:$D$305<>"Proposed")*$I$6:$I$305)),0) | U36: =IF($I36<>"",$I36,IF($T36>0,$T36,"")) | V36: =IF(AND($A36<>"",$B36="Program"),SUMIFS($J$6:$J$305,$C$6:$C$305,$A36,$B$6:$B$305,"Project",$D$6:$D$305,"<>Proposed"),0) | W36: =IF(AND($A36<>"",$B36="Program"),COUNTIFS($C$6:$C$305,$A36,$B$6:$B$305,"Project",$D$6:$D$305,"<>Proposed")-COUNTIFS($C$6:$C$305,$A36,$B$6:$B$305,"Project",$D$6:$D$305,"<>Proposed",$J$6:$J$305,">=0"),0) | X36: =IF(OR($Q36=0,$H36="",$AF36="Sprint"),0,IF(AND($B36="Project",$H36<TODAY()),3,IF($U36="",0,IF($U36<=$H36,1,IF(NETWORKDAYS($H36,$U36)-1>IF($B36="Program",Checks!$B$7,Checks!$B$6),3,2))))) | Y36: =IF(OR($Q36=0,$K36="",$K36=0,$AF36="Sprint"),0,IF(AND($B36="Project",$J36=""),0,IF(IF($B36="Program",$V36,$J36)>$K36*(1+Checks!$B$8),3,IF(IF($B36="Program",$V36,$J36)>$K36,2,IF(AND($B36="Program",OR($W36>0,$V36=0)),0,1))))) | Z36: =IF($A36="",0,IF($C36="Portfolio",1,IF(AND($B36="Project",$C36<>"",$C36<>"Outside the portfolio"),IFERROR(IF(AND(INDEX($B$6:$B$305,MATCH($C36,$A$6:$A$305,0))="Program",INDEX($C$6:$C$305,MATCH($C36,$A$6:$A$305,0))="Portfolio"),1,0),0),0))) | AA36: =IF(AND($A36<>"",$E36="",OR($Q36=1,$D36="Proposed")),1,0) | AB36: =IF(AND($A36<>"",$B36="Program",$F36="",$Q36=1),1,0) | AC36: =IF(OR($A36="",$D36="Completed",$D36="Terminated"),0,IF($C36="",1,IF($C36="Portfolio",0,IF($C36="Outside the portfolio",IF($Q36=1,2,0),IF($B36="Project",IF(IFERROR(INDEX($B$6:$B$305,MATCH($C36,$A$6:$A$305,0)),"")="Program",0,1),1))))) | AD36: =IF(AND($A36<>"",OR($M36="■ Red",$M36="◧ Amber"),$L36=""),1,0) | AE36: =$AA36+$AB36+IF($AC36>0,1,0)+$AD36+$AG36+$AH36 | AG36: =IF(AND($A36<>"",$K36<>"",$C36<>"Portfolio",$D36<>"Completed",$D36<>"Terminated"),1,0) | AH36: =IF(AND($A36<>"",COUNTIF($A$6:$A$305,$A36)>1),1,0) | AI36: =IF(AND($A36<>"",$C36="Portfolio"),COUNTIFS($C$6:$C36,"Portfolio",$A$6:$A36,"<>"),"")
M37: =IF($A37="","",IF($D37="","Not read",IF($Q37=0,"Not counted",IF(MAX($X37,$Y37)=3,"■ Red",IF(MAX($X37,$Y37)=2,"◧ Amber",IF(MAX($X37,$Y37)=1,"□ On track","Not read")))))) | N37: =IF(OR($A37="",$B37<>"Program"),"","■ "&COUNTIFS($C$6:$C$305,$A37,$M$6:$M$305,"■ Red")&" Red, ◧ "&COUNTIFS($C$6:$C$305,$A37,$M$6:$M$305,"◧ Amber")&" Amber") | O37: =IF(OR($A37="",$E37=""),"",COUNTIFS($E$6:$E$305,$E37,$D$6:$D$305,"Active")+COUNTIFS($E$6:$E$305,$E37,$D$6:$D$305,"Paused")) | P37: =IF($A37="","",IF($AE37=0,"○ Clear",IF($AA37=1,"△ No owner",IF($AC37=1,"△ Check Sits under",IF($AC37=2,"△ Outside the portfolio",IF($AB37=1,"△ No sponsor",IF($AH37=1,"△ Name used twice",IF($AG37=1,"△ Budget only counts under Portfolio","△ No variance note"))))))&IF($AE37>1," (+"&($AE37-1)&" more)",""))) | Q37: =IF(AND($A37<>"",OR($D37="Active",$D37="Paused")),1,0) | R37: =IFERROR(INDEX($A$6:$A$305,MATCH(30,$S$6:$S$305,0)),"") | S37: =IF(AND($A37<>"",$B37="Program"),COUNTIFS($B$6:$B37,"Program",$A$6:$A37,"<>"),"") | T37: =IF(AND($A37<>"",$B37="Program"),SUMPRODUCT(MAX(($C$6:$C$305=$A37)*($B$6:$B$305="Project")*($D$6:$D$305<>"Proposed")*$I$6:$I$305)),0) | U37: =IF($I37<>"",$I37,IF($T37>0,$T37,"")) | V37: =IF(AND($A37<>"",$B37="Program"),SUMIFS($J$6:$J$305,$C$6:$C$305,$A37,$B$6:$B$305,"Project",$D$6:$D$305,"<>Proposed"),0) | W37: =IF(AND($A37<>"",$B37="Program"),COUNTIFS($C$6:$C$305,$A37,$B$6:$B$305,"Project",$D$6:$D$305,"<>Proposed")-COUNTIFS($C$6:$C$305,$A37,$B$6:$B$305,"Project",$D$6:$D$305,"<>Proposed",$J$6:$J$305,">=0"),0) | X37: =IF(OR($Q37=0,$H37="",$AF37="Sprint"),0,IF(AND($B37="Project",$H37<TODAY()),3,IF($U37="",0,IF($U37<=$H37,1,IF(NETWORKDAYS($H37,$U37)-1>IF($B37="Program",Checks!$B$7,Checks!$B$6),3,2))))) | Y37: =IF(OR($Q37=0,$K37="",$K37=0,$AF37="Sprint"),0,IF(AND($B37="Project",$J37=""),0,IF(IF($B37="Program",$V37,$J37)>$K37*(1+Checks!$B$8),3,IF(IF($B37="Program",$V37,$J37)>$K37,2,IF(AND($B37="Program",OR($W37>0,$V37=0)),0,1))))) | Z37: =IF($A37="",0,IF($C37="Portfolio",1,IF(AND($B37="Project",$C37<>"",$C37<>"Outside the portfolio"),IFERROR(IF(AND(INDEX($B$6:$B$305,MATCH($C37,$A$6:$A$305,0))="Program",INDEX($C$6:$C$305,MATCH($C37,$A$6:$A$305,0))="Portfolio"),1,0),0),0))) | AA37: =IF(AND($A37<>"",$E37="",OR($Q37=1,$D37="Proposed")),1,0) | AB37: =IF(AND($A37<>"",$B37="Program",$F37="",$Q37=1),1,0) | AC37: =IF(OR($A37="",$D37="Completed",$D37="Terminated"),0,IF($C37="",1,IF($C37="Portfolio",0,IF($C37="Outside the portfolio",IF($Q37=1,2,0),IF($B37="Project",IF(IFERROR(INDEX($B$6:$B$305,MATCH($C37,$A$6:$A$305,0)),"")="Program",0,1),1))))) | AD37: =IF(AND($A37<>"",OR($M37="■ Red",$M37="◧ Amber"),$L37=""),1,0) | AE37: =$AA37+$AB37+IF($AC37>0,1,0)+$AD37+$AG37+$AH37 | AG37: =IF(AND($A37<>"",$K37<>"",$C37<>"Portfolio",$D37<>"Completed",$D37<>"Terminated"),1,0) | AH37: =IF(AND($A37<>"",COUNTIF($A$6:$A$305,$A37)>1),1,0) | AI37: =IF(AND($A37<>"",$C37="Portfolio"),COUNTIFS($C$6:$C37,"Portfolio",$A$6:$A37,"<>"),"")
M38: =IF($A38="","",IF($D38="","Not read",IF($Q38=0,"Not counted",IF(MAX($X38,$Y38)=3,"■ Red",IF(MAX($X38,$Y38)=2,"◧ Amber",IF(MAX($X38,$Y38)=1,"□ On track","Not read")))))) | N38: =IF(OR($A38="",$B38<>"Program"),"","■ "&COUNTIFS($C$6:$C$305,$A38,$M$6:$M$305,"■ Red")&" Red, ◧ "&COUNTIFS($C$6:$C$305,$A38,$M$6:$M$305,"◧ Amber")&" Amber") | O38: =IF(OR($A38="",$E38=""),"",COUNTIFS($E$6:$E$305,$E38,$D$6:$D$305,"Active")+COUNTIFS($E$6:$E$305,$E38,$D$6:$D$305,"Paused")) | P38: =IF($A38="","",IF($AE38=0,"○ Clear",IF($AA38=1,"△ No owner",IF($AC38=1,"△ Check Sits under",IF($AC38=2,"△ Outside the portfolio",IF($AB38=1,"△ No sponsor",IF($AH38=1,"△ Name used twice",IF($AG38=1,"△ Budget only counts under Portfolio","△ No variance note"))))))&IF($AE38>1," (+"&($AE38-1)&" more)",""))) | Q38: =IF(AND($A38<>"",OR($D38="Active",$D38="Paused")),1,0) | R38: =IFERROR(INDEX($A$6:$A$305,MATCH(31,$S$6:$S$305,0)),"") | S38: =IF(AND($A38<>"",$B38="Program"),COUNTIFS($B$6:$B38,"Program",$A$6:$A38,"<>"),"") | T38: =IF(AND($A38<>"",$B38="Program"),SUMPRODUCT(MAX(($C$6:$C$305=$A38)*($B$6:$B$305="Project")*($D$6:$D$305<>"Proposed")*$I$6:$I$305)),0) | U38: =IF($I38<>"",$I38,IF($T38>0,$T38,"")) | V38: =IF(AND($A38<>"",$B38="Program"),SUMIFS($J$6:$J$305,$C$6:$C$305,$A38,$B$6:$B$305,"Project",$D$6:$D$305,"<>Proposed"),0) | W38: =IF(AND($A38<>"",$B38="Program"),COUNTIFS($C$6:$C$305,$A38,$B$6:$B$305,"Project",$D$6:$D$305,"<>Proposed")-COUNTIFS($C$6:$C$305,$A38,$B$6:$B$305,"Project",$D$6:$D$305,"<>Proposed",$J$6:$J$305,">=0"),0) | X38: =IF(OR($Q38=0,$H38="",$AF38="Sprint"),0,IF(AND($B38="Project",$H38<TODAY()),3,IF($U38="",0,IF($U38<=$H38,1,IF(NETWORKDAYS($H38,$U38)-1>IF($B38="Program",Checks!$B$7,Checks!$B$6),3,2))))) | Y38: =IF(OR($Q38=0,$K38="",$K38=0,$AF38="Sprint"),0,IF(AND($B38="Project",$J38=""),0,IF(IF($B38="Program",$V38,$J38)>$K38*(1+Checks!$B$8),3,IF(IF($B38="Program",$V38,$J38)>$K38,2,IF(AND($B38="Program",OR($W38>0,$V38=0)),0,1))))) | Z38: =IF($A38="",0,IF($C38="Portfolio",1,IF(AND($B38="Project",$C38<>"",$C38<>"Outside the portfolio"),IFERROR(IF(AND(INDEX($B$6:$B$305,MATCH($C38,$A$6:$A$305,0))="Program",INDEX($C$6:$C$305,MATCH($C38,$A$6:$A$305,0))="Portfolio"),1,0),0),0))) | AA38: =IF(AND($A38<>"",$E38="",OR($Q38=1,$D38="Proposed")),1,0) | AB38: =IF(AND($A38<>"",$B38="Program",$F38="",$Q38=1),1,0) | AC38: =IF(OR($A38="",$D38="Completed",$D38="Terminated"),0,IF($C38="",1,IF($C38="Portfolio",0,IF($C38="Outside the portfolio",IF($Q38=1,2,0),IF($B38="Project",IF(IFERROR(INDEX($B$6:$B$305,MATCH($C38,$A$6:$A$305,0)),"")="Program",0,1),1))))) | AD38: =IF(AND($A38<>"",OR($M38="■ Red",$M38="◧ Amber"),$L38=""),1,0) | AE38: =$AA38+$AB38+IF($AC38>0,1,0)+$AD38+$AG38+$AH38 | AG38: =IF(AND($A38<>"",$K38<>"",$C38<>"Portfolio",$D38<>"Completed",$D38<>"Terminated"),1,0) | AH38: =IF(AND($A38<>"",COUNTIF($A$6:$A$305,$A38)>1),1,0) | AI38: =IF(AND($A38<>"",$C38="Portfolio"),COUNTIFS($C$6:$C38,"Portfolio",$A$6:$A38,"<>"),"")
M39: =IF($A39="","",IF($D39="","Not read",IF($Q39=0,"Not counted",IF(MAX($X39,$Y39)=3,"■ Red",IF(MAX($X39,$Y39)=2,"◧ Amber",IF(MAX($X39,$Y39)=1,"□ On track","Not read")))))) | N39: =IF(OR($A39="",$B39<>"Program"),"","■ "&COUNTIFS($C$6:$C$305,$A39,$M$6:$M$305,"■ Red")&" Red, ◧ "&COUNTIFS($C$6:$C$305,$A39,$M$6:$M$305,"◧ Amber")&" Amber") | O39: =IF(OR($A39="",$E39=""),"",COUNTIFS($E$6:$E$305,$E39,$D$6:$D$305,"Active")+COUNTIFS($E$6:$E$305,$E39,$D$6:$D$305,"Paused")) | P39: =IF($A39="","",IF($AE39=0,"○ Clear",IF($AA39=1,"△ No owner",IF($AC39=1,"△ Check Sits under",IF($AC39=2,"△ Outside the portfolio",IF($AB39=1,"△ No sponsor",IF($AH39=1,"△ Name used twice",IF($AG39=1,"△ Budget only counts under Portfolio","△ No variance note"))))))&IF($AE39>1," (+"&($AE39-1)&" more)",""))) | Q39: =IF(AND($A39<>"",OR($D39="Active",$D39="Paused")),1,0) | R39: =IFERROR(INDEX($A$6:$A$305,MATCH(32,$S$6:$S$305,0)),"") | S39: =IF(AND($A39<>"",$B39="Program"),COUNTIFS($B$6:$B39,"Program",$A$6:$A39,"<>"),"") | T39: =IF(AND($A39<>"",$B39="Program"),SUMPRODUCT(MAX(($C$6:$C$305=$A39)*($B$6:$B$305="Project")*($D$6:$D$305<>"Proposed")*$I$6:$I$305)),0) | U39: =IF($I39<>"",$I39,IF($T39>0,$T39,"")) | V39: =IF(AND($A39<>"",$B39="Program"),SUMIFS($J$6:$J$305,$C$6:$C$305,$A39,$B$6:$B$305,"Project",$D$6:$D$305,"<>Proposed"),0) | W39: =IF(AND($A39<>"",$B39="Program"),COUNTIFS($C$6:$C$305,$A39,$B$6:$B$305,"Project",$D$6:$D$305,"<>Proposed")-COUNTIFS($C$6:$C$305,$A39,$B$6:$B$305,"Project",$D$6:$D$305,"<>Proposed",$J$6:$J$305,">=0"),0) | X39: =IF(OR($Q39=0,$H39="",$AF39="Sprint"),0,IF(AND($B39="Project",$H39<TODAY()),3,IF($U39="",0,IF($U39<=$H39,1,IF(NETWORKDAYS($H39,$U39)-1>IF($B39="Program",Checks!$B$7,Checks!$B$6),3,2))))) | Y39: =IF(OR($Q39=0,$K39="",$K39=0,$AF39="Sprint"),0,IF(AND($B39="Project",$J39=""),0,IF(IF($B39="Program",$V39,$J39)>$K39*(1+Checks!$B$8),3,IF(IF($B39="Program",$V39,$J39)>$K39,2,IF(AND($B39="Program",OR($W39>0,$V39=0)),0,1))))) | Z39: =IF($A39="",0,IF($C39="Portfolio",1,IF(AND($B39="Project",$C39<>"",$C39<>"Outside the portfolio"),IFERROR(IF(AND(INDEX($B$6:$B$305,MATCH($C39,$A$6:$A$305,0))="Program",INDEX($C$6:$C$305,MATCH($C39,$A$6:$A$305,0))="Portfolio"),1,0),0),0))) | AA39: =IF(AND($A39<>"",$E39="",OR($Q39=1,$D39="Proposed")),1,0) | AB39: =IF(AND($A39<>"",$B39="Program",$F39="",$Q39=1),1,0) | AC39: =IF(OR($A39="",$D39="Completed",$D39="Terminated"),0,IF($C39="",1,IF($C39="Portfolio",0,IF($C39="Outside the portfolio",IF($Q39=1,2,0),IF($B39="Project",IF(IFERROR(INDEX($B$6:$B$305,MATCH($C39,$A$6:$A$305,0)),"")="Program",0,1),1))))) | AD39: =IF(AND($A39<>"",OR($M39="■ Red",$M39="◧ Amber"),$L39=""),1,0) | AE39: =$AA39+$AB39+IF($AC39>0,1,0)+$AD39+$AG39+$AH39 | AG39: =IF(AND($A39<>"",$K39<>"",$C39<>"Portfolio",$D39<>"Completed",$D39<>"Terminated"),1,0) | AH39: =IF(AND($A39<>"",COUNTIF($A$6:$A$305,$A39)>1),1,0) | AI39: =IF(AND($A39<>"",$C39="Portfolio"),COUNTIFS($C$6:$C39,"Portfolio",$A$6:$A39,"<>"),"")
M40: =IF($A40="","",IF($D40="","Not read",IF($Q40=0,"Not counted",IF(MAX($X40,$Y40)=3,"■ Red",IF(MAX($X40,$Y40)=2,"◧ Amber",IF(MAX($X40,$Y40)=1,"□ On track","Not read")))))) | N40: =IF(OR($A40="",$B40<>"Program"),"","■ "&COUNTIFS($C$6:$C$305,$A40,$M$6:$M$305,"■ Red")&" Red, ◧ "&COUNTIFS($C$6:$C$305,$A40,$M$6:$M$305,"◧ Amber")&" Amber") | O40: =IF(OR($A40="",$E40=""),"",COUNTIFS($E$6:$E$305,$E40,$D$6:$D$305,"Active")+COUNTIFS($E$6:$E$305,$E40,$D$6:$D$305,"Paused")) | P40: =IF($A40="","",IF($AE40=0,"○ Clear",IF($AA40=1,"△ No owner",IF($AC40=1,"△ Check Sits under",IF($AC40=2,"△ Outside the portfolio",IF($AB40=1,"△ No sponsor",IF($AH40=1,"△ Name used twice",IF($AG40=1,"△ Budget only counts under Portfolio","△ No variance note"))))))&IF($AE40>1," (+"&($AE40-1)&" more)",""))) | Q40: =IF(AND($A40<>"",OR($D40="Active",$D40="Paused")),1,0) | R40: =IFERROR(INDEX($A$6:$A$305,MATCH(33,$S$6:$S$305,0)),"") | S40: =IF(AND($A40<>"",$B40="Program"),COUNTIFS($B$6:$B40,"Program",$A$6:$A40,"<>"),"") | T40: =IF(AND($A40<>"",$B40="Program"),SUMPRODUCT(MAX(($C$6:$C$305=$A40)*($B$6:$B$305="Project")*($D$6:$D$305<>"Proposed")*$I$6:$I$305)),0) | U40: =IF($I40<>"",$I40,IF($T40>0,$T40,"")) | V40: =IF(AND($A40<>"",$B40="Program"),SUMIFS($J$6:$J$305,$C$6:$C$305,$A40,$B$6:$B$305,"Project",$D$6:$D$305,"<>Proposed"),0) | W40: =IF(AND($A40<>"",$B40="Program"),COUNTIFS($C$6:$C$305,$A40,$B$6:$B$305,"Project",$D$6:$D$305,"<>Proposed")-COUNTIFS($C$6:$C$305,$A40,$B$6:$B$305,"Project",$D$6:$D$305,"<>Proposed",$J$6:$J$305,">=0"),0) | X40: =IF(OR($Q40=0,$H40="",$AF40="Sprint"),0,IF(AND($B40="Project",$H40<TODAY()),3,IF($U40="",0,IF($U40<=$H40,1,IF(NETWORKDAYS($H40,$U40)-1>IF($B40="Program",Checks!$B$7,Checks!$B$6),3,2))))) | Y40: =IF(OR($Q40=0,$K40="",$K40=0,$AF40="Sprint"),0,IF(AND($B40="Project",$J40=""),0,IF(IF($B40="Program",$V40,$J40)>$K40*(1+Checks!$B$8),3,IF(IF($B40="Program",$V40,$J40)>$K40,2,IF(AND($B40="Program",OR($W40>0,$V40=0)),0,1))))) | Z40: =IF($A40="",0,IF($C40="Portfolio",1,IF(AND($B40="Project",$C40<>"",$C40<>"Outside the portfolio"),IFERROR(IF(AND(INDEX($B$6:$B$305,MATCH($C40,$A$6:$A$305,0))="Program",INDEX($C$6:$C$305,MATCH($C40,$A$6:$A$305,0))="Portfolio"),1,0),0),0))) | AA40: =IF(AND($A40<>"",$E40="",OR($Q40=1,$D40="Proposed")),1,0) | AB40: =IF(AND($A40<>"",$B40="Program",$F40="",$Q40=1),1,0) | AC40: =IF(OR($A40="",$D40="Completed",$D40="Terminated"),0,IF($C40="",1,IF($C40="Portfolio",0,IF($C40="Outside the portfolio",IF($Q40=1,2,0),IF($B40="Project",IF(IFERROR(INDEX($B$6:$B$305,MATCH($C40,$A$6:$A$305,0)),"")="Program",0,1),1))))) | AD40: =IF(AND($A40<>"",OR($M40="■ Red",$M40="◧ Amber"),$L40=""),1,0) | AE40: =$AA40+$AB40+IF($AC40>0,1,0)+$AD40+$AG40+$AH40 | AG40: =IF(AND($A40<>"",$K40<>"",$C40<>"Portfolio",$D40<>"Completed",$D40<>"Terminated"),1,0) | AH40: =IF(AND($A40<>"",COUNTIF($A$6:$A$305,$A40)>1),1,0) | AI40: =IF(AND($A40<>"",$C40="Portfolio"),COUNTIFS($C$6:$C40,"Portfolio",$A$6:$A40,"<>"),"")
M41: =IF($A41="","",IF($D41="","Not read",IF($Q41=0,"Not counted",IF(MAX($X41,$Y41)=3,"■ Red",IF(MAX($X41,$Y41)=2,"◧ Amber",IF(MAX($X41,$Y41)=1,"□ On track","Not read")))))) | N41: =IF(OR($A41="",$B41<>"Program"),"","■ "&COUNTIFS($C$6:$C$305,$A41,$M$6:$M$305,"■ Red")&" Red, ◧ "&COUNTIFS($C$6:$C$305,$A41,$M$6:$M$305,"◧ Amber")&" Amber") | O41: =IF(OR($A41="",$E41=""),"",COUNTIFS($E$6:$E$305,$E41,$D$6:$D$305,"Active")+COUNTIFS($E$6:$E$305,$E41,$D$6:$D$305,"Paused")) | P41: =IF($A41="","",IF($AE41=0,"○ Clear",IF($AA41=1,"△ No owner",IF($AC41=1,"△ Check Sits under",IF($AC41=2,"△ Outside the portfolio",IF($AB41=1,"△ No sponsor",IF($AH41=1,"△ Name used twice",IF($AG41=1,"△ Budget only counts under Portfolio","△ No variance note"))))))&IF($AE41>1," (+"&($AE41-1)&" more)",""))) | Q41: =IF(AND($A41<>"",OR($D41="Active",$D41="Paused")),1,0) | R41: =IFERROR(INDEX($A$6:$A$305,MATCH(34,$S$6:$S$305,0)),"") | S41: =IF(AND($A41<>"",$B41="Program"),COUNTIFS($B$6:$B41,"Program",$A$6:$A41,"<>"),"") | T41: =IF(AND($A41<>"",$B41="Program"),SUMPRODUCT(MAX(($C$6:$C$305=$A41)*($B$6:$B$305="Project")*($D$6:$D$305<>"Proposed")*$I$6:$I$305)),0) | U41: =IF($I41<>"",$I41,IF($T41>0,$T41,"")) | V41: =IF(AND($A41<>"",$B41="Program"),SUMIFS($J$6:$J$305,$C$6:$C$305,$A41,$B$6:$B$305,"Project",$D$6:$D$305,"<>Proposed"),0) | W41: =IF(AND($A41<>"",$B41="Program"),COUNTIFS($C$6:$C$305,$A41,$B$6:$B$305,"Project",$D$6:$D$305,"<>Proposed")-COUNTIFS($C$6:$C$305,$A41,$B$6:$B$305,"Project",$D$6:$D$305,"<>Proposed",$J$6:$J$305,">=0"),0) | X41: =IF(OR($Q41=0,$H41="",$AF41="Sprint"),0,IF(AND($B41="Project",$H41<TODAY()),3,IF($U41="",0,IF($U41<=$H41,1,IF(NETWORKDAYS($H41,$U41)-1>IF($B41="Program",Checks!$B$7,Checks!$B$6),3,2))))) | Y41: =IF(OR($Q41=0,$K41="",$K41=0,$AF41="Sprint"),0,IF(AND($B41="Project",$J41=""),0,IF(IF($B41="Program",$V41,$J41)>$K41*(1+Checks!$B$8),3,IF(IF($B41="Program",$V41,$J41)>$K41,2,IF(AND($B41="Program",OR($W41>0,$V41=0)),0,1))))) | Z41: =IF($A41="",0,IF($C41="Portfolio",1,IF(AND($B41="Project",$C41<>"",$C41<>"Outside the portfolio"),IFERROR(IF(AND(INDEX($B$6:$B$305,MATCH($C41,$A$6:$A$305,0))="Program",INDEX($C$6:$C$305,MATCH($C41,$A$6:$A$305,0))="Portfolio"),1,0),0),0))) | AA41: =IF(AND($A41<>"",$E41="",OR($Q41=1,$D41="Proposed")),1,0) | AB41: =IF(AND($A41<>"",$B41="Program",$F41="",$Q41=1),1,0) | AC41: =IF(OR($A41="",$D41="Completed",$D41="Terminated"),0,IF($C41="",1,IF($C41="Portfolio",0,IF($C41="Outside the portfolio",IF($Q41=1,2,0),IF($B41="Project",IF(IFERROR(INDEX($B$6:$B$305,MATCH($C41,$A$6:$A$305,0)),"")="Program",0,1),1))))) | AD41: =IF(AND($A41<>"",OR($M41="■ Red",$M41="◧ Amber"),$L41=""),1,0) | AE41: =$AA41+$AB41+IF($AC41>0,1,0)+$AD41+$AG41+$AH41 | AG41: =IF(AND($A41<>"",$K41<>"",$C41<>"Portfolio",$D41<>"Completed",$D41<>"Terminated"),1,0) | AH41: =IF(AND($A41<>"",COUNTIF($A$6:$A$305,$A41)>1),1,0) | AI41: =IF(AND($A41<>"",$C41="Portfolio"),COUNTIFS($C$6:$C41,"Portfolio",$A$6:$A41,"<>"),"")
M42: =IF($A42="","",IF($D42="","Not read",IF($Q42=0,"Not counted",IF(MAX($X42,$Y42)=3,"■ Red",IF(MAX($X42,$Y42)=2,"◧ Amber",IF(MAX($X42,$Y42)=1,"□ On track","Not read")))))) | N42: =IF(OR($A42="",$B42<>"Program"),"","■ "&COUNTIFS($C$6:$C$305,$A42,$M$6:$M$305,"■ Red")&" Red, ◧ "&COUNTIFS($C$6:$C$305,$A42,$M$6:$M$305,"◧ Amber")&" Amber") | O42: =IF(OR($A42="",$E42=""),"",COUNTIFS($E$6:$E$305,$E42,$D$6:$D$305,"Active")+COUNTIFS($E$6:$E$305,$E42,$D$6:$D$305,"Paused")) | P42: =IF($A42="","",IF($AE42=0,"○ Clear",IF($AA42=1,"△ No owner",IF($AC42=1,"△ Check Sits under",IF($AC42=2,"△ Outside the portfolio",IF($AB42=1,"△ No sponsor",IF($AH42=1,"△ Name used twice",IF($AG42=1,"△ Budget only counts under Portfolio","△ No variance note"))))))&IF($AE42>1," (+"&($AE42-1)&" more)",""))) | Q42: =IF(AND($A42<>"",OR($D42="Active",$D42="Paused")),1,0) | R42: =IFERROR(INDEX($A$6:$A$305,MATCH(35,$S$6:$S$305,0)),"") | S42: =IF(AND($A42<>"",$B42="Program"),COUNTIFS($B$6:$B42,"Program",$A$6:$A42,"<>"),"") | T42: =IF(AND($A42<>"",$B42="Program"),SUMPRODUCT(MAX(($C$6:$C$305=$A42)*($B$6:$B$305="Project")*($D$6:$D$305<>"Proposed")*$I$6:$I$305)),0) | U42: =IF($I42<>"",$I42,IF($T42>0,$T42,"")) | V42: =IF(AND($A42<>"",$B42="Program"),SUMIFS($J$6:$J$305,$C$6:$C$305,$A42,$B$6:$B$305,"Project",$D$6:$D$305,"<>Proposed"),0) | W42: =IF(AND($A42<>"",$B42="Program"),COUNTIFS($C$6:$C$305,$A42,$B$6:$B$305,"Project",$D$6:$D$305,"<>Proposed")-COUNTIFS($C$6:$C$305,$A42,$B$6:$B$305,"Project",$D$6:$D$305,"<>Proposed",$J$6:$J$305,">=0"),0) | X42: =IF(OR($Q42=0,$H42="",$AF42="Sprint"),0,IF(AND($B42="Project",$H42<TODAY()),3,IF($U42="",0,IF($U42<=$H42,1,IF(NETWORKDAYS($H42,$U42)-1>IF($B42="Program",Checks!$B$7,Checks!$B$6),3,2))))) | Y42: =IF(OR($Q42=0,$K42="",$K42=0,$AF42="Sprint"),0,IF(AND($B42="Project",$J42=""),0,IF(IF($B42="Program",$V42,$J42)>$K42*(1+Checks!$B$8),3,IF(IF($B42="Program",$V42,$J42)>$K42,2,IF(AND($B42="Program",OR($W42>0,$V42=0)),0,1))))) | Z42: =IF($A42="",0,IF($C42="Portfolio",1,IF(AND($B42="Project",$C42<>"",$C42<>"Outside the portfolio"),IFERROR(IF(AND(INDEX($B$6:$B$305,MATCH($C42,$A$6:$A$305,0))="Program",INDEX($C$6:$C$305,MATCH($C42,$A$6:$A$305,0))="Portfolio"),1,0),0),0))) | AA42: =IF(AND($A42<>"",$E42="",OR($Q42=1,$D42="Proposed")),1,0) | AB42: =IF(AND($A42<>"",$B42="Program",$F42="",$Q42=1),1,0) | AC42: =IF(OR($A42="",$D42="Completed",$D42="Terminated"),0,IF($C42="",1,IF($C42="Portfolio",0,IF($C42="Outside the portfolio",IF($Q42=1,2,0),IF($B42="Project",IF(IFERROR(INDEX($B$6:$B$305,MATCH($C42,$A$6:$A$305,0)),"")="Program",0,1),1))))) | AD42: =IF(AND($A42<>"",OR($M42="■ Red",$M42="◧ Amber"),$L42=""),1,0) | AE42: =$AA42+$AB42+IF($AC42>0,1,0)+$AD42+$AG42+$AH42 | AG42: =IF(AND($A42<>"",$K42<>"",$C42<>"Portfolio",$D42<>"Completed",$D42<>"Terminated"),1,0) | AH42: =IF(AND($A42<>"",COUNTIF($A$6:$A$305,$A42)>1),1,0) | AI42: =IF(AND($A42<>"",$C42="Portfolio"),COUNTIFS($C$6:$C42,"Portfolio",$A$6:$A42,"<>"),"")
M43: =IF($A43="","",IF($D43="","Not read",IF($Q43=0,"Not counted",IF(MAX($X43,$Y43)=3,"■ Red",IF(MAX($X43,$Y43)=2,"◧ Amber",IF(MAX($X43,$Y43)=1,"□ On track","Not read")))))) | N43: =IF(OR($A43="",$B43<>"Program"),"","■ "&COUNTIFS($C$6:$C$305,$A43,$M$6:$M$305,"■ Red")&" Red, ◧ "&COUNTIFS($C$6:$C$305,$A43,$M$6:$M$305,"◧ Amber")&" Amber") | O43: =IF(OR($A43="",$E43=""),"",COUNTIFS($E$6:$E$305,$E43,$D$6:$D$305,"Active")+COUNTIFS($E$6:$E$305,$E43,$D$6:$D$305,"Paused")) | P43: =IF($A43="","",IF($AE43=0,"○ Clear",IF($AA43=1,"△ No owner",IF($AC43=1,"△ Check Sits under",IF($AC43=2,"△ Outside the portfolio",IF($AB43=1,"△ No sponsor",IF($AH43=1,"△ Name used twice",IF($AG43=1,"△ Budget only counts under Portfolio","△ No variance note"))))))&IF($AE43>1," (+"&($AE43-1)&" more)",""))) | Q43: =IF(AND($A43<>"",OR($D43="Active",$D43="Paused")),1,0) | R43: =IFERROR(INDEX($A$6:$A$305,MATCH(36,$S$6:$S$305,0)),"") | S43: =IF(AND($A43<>"",$B43="Program"),COUNTIFS($B$6:$B43,"Program",$A$6:$A43,"<>"),"") | T43: =IF(AND($A43<>"",$B43="Program"),SUMPRODUCT(MAX(($C$6:$C$305=$A43)*($B$6:$B$305="Project")*($D$6:$D$305<>"Proposed")*$I$6:$I$305)),0) | U43: =IF($I43<>"",$I43,IF($T43>0,$T43,"")) | V43: =IF(AND($A43<>"",$B43="Program"),SUMIFS($J$6:$J$305,$C$6:$C$305,$A43,$B$6:$B$305,"Project",$D$6:$D$305,"<>Proposed"),0) | W43: =IF(AND($A43<>"",$B43="Program"),COUNTIFS($C$6:$C$305,$A43,$B$6:$B$305,"Project",$D$6:$D$305,"<>Proposed")-COUNTIFS($C$6:$C$305,$A43,$B$6:$B$305,"Project",$D$6:$D$305,"<>Proposed",$J$6:$J$305,">=0"),0) | X43: =IF(OR($Q43=0,$H43="",$AF43="Sprint"),0,IF(AND($B43="Project",$H43<TODAY()),3,IF($U43="",0,IF($U43<=$H43,1,IF(NETWORKDAYS($H43,$U43)-1>IF($B43="Program",Checks!$B$7,Checks!$B$6),3,2))))) | Y43: =IF(OR($Q43=0,$K43="",$K43=0,$AF43="Sprint"),0,IF(AND($B43="Project",$J43=""),0,IF(IF($B43="Program",$V43,$J43)>$K43*(1+Checks!$B$8),3,IF(IF($B43="Program",$V43,$J43)>$K43,2,IF(AND($B43="Program",OR($W43>0,$V43=0)),0,1))))) | Z43: =IF($A43="",0,IF($C43="Portfolio",1,IF(AND($B43="Project",$C43<>"",$C43<>"Outside the portfolio"),IFERROR(IF(AND(INDEX($B$6:$B$305,MATCH($C43,$A$6:$A$305,0))="Program",INDEX($C$6:$C$305,MATCH($C43,$A$6:$A$305,0))="Portfolio"),1,0),0),0))) | AA43: =IF(AND($A43<>"",$E43="",OR($Q43=1,$D43="Proposed")),1,0) | AB43: =IF(AND($A43<>"",$B43="Program",$F43="",$Q43=1),1,0) | AC43: =IF(OR($A43="",$D43="Completed",$D43="Terminated"),0,IF($C43="",1,IF($C43="Portfolio",0,IF($C43="Outside the portfolio",IF($Q43=1,2,0),IF($B43="Project",IF(IFERROR(INDEX($B$6:$B$305,MATCH($C43,$A$6:$A$305,0)),"")="Program",0,1),1))))) | AD43: =IF(AND($A43<>"",OR($M43="■ Red",$M43="◧ Amber"),$L43=""),1,0) | AE43: =$AA43+$AB43+IF($AC43>0,1,0)+$AD43+$AG43+$AH43 | AG43: =IF(AND($A43<>"",$K43<>"",$C43<>"Portfolio",$D43<>"Completed",$D43<>"Terminated"),1,0) | AH43: =IF(AND($A43<>"",COUNTIF($A$6:$A$305,$A43)>1),1,0) | AI43: =IF(AND($A43<>"",$C43="Portfolio"),COUNTIFS($C$6:$C43,"Portfolio",$A$6:$A43,"<>"),"")
M44: =IF($A44="","",IF($D44="","Not read",IF($Q44=0,"Not counted",IF(MAX($X44,$Y44)=3,"■ Red",IF(MAX($X44,$Y44)=2,"◧ Amber",IF(MAX($X44,$Y44)=1,"□ On track","Not read")))))) | N44: =IF(OR($A44="",$B44<>"Program"),"","■ "&COUNTIFS($C$6:$C$305,$A44,$M$6:$M$305,"■ Red")&" Red, ◧ "&COUNTIFS($C$6:$C$305,$A44,$M$6:$M$305,"◧ Amber")&" Amber") | O44: =IF(OR($A44="",$E44=""),"",COUNTIFS($E$6:$E$305,$E44,$D$6:$D$305,"Active")+COUNTIFS($E$6:$E$305,$E44,$D$6:$D$305,"Paused")) | P44: =IF($A44="","",IF($AE44=0,"○ Clear",IF($AA44=1,"△ No owner",IF($AC44=1,"△ Check Sits under",IF($AC44=2,"△ Outside the portfolio",IF($AB44=1,"△ No sponsor",IF($AH44=1,"△ Name used twice",IF($AG44=1,"△ Budget only counts under Portfolio","△ No variance note"))))))&IF($AE44>1," (+"&($AE44-1)&" more)",""))) | Q44: =IF(AND($A44<>"",OR($D44="Active",$D44="Paused")),1,0) | R44: =IFERROR(INDEX($A$6:$A$305,MATCH(37,$S$6:$S$305,0)),"") | S44: =IF(AND($A44<>"",$B44="Program"),COUNTIFS($B$6:$B44,"Program",$A$6:$A44,"<>"),"") | T44: =IF(AND($A44<>"",$B44="Program"),SUMPRODUCT(MAX(($C$6:$C$305=$A44)*($B$6:$B$305="Project")*($D$6:$D$305<>"Proposed")*$I$6:$I$305)),0) | U44: =IF($I44<>"",$I44,IF($T44>0,$T44,"")) | V44: =IF(AND($A44<>"",$B44="Program"),SUMIFS($J$6:$J$305,$C$6:$C$305,$A44,$B$6:$B$305,"Project",$D$6:$D$305,"<>Proposed"),0) | W44: =IF(AND($A44<>"",$B44="Program"),COUNTIFS($C$6:$C$305,$A44,$B$6:$B$305,"Project",$D$6:$D$305,"<>Proposed")-COUNTIFS($C$6:$C$305,$A44,$B$6:$B$305,"Project",$D$6:$D$305,"<>Proposed",$J$6:$J$305,">=0"),0) | X44: =IF(OR($Q44=0,$H44="",$AF44="Sprint"),0,IF(AND($B44="Project",$H44<TODAY()),3,IF($U44="",0,IF($U44<=$H44,1,IF(NETWORKDAYS($H44,$U44)-1>IF($B44="Program",Checks!$B$7,Checks!$B$6),3,2))))) | Y44: =IF(OR($Q44=0,$K44="",$K44=0,$AF44="Sprint"),0,IF(AND($B44="Project",$J44=""),0,IF(IF($B44="Program",$V44,$J44)>$K44*(1+Checks!$B$8),3,IF(IF($B44="Program",$V44,$J44)>$K44,2,IF(AND($B44="Program",OR($W44>0,$V44=0)),0,1))))) | Z44: =IF($A44="",0,IF($C44="Portfolio",1,IF(AND($B44="Project",$C44<>"",$C44<>"Outside the portfolio"),IFERROR(IF(AND(INDEX($B$6:$B$305,MATCH($C44,$A$6:$A$305,0))="Program",INDEX($C$6:$C$305,MATCH($C44,$A$6:$A$305,0))="Portfolio"),1,0),0),0))) | AA44: =IF(AND($A44<>"",$E44="",OR($Q44=1,$D44="Proposed")),1,0) | AB44: =IF(AND($A44<>"",$B44="Program",$F44="",$Q44=1),1,0) | AC44: =IF(OR($A44="",$D44="Completed",$D44="Terminated"),0,IF($C44="",1,IF($C44="Portfolio",0,IF($C44="Outside the portfolio",IF($Q44=1,2,0),IF($B44="Project",IF(IFERROR(INDEX($B$6:$B$305,MATCH($C44,$A$6:$A$305,0)),"")="Program",0,1),1))))) | AD44: =IF(AND($A44<>"",OR($M44="■ Red",$M44="◧ Amber"),$L44=""),1,0) | AE44: =$AA44+$AB44+IF($AC44>0,1,0)+$AD44+$AG44+$AH44 | AG44: =IF(AND($A44<>"",$K44<>"",$C44<>"Portfolio",$D44<>"Completed",$D44<>"Terminated"),1,0) | AH44: =IF(AND($A44<>"",COUNTIF($A$6:$A$305,$A44)>1),1,0) | AI44: =IF(AND($A44<>"",$C44="Portfolio"),COUNTIFS($C$6:$C44,"Portfolio",$A$6:$A44,"<>"),"")
M45: =IF($A45="","",IF($D45="","Not read",IF($Q45=0,"Not counted",IF(MAX($X45,$Y45)=3,"■ Red",IF(MAX($X45,$Y45)=2,"◧ Amber",IF(MAX($X45,$Y45)=1,"□ On track","Not read")))))) | N45: =IF(OR($A45="",$B45<>"Program"),"","■ "&COUNTIFS($C$6:$C$305,$A45,$M$6:$M$305,"■ Red")&" Red, ◧ "&COUNTIFS($C$6:$C$305,$A45,$M$6:$M$305,"◧ Amber")&" Amber") | O45: =IF(OR($A45="",$E45=""),"",COUNTIFS($E$6:$E$305,$E45,$D$6:$D$305,"Active")+COUNTIFS($E$6:$E$305,$E45,$D$6:$D$305,"Paused")) | P45: =IF($A45="","",IF($AE45=0,"○ Clear",IF($AA45=1,"△ No owner",IF($AC45=1,"△ Check Sits under",IF($AC45=2,"△ Outside the portfolio",IF($AB45=1,"△ No sponsor",IF($AH45=1,"△ Name used twice",IF($AG45=1,"△ Budget only counts under Portfolio","△ No variance note"))))))&IF($AE45>1," (+"&($AE45-1)&" more)",""))) | Q45: =IF(AND($A45<>"",OR($D45="Active",$D45="Paused")),1,0) | R45: =IFERROR(INDEX($A$6:$A$305,MATCH(38,$S$6:$S$305,0)),"") | S45: =IF(AND($A45<>"",$B45="Program"),COUNTIFS($B$6:$B45,"Program",$A$6:$A45,"<>"),"") | T45: =IF(AND($A45<>"",$B45="Program"),SUMPRODUCT(MAX(($C$6:$C$305=$A45)*($B$6:$B$305="Project")*($D$6:$D$305<>"Proposed")*$I$6:$I$305)),0) | U45: =IF($I45<>"",$I45,IF($T45>0,$T45,"")) | V45: =IF(AND($A45<>"",$B45="Program"),SUMIFS($J$6:$J$305,$C$6:$C$305,$A45,$B$6:$B$305,"Project",$D$6:$D$305,"<>Proposed"),0) | W45: =IF(AND($A45<>"",$B45="Program"),COUNTIFS($C$6:$C$305,$A45,$B$6:$B$305,"Project",$D$6:$D$305,"<>Proposed")-COUNTIFS($C$6:$C$305,$A45,$B$6:$B$305,"Project",$D$6:$D$305,"<>Proposed",$J$6:$J$305,">=0"),0) | X45: =IF(OR($Q45=0,$H45="",$AF45="Sprint"),0,IF(AND($B45="Project",$H45<TODAY()),3,IF($U45="",0,IF($U45<=$H45,1,IF(NETWORKDAYS($H45,$U45)-1>IF($B45="Program",Checks!$B$7,Checks!$B$6),3,2))))) | Y45: =IF(OR($Q45=0,$K45="",$K45=0,$AF45="Sprint"),0,IF(AND($B45="Project",$J45=""),0,IF(IF($B45="Program",$V45,$J45)>$K45*(1+Checks!$B$8),3,IF(IF($B45="Program",$V45,$J45)>$K45,2,IF(AND($B45="Program",OR($W45>0,$V45=0)),0,1))))) | Z45: =IF($A45="",0,IF($C45="Portfolio",1,IF(AND($B45="Project",$C45<>"",$C45<>"Outside the portfolio"),IFERROR(IF(AND(INDEX($B$6:$B$305,MATCH($C45,$A$6:$A$305,0))="Program",INDEX($C$6:$C$305,MATCH($C45,$A$6:$A$305,0))="Portfolio"),1,0),0),0))) | AA45: =IF(AND($A45<>"",$E45="",OR($Q45=1,$D45="Proposed")),1,0) | AB45: =IF(AND($A45<>"",$B45="Program",$F45="",$Q45=1),1,0) | AC45: =IF(OR($A45="",$D45="Completed",$D45="Terminated"),0,IF($C45="",1,IF($C45="Portfolio",0,IF($C45="Outside the portfolio",IF($Q45=1,2,0),IF($B45="Project",IF(IFERROR(INDEX($B$6:$B$305,MATCH($C45,$A$6:$A$305,0)),"")="Program",0,1),1))))) | AD45: =IF(AND($A45<>"",OR($M45="■ Red",$M45="◧ Amber"),$L45=""),1,0) | AE45: =$AA45+$AB45+IF($AC45>0,1,0)+$AD45+$AG45+$AH45 | AG45: =IF(AND($A45<>"",$K45<>"",$C45<>"Portfolio",$D45<>"Completed",$D45<>"Terminated"),1,0) | AH45: =IF(AND($A45<>"",COUNTIF($A$6:$A$305,$A45)>1),1,0) | AI45: =IF(AND($A45<>"",$C45="Portfolio"),COUNTIFS($C$6:$C45,"Portfolio",$A$6:$A45,"<>"),"")
M46: =IF($A46="","",IF($D46="","Not read",IF($Q46=0,"Not counted",IF(MAX($X46,$Y46)=3,"■ Red",IF(MAX($X46,$Y46)=2,"◧ Amber",IF(MAX($X46,$Y46)=1,"□ On track","Not read")))))) | N46: =IF(OR($A46="",$B46<>"Program"),"","■ "&COUNTIFS($C$6:$C$305,$A46,$M$6:$M$305,"■ Red")&" Red, ◧ "&COUNTIFS($C$6:$C$305,$A46,$M$6:$M$305,"◧ Amber")&" Amber") | O46: =IF(OR($A46="",$E46=""),"",COUNTIFS($E$6:$E$305,$E46,$D$6:$D$305,"Active")+COUNTIFS($E$6:$E$305,$E46,$D$6:$D$305,"Paused")) | P46: =IF($A46="","",IF($AE46=0,"○ Clear",IF($AA46=1,"△ No owner",IF($AC46=1,"△ Check Sits under",IF($AC46=2,"△ Outside the portfolio",IF($AB46=1,"△ No sponsor",IF($AH46=1,"△ Name used twice",IF($AG46=1,"△ Budget only counts under Portfolio","△ No variance note"))))))&IF($AE46>1," (+"&($AE46-1)&" more)",""))) | Q46: =IF(AND($A46<>"",OR($D46="Active",$D46="Paused")),1,0) | R46: =IFERROR(INDEX($A$6:$A$305,MATCH(39,$S$6:$S$305,0)),"") | S46: =IF(AND($A46<>"",$B46="Program"),COUNTIFS($B$6:$B46,"Program",$A$6:$A46,"<>"),"") | T46: =IF(AND($A46<>"",$B46="Program"),SUMPRODUCT(MAX(($C$6:$C$305=$A46)*($B$6:$B$305="Project")*($D$6:$D$305<>"Proposed")*$I$6:$I$305)),0) | U46: =IF($I46<>"",$I46,IF($T46>0,$T46,"")) | V46: =IF(AND($A46<>"",$B46="Program"),SUMIFS($J$6:$J$305,$C$6:$C$305,$A46,$B$6:$B$305,"Project",$D$6:$D$305,"<>Proposed"),0) | W46: =IF(AND($A46<>"",$B46="Program"),COUNTIFS($C$6:$C$305,$A46,$B$6:$B$305,"Project",$D$6:$D$305,"<>Proposed")-COUNTIFS($C$6:$C$305,$A46,$B$6:$B$305,"Project",$D$6:$D$305,"<>Proposed",$J$6:$J$305,">=0"),0) | X46: =IF(OR($Q46=0,$H46="",$AF46="Sprint"),0,IF(AND($B46="Project",$H46<TODAY()),3,IF($U46="",0,IF($U46<=$H46,1,IF(NETWORKDAYS($H46,$U46)-1>IF($B46="Program",Checks!$B$7,Checks!$B$6),3,2))))) | Y46: =IF(OR($Q46=0,$K46="",$K46=0,$AF46="Sprint"),0,IF(AND($B46="Project",$J46=""),0,IF(IF($B46="Program",$V46,$J46)>$K46*(1+Checks!$B$8),3,IF(IF($B46="Program",$V46,$J46)>$K46,2,IF(AND($B46="Program",OR($W46>0,$V46=0)),0,1))))) | Z46: =IF($A46="",0,IF($C46="Portfolio",1,IF(AND($B46="Project",$C46<>"",$C46<>"Outside the portfolio"),IFERROR(IF(AND(INDEX($B$6:$B$305,MATCH($C46,$A$6:$A$305,0))="Program",INDEX($C$6:$C$305,MATCH($C46,$A$6:$A$305,0))="Portfolio"),1,0),0),0))) | AA46: =IF(AND($A46<>"",$E46="",OR($Q46=1,$D46="Proposed")),1,0) | AB46: =IF(AND($A46<>"",$B46="Program",$F46="",$Q46=1),1,0) | AC46: =IF(OR($A46="",$D46="Completed",$D46="Terminated"),0,IF($C46="",1,IF($C46="Portfolio",0,IF($C46="Outside the portfolio",IF($Q46=1,2,0),IF($B46="Project",IF(IFERROR(INDEX($B$6:$B$305,MATCH($C46,$A$6:$A$305,0)),"")="Program",0,1),1))))) | AD46: =IF(AND($A46<>"",OR($M46="■ Red",$M46="◧ Amber"),$L46=""),1,0) | AE46: =$AA46+$AB46+IF($AC46>0,1,0)+$AD46+$AG46+$AH46 | AG46: =IF(AND($A46<>"",$K46<>"",$C46<>"Portfolio",$D46<>"Completed",$D46<>"Terminated"),1,0) | AH46: =IF(AND($A46<>"",COUNTIF($A$6:$A$305,$A46)>1),1,0) | AI46: =IF(AND($A46<>"",$C46="Portfolio"),COUNTIFS($C$6:$C46,"Portfolio",$A$6:$A46,"<>"),"")
M47: =IF($A47="","",IF($D47="","Not read",IF($Q47=0,"Not counted",IF(MAX($X47,$Y47)=3,"■ Red",IF(MAX($X47,$Y47)=2,"◧ Amber",IF(MAX($X47,$Y47)=1,"□ On track","Not read")))))) | N47: =IF(OR($A47="",$B47<>"Program"),"","■ "&COUNTIFS($C$6:$C$305,$A47,$M$6:$M$305,"■ Red")&" Red, ◧ "&COUNTIFS($C$6:$C$305,$A47,$M$6:$M$305,"◧ Amber")&" Amber") | O47: =IF(OR($A47="",$E47=""),"",COUNTIFS($E$6:$E$305,$E47,$D$6:$D$305,"Active")+COUNTIFS($E$6:$E$305,$E47,$D$6:$D$305,"Paused")) | P47: =IF($A47="","",IF($AE47=0,"○ Clear",IF($AA47=1,"△ No owner",IF($AC47=1,"△ Check Sits under",IF($AC47=2,"△ Outside the portfolio",IF($AB47=1,"△ No sponsor",IF($AH47=1,"△ Name used twice",IF($AG47=1,"△ Budget only counts under Portfolio","△ No variance note"))))))&IF($AE47>1," (+"&($AE47-1)&" more)",""))) | Q47: =IF(AND($A47<>"",OR($D47="Active",$D47="Paused")),1,0) | R47: =IFERROR(INDEX($A$6:$A$305,MATCH(40,$S$6:$S$305,0)),"") | S47: =IF(AND($A47<>"",$B47="Program"),COUNTIFS($B$6:$B47,"Program",$A$6:$A47,"<>"),"") | T47: =IF(AND($A47<>"",$B47="Program"),SUMPRODUCT(MAX(($C$6:$C$305=$A47)*($B$6:$B$305="Project")*($D$6:$D$305<>"Proposed")*$I$6:$I$305)),0) | U47: =IF($I47<>"",$I47,IF($T47>0,$T47,"")) | V47: =IF(AND($A47<>"",$B47="Program"),SUMIFS($J$6:$J$305,$C$6:$C$305,$A47,$B$6:$B$305,"Project",$D$6:$D$305,"<>Proposed"),0) | W47: =IF(AND($A47<>"",$B47="Program"),COUNTIFS($C$6:$C$305,$A47,$B$6:$B$305,"Project",$D$6:$D$305,"<>Proposed")-COUNTIFS($C$6:$C$305,$A47,$B$6:$B$305,"Project",$D$6:$D$305,"<>Proposed",$J$6:$J$305,">=0"),0) | X47: =IF(OR($Q47=0,$H47="",$AF47="Sprint"),0,IF(AND($B47="Project",$H47<TODAY()),3,IF($U47="",0,IF($U47<=$H47,1,IF(NETWORKDAYS($H47,$U47)-1>IF($B47="Program",Checks!$B$7,Checks!$B$6),3,2))))) | Y47: =IF(OR($Q47=0,$K47="",$K47=0,$AF47="Sprint"),0,IF(AND($B47="Project",$J47=""),0,IF(IF($B47="Program",$V47,$J47)>$K47*(1+Checks!$B$8),3,IF(IF($B47="Program",$V47,$J47)>$K47,2,IF(AND($B47="Program",OR($W47>0,$V47=0)),0,1))))) | Z47: =IF($A47="",0,IF($C47="Portfolio",1,IF(AND($B47="Project",$C47<>"",$C47<>"Outside the portfolio"),IFERROR(IF(AND(INDEX($B$6:$B$305,MATCH($C47,$A$6:$A$305,0))="Program",INDEX($C$6:$C$305,MATCH($C47,$A$6:$A$305,0))="Portfolio"),1,0),0),0))) | AA47: =IF(AND($A47<>"",$E47="",OR($Q47=1,$D47="Proposed")),1,0) | AB47: =IF(AND($A47<>"",$B47="Program",$F47="",$Q47=1),1,0) | AC47: =IF(OR($A47="",$D47="Completed",$D47="Terminated"),0,IF($C47="",1,IF($C47="Portfolio",0,IF($C47="Outside the portfolio",IF($Q47=1,2,0),IF($B47="Project",IF(IFERROR(INDEX($B$6:$B$305,MATCH($C47,$A$6:$A$305,0)),"")="Program",0,1),1))))) | AD47: =IF(AND($A47<>"",OR($M47="■ Red",$M47="◧ Amber"),$L47=""),1,0) | AE47: =$AA47+$AB47+IF($AC47>0,1,0)+$AD47+$AG47+$AH47 | AG47: =IF(AND($A47<>"",$K47<>"",$C47<>"Portfolio",$D47<>"Completed",$D47<>"Terminated"),1,0) | AH47: =IF(AND($A47<>"",COUNTIF($A$6:$A$305,$A47)>1),1,0) | AI47: =IF(AND($A47<>"",$C47="Portfolio"),COUNTIFS($C$6:$C47,"Portfolio",$A$6:$A47,"<>"),"")
M48: =IF($A48="","",IF($D48="","Not read",IF($Q48=0,"Not counted",IF(MAX($X48,$Y48)=3,"■ Red",IF(MAX($X48,$Y48)=2,"◧ Amber",IF(MAX($X48,$Y48)=1,"□ On track","Not read")))))) | N48: =IF(OR($A48="",$B48<>"Program"),"","■ "&COUNTIFS($C$6:$C$305,$A48,$M$6:$M$305,"■ Red")&" Red, ◧ "&COUNTIFS($C$6:$C$305,$A48,$M$6:$M$305,"◧ Amber")&" Amber") | O48: =IF(OR($A48="",$E48=""),"",COUNTIFS($E$6:$E$305,$E48,$D$6:$D$305,"Active")+COUNTIFS($E$6:$E$305,$E48,$D$6:$D$305,"Paused")) | P48: =IF($A48="","",IF($AE48=0,"○ Clear",IF($AA48=1,"△ No owner",IF($AC48=1,"△ Check Sits under",IF($AC48=2,"△ Outside the portfolio",IF($AB48=1,"△ No sponsor",IF($AH48=1,"△ Name used twice",IF($AG48=1,"△ Budget only counts under Portfolio","△ No variance note"))))))&IF($AE48>1," (+"&($AE48-1)&" more)",""))) | Q48: =IF(AND($A48<>"",OR($D48="Active",$D48="Paused")),1,0) | R48: =IFERROR(INDEX($A$6:$A$305,MATCH(41,$S$6:$S$305,0)),"") | S48: =IF(AND($A48<>"",$B48="Program"),COUNTIFS($B$6:$B48,"Program",$A$6:$A48,"<>"),"") | T48: =IF(AND($A48<>"",$B48="Program"),SUMPRODUCT(MAX(($C$6:$C$305=$A48)*($B$6:$B$305="Project")*($D$6:$D$305<>"Proposed")*$I$6:$I$305)),0) | U48: =IF($I48<>"",$I48,IF($T48>0,$T48,"")) | V48: =IF(AND($A48<>"",$B48="Program"),SUMIFS($J$6:$J$305,$C$6:$C$305,$A48,$B$6:$B$305,"Project",$D$6:$D$305,"<>Proposed"),0) | W48: =IF(AND($A48<>"",$B48="Program"),COUNTIFS($C$6:$C$305,$A48,$B$6:$B$305,"Project",$D$6:$D$305,"<>Proposed")-COUNTIFS($C$6:$C$305,$A48,$B$6:$B$305,"Project",$D$6:$D$305,"<>Proposed",$J$6:$J$305,">=0"),0) | X48: =IF(OR($Q48=0,$H48="",$AF48="Sprint"),0,IF(AND($B48="Project",$H48<TODAY()),3,IF($U48="",0,IF($U48<=$H48,1,IF(NETWORKDAYS($H48,$U48)-1>IF($B48="Program",Checks!$B$7,Checks!$B$6),3,2))))) | Y48: =IF(OR($Q48=0,$K48="",$K48=0,$AF48="Sprint"),0,IF(AND($B48="Project",$J48=""),0,IF(IF($B48="Program",$V48,$J48)>$K48*(1+Checks!$B$8),3,IF(IF($B48="Program",$V48,$J48)>$K48,2,IF(AND($B48="Program",OR($W48>0,$V48=0)),0,1))))) | Z48: =IF($A48="",0,IF($C48="Portfolio",1,IF(AND($B48="Project",$C48<>"",$C48<>"Outside the portfolio"),IFERROR(IF(AND(INDEX($B$6:$B$305,MATCH($C48,$A$6:$A$305,0))="Program",INDEX($C$6:$C$305,MATCH($C48,$A$6:$A$305,0))="Portfolio"),1,0),0),0))) | AA48: =IF(AND($A48<>"",$E48="",OR($Q48=1,$D48="Proposed")),1,0) | AB48: =IF(AND($A48<>"",$B48="Program",$F48="",$Q48=1),1,0) | AC48: =IF(OR($A48="",$D48="Completed",$D48="Terminated"),0,IF($C48="",1,IF($C48="Portfolio",0,IF($C48="Outside the portfolio",IF($Q48=1,2,0),IF($B48="Project",IF(IFERROR(INDEX($B$6:$B$305,MATCH($C48,$A$6:$A$305,0)),"")="Program",0,1),1))))) | AD48: =IF(AND($A48<>"",OR($M48="■ Red",$M48="◧ Amber"),$L48=""),1,0) | AE48: =$AA48+$AB48+IF($AC48>0,1,0)+$AD48+$AG48+$AH48 | AG48: =IF(AND($A48<>"",$K48<>"",$C48<>"Portfolio",$D48<>"Completed",$D48<>"Terminated"),1,0) | AH48: =IF(AND($A48<>"",COUNTIF($A$6:$A$305,$A48)>1),1,0) | AI48: =IF(AND($A48<>"",$C48="Portfolio"),COUNTIFS($C$6:$C48,"Portfolio",$A$6:$A48,"<>"),"")
M49: =IF($A49="","",IF($D49="","Not read",IF($Q49=0,"Not counted",IF(MAX($X49,$Y49)=3,"■ Red",IF(MAX($X49,$Y49)=2,"◧ Amber",IF(MAX($X49,$Y49)=1,"□ On track","Not read")))))) | N49: =IF(OR($A49="",$B49<>"Program"),"","■ "&COUNTIFS($C$6:$C$305,$A49,$M$6:$M$305,"■ Red")&" Red, ◧ "&COUNTIFS($C$6:$C$305,$A49,$M$6:$M$305,"◧ Amber")&" Amber") | O49: =IF(OR($A49="",$E49=""),"",COUNTIFS($E$6:$E$305,$E49,$D$6:$D$305,"Active")+COUNTIFS($E$6:$E$305,$E49,$D$6:$D$305,"Paused")) | P49: =IF($A49="","",IF($AE49=0,"○ Clear",IF($AA49=1,"△ No owner",IF($AC49=1,"△ Check Sits under",IF($AC49=2,"△ Outside the portfolio",IF($AB49=1,"△ No sponsor",IF($AH49=1,"△ Name used twice",IF($AG49=1,"△ Budget only counts under Portfolio","△ No variance note"))))))&IF($AE49>1," (+"&($AE49-1)&" more)",""))) | Q49: =IF(AND($A49<>"",OR($D49="Active",$D49="Paused")),1,0) | R49: =IFERROR(INDEX($A$6:$A$305,MATCH(42,$S$6:$S$305,0)),"") | S49: =IF(AND($A49<>"",$B49="Program"),COUNTIFS($B$6:$B49,"Program",$A$6:$A49,"<>"),"") | T49: =IF(AND($A49<>"",$B49="Program"),SUMPRODUCT(MAX(($C$6:$C$305=$A49)*($B$6:$B$305="Project")*($D$6:$D$305<>"Proposed")*$I$6:$I$305)),0) | U49: =IF($I49<>"",$I49,IF($T49>0,$T49,"")) | V49: =IF(AND($A49<>"",$B49="Program"),SUMIFS($J$6:$J$305,$C$6:$C$305,$A49,$B$6:$B$305,"Project",$D$6:$D$305,"<>Proposed"),0) | W49: =IF(AND($A49<>"",$B49="Program"),COUNTIFS($C$6:$C$305,$A49,$B$6:$B$305,"Project",$D$6:$D$305,"<>Proposed")-COUNTIFS($C$6:$C$305,$A49,$B$6:$B$305,"Project",$D$6:$D$305,"<>Proposed",$J$6:$J$305,">=0"),0) | X49: =IF(OR($Q49=0,$H49="",$AF49="Sprint"),0,IF(AND($B49="Project",$H49<TODAY()),3,IF($U49="",0,IF($U49<=$H49,1,IF(NETWORKDAYS($H49,$U49)-1>IF($B49="Program",Checks!$B$7,Checks!$B$6),3,2))))) | Y49: =IF(OR($Q49=0,$K49="",$K49=0,$AF49="Sprint"),0,IF(AND($B49="Project",$J49=""),0,IF(IF($B49="Program",$V49,$J49)>$K49*(1+Checks!$B$8),3,IF(IF($B49="Program",$V49,$J49)>$K49,2,IF(AND($B49="Program",OR($W49>0,$V49=0)),0,1))))) | Z49: =IF($A49="",0,IF($C49="Portfolio",1,IF(AND($B49="Project",$C49<>"",$C49<>"Outside the portfolio"),IFERROR(IF(AND(INDEX($B$6:$B$305,MATCH($C49,$A$6:$A$305,0))="Program",INDEX($C$6:$C$305,MATCH($C49,$A$6:$A$305,0))="Portfolio"),1,0),0),0))) | AA49: =IF(AND($A49<>"",$E49="",OR($Q49=1,$D49="Proposed")),1,0) | AB49: =IF(AND($A49<>"",$B49="Program",$F49="",$Q49=1),1,0) | AC49: =IF(OR($A49="",$D49="Completed",$D49="Terminated"),0,IF($C49="",1,IF($C49="Portfolio",0,IF($C49="Outside the portfolio",IF($Q49=1,2,0),IF($B49="Project",IF(IFERROR(INDEX($B$6:$B$305,MATCH($C49,$A$6:$A$305,0)),"")="Program",0,1),1))))) | AD49: =IF(AND($A49<>"",OR($M49="■ Red",$M49="◧ Amber"),$L49=""),1,0) | AE49: =$AA49+$AB49+IF($AC49>0,1,0)+$AD49+$AG49+$AH49 | AG49: =IF(AND($A49<>"",$K49<>"",$C49<>"Portfolio",$D49<>"Completed",$D49<>"Terminated"),1,0) | AH49: =IF(AND($A49<>"",COUNTIF($A$6:$A$305,$A49)>1),1,0) | AI49: =IF(AND($A49<>"",$C49="Portfolio"),COUNTIFS($C$6:$C49,"Portfolio",$A$6:$A49,"<>"),"")
M50: =IF($A50="","",IF($D50="","Not read",IF($Q50=0,"Not counted",IF(MAX($X50,$Y50)=3,"■ Red",IF(MAX($X50,$Y50)=2,"◧ Amber",IF(MAX($X50,$Y50)=1,"□ On track","Not read")))))) | N50: =IF(OR($A50="",$B50<>"Program"),"","■ "&COUNTIFS($C$6:$C$305,$A50,$M$6:$M$305,"■ Red")&" Red, ◧ "&COUNTIFS($C$6:$C$305,$A50,$M$6:$M$305,"◧ Amber")&" Amber") | O50: =IF(OR($A50="",$E50=""),"",COUNTIFS($E$6:$E$305,$E50,$D$6:$D$305,"Active")+COUNTIFS($E$6:$E$305,$E50,$D$6:$D$305,"Paused")) | P50: =IF($A50="","",IF($AE50=0,"○ Clear",IF($AA50=1,"△ No owner",IF($AC50=1,"△ Check Sits under",IF($AC50=2,"△ Outside the portfolio",IF($AB50=1,"△ No sponsor",IF($AH50=1,"△ Name used twice",IF($AG50=1,"△ Budget only counts under Portfolio","△ No variance note"))))))&IF($AE50>1," (+"&($AE50-1)&" more)",""))) | Q50: =IF(AND($A50<>"",OR($D50="Active",$D50="Paused")),1,0) | R50: =IFERROR(INDEX($A$6:$A$305,MATCH(43,$S$6:$S$305,0)),"") | S50: =IF(AND($A50<>"",$B50="Program"),COUNTIFS($B$6:$B50,"Program",$A$6:$A50,"<>"),"") | T50: =IF(AND($A50<>"",$B50="Program"),SUMPRODUCT(MAX(($C$6:$C$305=$A50)*($B$6:$B$305="Project")*($D$6:$D$305<>"Proposed")*$I$6:$I$305)),0) | U50: =IF($I50<>"",$I50,IF($T50>0,$T50,"")) | V50: =IF(AND($A50<>"",$B50="Program"),SUMIFS($J$6:$J$305,$C$6:$C$305,$A50,$B$6:$B$305,"Project",$D$6:$D$305,"<>Proposed"),0) | W50: =IF(AND($A50<>"",$B50="Program"),COUNTIFS($C$6:$C$305,$A50,$B$6:$B$305,"Project",$D$6:$D$305,"<>Proposed")-COUNTIFS($C$6:$C$305,$A50,$B$6:$B$305,"Project",$D$6:$D$305,"<>Proposed",$J$6:$J$305,">=0"),0) | X50: =IF(OR($Q50=0,$H50="",$AF50="Sprint"),0,IF(AND($B50="Project",$H50<TODAY()),3,IF($U50="",0,IF($U50<=$H50,1,IF(NETWORKDAYS($H50,$U50)-1>IF($B50="Program",Checks!$B$7,Checks!$B$6),3,2))))) | Y50: =IF(OR($Q50=0,$K50="",$K50=0,$AF50="Sprint"),0,IF(AND($B50="Project",$J50=""),0,IF(IF($B50="Program",$V50,$J50)>$K50*(1+Checks!$B$8),3,IF(IF($B50="Program",$V50,$J50)>$K50,2,IF(AND($B50="Program",OR($W50>0,$V50=0)),0,1))))) | Z50: =IF($A50="",0,IF($C50="Portfolio",1,IF(AND($B50="Project",$C50<>"",$C50<>"Outside the portfolio"),IFERROR(IF(AND(INDEX($B$6:$B$305,MATCH($C50,$A$6:$A$305,0))="Program",INDEX($C$6:$C$305,MATCH($C50,$A$6:$A$305,0))="Portfolio"),1,0),0),0))) | AA50: =IF(AND($A50<>"",$E50="",OR($Q50=1,$D50="Proposed")),1,0) | AB50: =IF(AND($A50<>"",$B50="Program",$F50="",$Q50=1),1,0) | AC50: =IF(OR($A50="",$D50="Completed",$D50="Terminated"),0,IF($C50="",1,IF($C50="Portfolio",0,IF($C50="Outside the portfolio",IF($Q50=1,2,0),IF($B50="Project",IF(IFERROR(INDEX($B$6:$B$305,MATCH($C50,$A$6:$A$305,0)),"")="Program",0,1),1))))) | AD50: =IF(AND($A50<>"",OR($M50="■ Red",$M50="◧ Amber"),$L50=""),1,0) | AE50: =$AA50+$AB50+IF($AC50>0,1,0)+$AD50+$AG50+$AH50 | AG50: =IF(AND($A50<>"",$K50<>"",$C50<>"Portfolio",$D50<>"Completed",$D50<>"Terminated"),1,0) | AH50: =IF(AND($A50<>"",COUNTIF($A$6:$A$305,$A50)>1),1,0) | AI50: =IF(AND($A50<>"",$C50="Portfolio"),COUNTIFS($C$6:$C50,"Portfolio",$A$6:$A50,"<>"),"")
M51: =IF($A51="","",IF($D51="","Not read",IF($Q51=0,"Not counted",IF(MAX($X51,$Y51)=3,"■ Red",IF(MAX($X51,$Y51)=2,"◧ Amber",IF(MAX($X51,$Y51)=1,"□ On track","Not read")))))) | N51: =IF(OR($A51="",$B51<>"Program"),"","■ "&COUNTIFS($C$6:$C$305,$A51,$M$6:$M$305,"■ Red")&" Red, ◧ "&COUNTIFS($C$6:$C$305,$A51,$M$6:$M$305,"◧ Amber")&" Amber") | O51: =IF(OR($A51="",$E51=""),"",COUNTIFS($E$6:$E$305,$E51,$D$6:$D$305,"Active")+COUNTIFS($E$6:$E$305,$E51,$D$6:$D$305,"Paused")) | P51: =IF($A51="","",IF($AE51=0,"○ Clear",IF($AA51=1,"△ No owner",IF($AC51=1,"△ Check Sits under",IF($AC51=2,"△ Outside the portfolio",IF($AB51=1,"△ No sponsor",IF($AH51=1,"△ Name used twice",IF($AG51=1,"△ Budget only counts under Portfolio","△ No variance note"))))))&IF($AE51>1," (+"&($AE51-1)&" more)",""))) | Q51: =IF(AND($A51<>"",OR($D51="Active",$D51="Paused")),1,0) | R51: =IFERROR(INDEX($A$6:$A$305,MATCH(44,$S$6:$S$305,0)),"") | S51: =IF(AND($A51<>"",$B51="Program"),COUNTIFS($B$6:$B51,"Program",$A$6:$A51,"<>"),"") | T51: =IF(AND($A51<>"",$B51="Program"),SUMPRODUCT(MAX(($C$6:$C$305=$A51)*($B$6:$B$305="Project")*($D$6:$D$305<>"Proposed")*$I$6:$I$305)),0) | U51: =IF($I51<>"",$I51,IF($T51>0,$T51,"")) | V51: =IF(AND($A51<>"",$B51="Program"),SUMIFS($J$6:$J$305,$C$6:$C$305,$A51,$B$6:$B$305,"Project",$D$6:$D$305,"<>Proposed"),0) | W51: =IF(AND($A51<>"",$B51="Program"),COUNTIFS($C$6:$C$305,$A51,$B$6:$B$305,"Project",$D$6:$D$305,"<>Proposed")-COUNTIFS($C$6:$C$305,$A51,$B$6:$B$305,"Project",$D$6:$D$305,"<>Proposed",$J$6:$J$305,">=0"),0) | X51: =IF(OR($Q51=0,$H51="",$AF51="Sprint"),0,IF(AND($B51="Project",$H51<TODAY()),3,IF($U51="",0,IF($U51<=$H51,1,IF(NETWORKDAYS($H51,$U51)-1>IF($B51="Program",Checks!$B$7,Checks!$B$6),3,2))))) | Y51: =IF(OR($Q51=0,$K51="",$K51=0,$AF51="Sprint"),0,IF(AND($B51="Project",$J51=""),0,IF(IF($B51="Program",$V51,$J51)>$K51*(1+Checks!$B$8),3,IF(IF($B51="Program",$V51,$J51)>$K51,2,IF(AND($B51="Program",OR($W51>0,$V51=0)),0,1))))) | Z51: =IF($A51="",0,IF($C51="Portfolio",1,IF(AND($B51="Project",$C51<>"",$C51<>"Outside the portfolio"),IFERROR(IF(AND(INDEX($B$6:$B$305,MATCH($C51,$A$6:$A$305,0))="Program",INDEX($C$6:$C$305,MATCH($C51,$A$6:$A$305,0))="Portfolio"),1,0),0),0))) | AA51: =IF(AND($A51<>"",$E51="",OR($Q51=1,$D51="Proposed")),1,0) | AB51: =IF(AND($A51<>"",$B51="Program",$F51="",$Q51=1),1,0) | AC51: =IF(OR($A51="",$D51="Completed",$D51="Terminated"),0,IF($C51="",1,IF($C51="Portfolio",0,IF($C51="Outside the portfolio",IF($Q51=1,2,0),IF($B51="Project",IF(IFERROR(INDEX($B$6:$B$305,MATCH($C51,$A$6:$A$305,0)),"")="Program",0,1),1))))) | AD51: =IF(AND($A51<>"",OR($M51="■ Red",$M51="◧ Amber"),$L51=""),1,0) | AE51: =$AA51+$AB51+IF($AC51>0,1,0)+$AD51+$AG51+$AH51 | AG51: =IF(AND($A51<>"",$K51<>"",$C51<>"Portfolio",$D51<>"Completed",$D51<>"Terminated"),1,0) | AH51: =IF(AND($A51<>"",COUNTIF($A$6:$A$305,$A51)>1),1,0) | AI51: =IF(AND($A51<>"",$C51="Portfolio"),COUNTIFS($C$6:$C51,"Portfolio",$A$6:$A51,"<>"),"")
M52: =IF($A52="","",IF($D52="","Not read",IF($Q52=0,"Not counted",IF(MAX($X52,$Y52)=3,"■ Red",IF(MAX($X52,$Y52)=2,"◧ Amber",IF(MAX($X52,$Y52)=1,"□ On track","Not read")))))) | N52: =IF(OR($A52="",$B52<>"Program"),"","■ "&COUNTIFS($C$6:$C$305,$A52,$M$6:$M$305,"■ Red")&" Red, ◧ "&COUNTIFS($C$6:$C$305,$A52,$M$6:$M$305,"◧ Amber")&" Amber") | O52: =IF(OR($A52="",$E52=""),"",COUNTIFS($E$6:$E$305,$E52,$D$6:$D$305,"Active")+COUNTIFS($E$6:$E$305,$E52,$D$6:$D$305,"Paused")) | P52: =IF($A52="","",IF($AE52=0,"○ Clear",IF($AA52=1,"△ No owner",IF($AC52=1,"△ Check Sits under",IF($AC52=2,"△ Outside the portfolio",IF($AB52=1,"△ No sponsor",IF($AH52=1,"△ Name used twice",IF($AG52=1,"△ Budget only counts under Portfolio","△ No variance note"))))))&IF($AE52>1," (+"&($AE52-1)&" more)",""))) | Q52: =IF(AND($A52<>"",OR($D52="Active",$D52="Paused")),1,0) | R52: =IFERROR(INDEX($A$6:$A$305,MATCH(45,$S$6:$S$305,0)),"") | S52: =IF(AND($A52<>"",$B52="Program"),COUNTIFS($B$6:$B52,"Program",$A$6:$A52,"<>"),"") | T52: =IF(AND($A52<>"",$B52="Program"),SUMPRODUCT(MAX(($C$6:$C$305=$A52)*($B$6:$B$305="Project")*($D$6:$D$305<>"Proposed")*$I$6:$I$305)),0) | U52: =IF($I52<>"",$I52,IF($T52>0,$T52,"")) | V52: =IF(AND($A52<>"",$B52="Program"),SUMIFS($J$6:$J$305,$C$6:$C$305,$A52,$B$6:$B$305,"Project",$D$6:$D$305,"<>Proposed"),0) | W52: =IF(AND($A52<>"",$B52="Program"),COUNTIFS($C$6:$C$305,$A52,$B$6:$B$305,"Project",$D$6:$D$305,"<>Proposed")-COUNTIFS($C$6:$C$305,$A52,$B$6:$B$305,"Project",$D$6:$D$305,"<>Proposed",$J$6:$J$305,">=0"),0) | X52: =IF(OR($Q52=0,$H52="",$AF52="Sprint"),0,IF(AND($B52="Project",$H52<TODAY()),3,IF($U52="",0,IF($U52<=$H52,1,IF(NETWORKDAYS($H52,$U52)-1>IF($B52="Program",Checks!$B$7,Checks!$B$6),3,2))))) | Y52: =IF(OR($Q52=0,$K52="",$K52=0,$AF52="Sprint"),0,IF(AND($B52="Project",$J52=""),0,IF(IF($B52="Program",$V52,$J52)>$K52*(1+Checks!$B$8),3,IF(IF($B52="Program",$V52,$J52)>$K52,2,IF(AND($B52="Program",OR($W52>0,$V52=0)),0,1))))) | Z52: =IF($A52="",0,IF($C52="Portfolio",1,IF(AND($B52="Project",$C52<>"",$C52<>"Outside the portfolio"),IFERROR(IF(AND(INDEX($B$6:$B$305,MATCH($C52,$A$6:$A$305,0))="Program",INDEX($C$6:$C$305,MATCH($C52,$A$6:$A$305,0))="Portfolio"),1,0),0),0))) | AA52: =IF(AND($A52<>"",$E52="",OR($Q52=1,$D52="Proposed")),1,0) | AB52: =IF(AND($A52<>"",$B52="Program",$F52="",$Q52=1),1,0) | AC52: =IF(OR($A52="",$D52="Completed",$D52="Terminated"),0,IF($C52="",1,IF($C52="Portfolio",0,IF($C52="Outside the portfolio",IF($Q52=1,2,0),IF($B52="Project",IF(IFERROR(INDEX($B$6:$B$305,MATCH($C52,$A$6:$A$305,0)),"")="Program",0,1),1))))) | AD52: =IF(AND($A52<>"",OR($M52="■ Red",$M52="◧ Amber"),$L52=""),1,0) | AE52: =$AA52+$AB52+IF($AC52>0,1,0)+$AD52+$AG52+$AH52 | AG52: =IF(AND($A52<>"",$K52<>"",$C52<>"Portfolio",$D52<>"Completed",$D52<>"Terminated"),1,0) | AH52: =IF(AND($A52<>"",COUNTIF($A$6:$A$305,$A52)>1),1,0) | AI52: =IF(AND($A52<>"",$C52="Portfolio"),COUNTIFS($C$6:$C52,"Portfolio",$A$6:$A52,"<>"),"")
M53: =IF($A53="","",IF($D53="","Not read",IF($Q53=0,"Not counted",IF(MAX($X53,$Y53)=3,"■ Red",IF(MAX($X53,$Y53)=2,"◧ Amber",IF(MAX($X53,$Y53)=1,"□ On track","Not read")))))) | N53: =IF(OR($A53="",$B53<>"Program"),"","■ "&COUNTIFS($C$6:$C$305,$A53,$M$6:$M$305,"■ Red")&" Red, ◧ "&COUNTIFS($C$6:$C$305,$A53,$M$6:$M$305,"◧ Amber")&" Amber") | O53: =IF(OR($A53="",$E53=""),"",COUNTIFS($E$6:$E$305,$E53,$D$6:$D$305,"Active")+COUNTIFS($E$6:$E$305,$E53,$D$6:$D$305,"Paused")) | P53: =IF($A53="","",IF($AE53=0,"○ Clear",IF($AA53=1,"△ No owner",IF($AC53=1,"△ Check Sits under",IF($AC53=2,"△ Outside the portfolio",IF($AB53=1,"△ No sponsor",IF($AH53=1,"△ Name used twice",IF($AG53=1,"△ Budget only counts under Portfolio","△ No variance note"))))))&IF($AE53>1," (+"&($AE53-1)&" more)",""))) | Q53: =IF(AND($A53<>"",OR($D53="Active",$D53="Paused")),1,0) | R53: =IFERROR(INDEX($A$6:$A$305,MATCH(46,$S$6:$S$305,0)),"") | S53: =IF(AND($A53<>"",$B53="Program"),COUNTIFS($B$6:$B53,"Program",$A$6:$A53,"<>"),"") | T53: =IF(AND($A53<>"",$B53="Program"),SUMPRODUCT(MAX(($C$6:$C$305=$A53)*($B$6:$B$305="Project")*($D$6:$D$305<>"Proposed")*$I$6:$I$305)),0) | U53: =IF($I53<>"",$I53,IF($T53>0,$T53,"")) | V53: =IF(AND($A53<>"",$B53="Program"),SUMIFS($J$6:$J$305,$C$6:$C$305,$A53,$B$6:$B$305,"Project",$D$6:$D$305,"<>Proposed"),0) | W53: =IF(AND($A53<>"",$B53="Program"),COUNTIFS($C$6:$C$305,$A53,$B$6:$B$305,"Project",$D$6:$D$305,"<>Proposed")-COUNTIFS($C$6:$C$305,$A53,$B$6:$B$305,"Project",$D$6:$D$305,"<>Proposed",$J$6:$J$305,">=0"),0) | X53: =IF(OR($Q53=0,$H53="",$AF53="Sprint"),0,IF(AND($B53="Project",$H53<TODAY()),3,IF($U53="",0,IF($U53<=$H53,1,IF(NETWORKDAYS($H53,$U53)-1>IF($B53="Program",Checks!$B$7,Checks!$B$6),3,2))))) | Y53: =IF(OR($Q53=0,$K53="",$K53=0,$AF53="Sprint"),0,IF(AND($B53="Project",$J53=""),0,IF(IF($B53="Program",$V53,$J53)>$K53*(1+Checks!$B$8),3,IF(IF($B53="Program",$V53,$J53)>$K53,2,IF(AND($B53="Program",OR($W53>0,$V53=0)),0,1))))) | Z53: =IF($A53="",0,IF($C53="Portfolio",1,IF(AND($B53="Project",$C53<>"",$C53<>"Outside the portfolio"),IFERROR(IF(AND(INDEX($B$6:$B$305,MATCH($C53,$A$6:$A$305,0))="Program",INDEX($C$6:$C$305,MATCH($C53,$A$6:$A$305,0))="Portfolio"),1,0),0),0))) | AA53: =IF(AND($A53<>"",$E53="",OR($Q53=1,$D53="Proposed")),1,0) | AB53: =IF(AND($A53<>"",$B53="Program",$F53="",$Q53=1),1,0) | AC53: =IF(OR($A53="",$D53="Completed",$D53="Terminated"),0,IF($C53="",1,IF($C53="Portfolio",0,IF($C53="Outside the portfolio",IF($Q53=1,2,0),IF($B53="Project",IF(IFERROR(INDEX($B$6:$B$305,MATCH($C53,$A$6:$A$305,0)),"")="Program",0,1),1))))) | AD53: =IF(AND($A53<>"",OR($M53="■ Red",$M53="◧ Amber"),$L53=""),1,0) | AE53: =$AA53+$AB53+IF($AC53>0,1,0)+$AD53+$AG53+$AH53 | AG53: =IF(AND($A53<>"",$K53<>"",$C53<>"Portfolio",$D53<>"Completed",$D53<>"Terminated"),1,0) | AH53: =IF(AND($A53<>"",COUNTIF($A$6:$A$305,$A53)>1),1,0) | AI53: =IF(AND($A53<>"",$C53="Portfolio"),COUNTIFS($C$6:$C53,"Portfolio",$A$6:$A53,"<>"),"")
M54: =IF($A54="","",IF($D54="","Not read",IF($Q54=0,"Not counted",IF(MAX($X54,$Y54)=3,"■ Red",IF(MAX($X54,$Y54)=2,"◧ Amber",IF(MAX($X54,$Y54)=1,"□ On track","Not read")))))) | N54: =IF(OR($A54="",$B54<>"Program"),"","■ "&COUNTIFS($C$6:$C$305,$A54,$M$6:$M$305,"■ Red")&" Red, ◧ "&COUNTIFS($C$6:$C$305,$A54,$M$6:$M$305,"◧ Amber")&" Amber") | O54: =IF(OR($A54="",$E54=""),"",COUNTIFS($E$6:$E$305,$E54,$D$6:$D$305,"Active")+COUNTIFS($E$6:$E$305,$E54,$D$6:$D$305,"Paused")) | P54: =IF($A54="","",IF($AE54=0,"○ Clear",IF($AA54=1,"△ No owner",IF($AC54=1,"△ Check Sits under",IF($AC54=2,"△ Outside the portfolio",IF($AB54=1,"△ No sponsor",IF($AH54=1,"△ Name used twice",IF($AG54=1,"△ Budget only counts under Portfolio","△ No variance note"))))))&IF($AE54>1," (+"&($AE54-1)&" more)",""))) | Q54: =IF(AND($A54<>"",OR($D54="Active",$D54="Paused")),1,0) | R54: =IFERROR(INDEX($A$6:$A$305,MATCH(47,$S$6:$S$305,0)),"") | S54: =IF(AND($A54<>"",$B54="Program"),COUNTIFS($B$6:$B54,"Program",$A$6:$A54,"<>"),"") | T54: =IF(AND($A54<>"",$B54="Program"),SUMPRODUCT(MAX(($C$6:$C$305=$A54)*($B$6:$B$305="Project")*($D$6:$D$305<>"Proposed")*$I$6:$I$305)),0) | U54: =IF($I54<>"",$I54,IF($T54>0,$T54,"")) | V54: =IF(AND($A54<>"",$B54="Program"),SUMIFS($J$6:$J$305,$C$6:$C$305,$A54,$B$6:$B$305,"Project",$D$6:$D$305,"<>Proposed"),0) | W54: =IF(AND($A54<>"",$B54="Program"),COUNTIFS($C$6:$C$305,$A54,$B$6:$B$305,"Project",$D$6:$D$305,"<>Proposed")-COUNTIFS($C$6:$C$305,$A54,$B$6:$B$305,"Project",$D$6:$D$305,"<>Proposed",$J$6:$J$305,">=0"),0) | X54: =IF(OR($Q54=0,$H54="",$AF54="Sprint"),0,IF(AND($B54="Project",$H54<TODAY()),3,IF($U54="",0,IF($U54<=$H54,1,IF(NETWORKDAYS($H54,$U54)-1>IF($B54="Program",Checks!$B$7,Checks!$B$6),3,2))))) | Y54: =IF(OR($Q54=0,$K54="",$K54=0,$AF54="Sprint"),0,IF(AND($B54="Project",$J54=""),0,IF(IF($B54="Program",$V54,$J54)>$K54*(1+Checks!$B$8),3,IF(IF($B54="Program",$V54,$J54)>$K54,2,IF(AND($B54="Program",OR($W54>0,$V54=0)),0,1))))) | Z54: =IF($A54="",0,IF($C54="Portfolio",1,IF(AND($B54="Project",$C54<>"",$C54<>"Outside the portfolio"),IFERROR(IF(AND(INDEX($B$6:$B$305,MATCH($C54,$A$6:$A$305,0))="Program",INDEX($C$6:$C$305,MATCH($C54,$A$6:$A$305,0))="Portfolio"),1,0),0),0))) | AA54: =IF(AND($A54<>"",$E54="",OR($Q54=1,$D54="Proposed")),1,0) | AB54: =IF(AND($A54<>"",$B54="Program",$F54="",$Q54=1),1,0) | AC54: =IF(OR($A54="",$D54="Completed",$D54="Terminated"),0,IF($C54="",1,IF($C54="Portfolio",0,IF($C54="Outside the portfolio",IF($Q54=1,2,0),IF($B54="Project",IF(IFERROR(INDEX($B$6:$B$305,MATCH($C54,$A$6:$A$305,0)),"")="Program",0,1),1))))) | AD54: =IF(AND($A54<>"",OR($M54="■ Red",$M54="◧ Amber"),$L54=""),1,0) | AE54: =$AA54+$AB54+IF($AC54>0,1,0)+$AD54+$AG54+$AH54 | AG54: =IF(AND($A54<>"",$K54<>"",$C54<>"Portfolio",$D54<>"Completed",$D54<>"Terminated"),1,0) | AH54: =IF(AND($A54<>"",COUNTIF($A$6:$A$305,$A54)>1),1,0) | AI54: =IF(AND($A54<>"",$C54="Portfolio"),COUNTIFS($C$6:$C54,"Portfolio",$A$6:$A54,"<>"),"")
M55: =IF($A55="","",IF($D55="","Not read",IF($Q55=0,"Not counted",IF(MAX($X55,$Y55)=3,"■ Red",IF(MAX($X55,$Y55)=2,"◧ Amber",IF(MAX($X55,$Y55)=1,"□ On track","Not read")))))) | N55: =IF(OR($A55="",$B55<>"Program"),"","■ "&COUNTIFS($C$6:$C$305,$A55,$M$6:$M$305,"■ Red")&" Red, ◧ "&COUNTIFS($C$6:$C$305,$A55,$M$6:$M$305,"◧ Amber")&" Amber") | O55: =IF(OR($A55="",$E55=""),"",COUNTIFS($E$6:$E$305,$E55,$D$6:$D$305,"Active")+COUNTIFS($E$6:$E$305,$E55,$D$6:$D$305,"Paused")) | P55: =IF($A55="","",IF($AE55=0,"○ Clear",IF($AA55=1,"△ No owner",IF($AC55=1,"△ Check Sits under",IF($AC55=2,"△ Outside the portfolio",IF($AB55=1,"△ No sponsor",IF($AH55=1,"△ Name used twice",IF($AG55=1,"△ Budget only counts under Portfolio","△ No variance note"))))))&IF($AE55>1," (+"&($AE55-1)&" more)",""))) | Q55: =IF(AND($A55<>"",OR($D55="Active",$D55="Paused")),1,0) | R55: =IFERROR(INDEX($A$6:$A$305,MATCH(48,$S$6:$S$305,0)),"") | S55: =IF(AND($A55<>"",$B55="Program"),COUNTIFS($B$6:$B55,"Program",$A$6:$A55,"<>"),"") | T55: =IF(AND($A55<>"",$B55="Program"),SUMPRODUCT(MAX(($C$6:$C$305=$A55)*($B$6:$B$305="Project")*($D$6:$D$305<>"Proposed")*$I$6:$I$305)),0) | U55: =IF($I55<>"",$I55,IF($T55>0,$T55,"")) | V55: =IF(AND($A55<>"",$B55="Program"),SUMIFS($J$6:$J$305,$C$6:$C$305,$A55,$B$6:$B$305,"Project",$D$6:$D$305,"<>Proposed"),0) | W55: =IF(AND($A55<>"",$B55="Program"),COUNTIFS($C$6:$C$305,$A55,$B$6:$B$305,"Project",$D$6:$D$305,"<>Proposed")-COUNTIFS($C$6:$C$305,$A55,$B$6:$B$305,"Project",$D$6:$D$305,"<>Proposed",$J$6:$J$305,">=0"),0) | X55: =IF(OR($Q55=0,$H55="",$AF55="Sprint"),0,IF(AND($B55="Project",$H55<TODAY()),3,IF($U55="",0,IF($U55<=$H55,1,IF(NETWORKDAYS($H55,$U55)-1>IF($B55="Program",Checks!$B$7,Checks!$B$6),3,2))))) | Y55: =IF(OR($Q55=0,$K55="",$K55=0,$AF55="Sprint"),0,IF(AND($B55="Project",$J55=""),0,IF(IF($B55="Program",$V55,$J55)>$K55*(1+Checks!$B$8),3,IF(IF($B55="Program",$V55,$J55)>$K55,2,IF(AND($B55="Program",OR($W55>0,$V55=0)),0,1))))) | Z55: =IF($A55="",0,IF($C55="Portfolio",1,IF(AND($B55="Project",$C55<>"",$C55<>"Outside the portfolio"),IFERROR(IF(AND(INDEX($B$6:$B$305,MATCH($C55,$A$6:$A$305,0))="Program",INDEX($C$6:$C$305,MATCH($C55,$A$6:$A$305,0))="Portfolio"),1,0),0),0))) | AA55: =IF(AND($A55<>"",$E55="",OR($Q55=1,$D55="Proposed")),1,0) | AB55: =IF(AND($A55<>"",$B55="Program",$F55="",$Q55=1),1,0) | AC55: =IF(OR($A55="",$D55="Completed",$D55="Terminated"),0,IF($C55="",1,IF($C55="Portfolio",0,IF($C55="Outside the portfolio",IF($Q55=1,2,0),IF($B55="Project",IF(IFERROR(INDEX($B$6:$B$305,MATCH($C55,$A$6:$A$305,0)),"")="Program",0,1),1))))) | AD55: =IF(AND($A55<>"",OR($M55="■ Red",$M55="◧ Amber"),$L55=""),1,0) | AE55: =$AA55+$AB55+IF($AC55>0,1,0)+$AD55+$AG55+$AH55 | AG55: =IF(AND($A55<>"",$K55<>"",$C55<>"Portfolio",$D55<>"Completed",$D55<>"Terminated"),1,0) | AH55: =IF(AND($A55<>"",COUNTIF($A$6:$A$305,$A55)>1),1,0) | AI55: =IF(AND($A55<>"",$C55="Portfolio"),COUNTIFS($C$6:$C55,"Portfolio",$A$6:$A55,"<>"),"")
M56: =IF($A56="","",IF($D56="","Not read",IF($Q56=0,"Not counted",IF(MAX($X56,$Y56)=3,"■ Red",IF(MAX($X56,$Y56)=2,"◧ Amber",IF(MAX($X56,$Y56)=1,"□ On track","Not read")))))) | N56: =IF(OR($A56="",$B56<>"Program"),"","■ "&COUNTIFS($C$6:$C$305,$A56,$M$6:$M$305,"■ Red")&" Red, ◧ "&COUNTIFS($C$6:$C$305,$A56,$M$6:$M$305,"◧ Amber")&" Amber") | O56: =IF(OR($A56="",$E56=""),"",COUNTIFS($E$6:$E$305,$E56,$D$6:$D$305,"Active")+COUNTIFS($E$6:$E$305,$E56,$D$6:$D$305,"Paused")) | P56: =IF($A56="","",IF($AE56=0,"○ Clear",IF($AA56=1,"△ No owner",IF($AC56=1,"△ Check Sits under",IF($AC56=2,"△ Outside the portfolio",IF($AB56=1,"△ No sponsor",IF($AH56=1,"△ Name used twice",IF($AG56=1,"△ Budget only counts under Portfolio","△ No variance note"))))))&IF($AE56>1," (+"&($AE56-1)&" more)",""))) | Q56: =IF(AND($A56<>"",OR($D56="Active",$D56="Paused")),1,0) | R56: =IFERROR(INDEX($A$6:$A$305,MATCH(49,$S$6:$S$305,0)),"") | S56: =IF(AND($A56<>"",$B56="Program"),COUNTIFS($B$6:$B56,"Program",$A$6:$A56,"<>"),"") | T56: =IF(AND($A56<>"",$B56="Program"),SUMPRODUCT(MAX(($C$6:$C$305=$A56)*($B$6:$B$305="Project")*($D$6:$D$305<>"Proposed")*$I$6:$I$305)),0) | U56: =IF($I56<>"",$I56,IF($T56>0,$T56,"")) | V56: =IF(AND($A56<>"",$B56="Program"),SUMIFS($J$6:$J$305,$C$6:$C$305,$A56,$B$6:$B$305,"Project",$D$6:$D$305,"<>Proposed"),0) | W56: =IF(AND($A56<>"",$B56="Program"),COUNTIFS($C$6:$C$305,$A56,$B$6:$B$305,"Project",$D$6:$D$305,"<>Proposed")-COUNTIFS($C$6:$C$305,$A56,$B$6:$B$305,"Project",$D$6:$D$305,"<>Proposed",$J$6:$J$305,">=0"),0) | X56: =IF(OR($Q56=0,$H56="",$AF56="Sprint"),0,IF(AND($B56="Project",$H56<TODAY()),3,IF($U56="",0,IF($U56<=$H56,1,IF(NETWORKDAYS($H56,$U56)-1>IF($B56="Program",Checks!$B$7,Checks!$B$6),3,2))))) | Y56: =IF(OR($Q56=0,$K56="",$K56=0,$AF56="Sprint"),0,IF(AND($B56="Project",$J56=""),0,IF(IF($B56="Program",$V56,$J56)>$K56*(1+Checks!$B$8),3,IF(IF($B56="Program",$V56,$J56)>$K56,2,IF(AND($B56="Program",OR($W56>0,$V56=0)),0,1))))) | Z56: =IF($A56="",0,IF($C56="Portfolio",1,IF(AND($B56="Project",$C56<>"",$C56<>"Outside the portfolio"),IFERROR(IF(AND(INDEX($B$6:$B$305,MATCH($C56,$A$6:$A$305,0))="Program",INDEX($C$6:$C$305,MATCH($C56,$A$6:$A$305,0))="Portfolio"),1,0),0),0))) | AA56: =IF(AND($A56<>"",$E56="",OR($Q56=1,$D56="Proposed")),1,0) | AB56: =IF(AND($A56<>"",$B56="Program",$F56="",$Q56=1),1,0) | AC56: =IF(OR($A56="",$D56="Completed",$D56="Terminated"),0,IF($C56="",1,IF($C56="Portfolio",0,IF($C56="Outside the portfolio",IF($Q56=1,2,0),IF($B56="Project",IF(IFERROR(INDEX($B$6:$B$305,MATCH($C56,$A$6:$A$305,0)),"")="Program",0,1),1))))) | AD56: =IF(AND($A56<>"",OR($M56="■ Red",$M56="◧ Amber"),$L56=""),1,0) | AE56: =$AA56+$AB56+IF($AC56>0,1,0)+$AD56+$AG56+$AH56 | AG56: =IF(AND($A56<>"",$K56<>"",$C56<>"Portfolio",$D56<>"Completed",$D56<>"Terminated"),1,0) | AH56: =IF(AND($A56<>"",COUNTIF($A$6:$A$305,$A56)>1),1,0) | AI56: =IF(AND($A56<>"",$C56="Portfolio"),COUNTIFS($C$6:$C56,"Portfolio",$A$6:$A56,"<>"),"")
M57: =IF($A57="","",IF($D57="","Not read",IF($Q57=0,"Not counted",IF(MAX($X57,$Y57)=3,"■ Red",IF(MAX($X57,$Y57)=2,"◧ Amber",IF(MAX($X57,$Y57)=1,"□ On track","Not read")))))) | N57: =IF(OR($A57="",$B57<>"Program"),"","■ "&COUNTIFS($C$6:$C$305,$A57,$M$6:$M$305,"■ Red")&" Red, ◧ "&COUNTIFS($C$6:$C$305,$A57,$M$6:$M$305,"◧ Amber")&" Amber") | O57: =IF(OR($A57="",$E57=""),"",COUNTIFS($E$6:$E$305,$E57,$D$6:$D$305,"Active")+COUNTIFS($E$6:$E$305,$E57,$D$6:$D$305,"Paused")) | P57: =IF($A57="","",IF($AE57=0,"○ Clear",IF($AA57=1,"△ No owner",IF($AC57=1,"△ Check Sits under",IF($AC57=2,"△ Outside the portfolio",IF($AB57=1,"△ No sponsor",IF($AH57=1,"△ Name used twice",IF($AG57=1,"△ Budget only counts under Portfolio","△ No variance note"))))))&IF($AE57>1," (+"&($AE57-1)&" more)",""))) | Q57: =IF(AND($A57<>"",OR($D57="Active",$D57="Paused")),1,0) | R57: =IFERROR(INDEX($A$6:$A$305,MATCH(50,$S$6:$S$305,0)),"") | S57: =IF(AND($A57<>"",$B57="Program"),COUNTIFS($B$6:$B57,"Program",$A$6:$A57,"<>"),"") | T57: =IF(AND($A57<>"",$B57="Program"),SUMPRODUCT(MAX(($C$6:$C$305=$A57)*($B$6:$B$305="Project")*($D$6:$D$305<>"Proposed")*$I$6:$I$305)),0) | U57: =IF($I57<>"",$I57,IF($T57>0,$T57,"")) | V57: =IF(AND($A57<>"",$B57="Program"),SUMIFS($J$6:$J$305,$C$6:$C$305,$A57,$B$6:$B$305,"Project",$D$6:$D$305,"<>Proposed"),0) | W57: =IF(AND($A57<>"",$B57="Program"),COUNTIFS($C$6:$C$305,$A57,$B$6:$B$305,"Project",$D$6:$D$305,"<>Proposed")-COUNTIFS($C$6:$C$305,$A57,$B$6:$B$305,"Project",$D$6:$D$305,"<>Proposed",$J$6:$J$305,">=0"),0) | X57: =IF(OR($Q57=0,$H57="",$AF57="Sprint"),0,IF(AND($B57="Project",$H57<TODAY()),3,IF($U57="",0,IF($U57<=$H57,1,IF(NETWORKDAYS($H57,$U57)-1>IF($B57="Program",Checks!$B$7,Checks!$B$6),3,2))))) | Y57: =IF(OR($Q57=0,$K57="",$K57=0,$AF57="Sprint"),0,IF(AND($B57="Project",$J57=""),0,IF(IF($B57="Program",$V57,$J57)>$K57*(1+Checks!$B$8),3,IF(IF($B57="Program",$V57,$J57)>$K57,2,IF(AND($B57="Program",OR($W57>0,$V57=0)),0,1))))) | Z57: =IF($A57="",0,IF($C57="Portfolio",1,IF(AND($B57="Project",$C57<>"",$C57<>"Outside the portfolio"),IFERROR(IF(AND(INDEX($B$6:$B$305,MATCH($C57,$A$6:$A$305,0))="Program",INDEX($C$6:$C$305,MATCH($C57,$A$6:$A$305,0))="Portfolio"),1,0),0),0))) | AA57: =IF(AND($A57<>"",$E57="",OR($Q57=1,$D57="Proposed")),1,0) | AB57: =IF(AND($A57<>"",$B57="Program",$F57="",$Q57=1),1,0) | AC57: =IF(OR($A57="",$D57="Completed",$D57="Terminated"),0,IF($C57="",1,IF($C57="Portfolio",0,IF($C57="Outside the portfolio",IF($Q57=1,2,0),IF($B57="Project",IF(IFERROR(INDEX($B$6:$B$305,MATCH($C57,$A$6:$A$305,0)),"")="Program",0,1),1))))) | AD57: =IF(AND($A57<>"",OR($M57="■ Red",$M57="◧ Amber"),$L57=""),1,0) | AE57: =$AA57+$AB57+IF($AC57>0,1,0)+$AD57+$AG57+$AH57 | AG57: =IF(AND($A57<>"",$K57<>"",$C57<>"Portfolio",$D57<>"Completed",$D57<>"Terminated"),1,0) | AH57: =IF(AND($A57<>"",COUNTIF($A$6:$A$305,$A57)>1),1,0) | AI57: =IF(AND($A57<>"",$C57="Portfolio"),COUNTIFS($C$6:$C57,"Portfolio",$A$6:$A57,"<>"),"")
M58: =IF($A58="","",IF($D58="","Not read",IF($Q58=0,"Not counted",IF(MAX($X58,$Y58)=3,"■ Red",IF(MAX($X58,$Y58)=2,"◧ Amber",IF(MAX($X58,$Y58)=1,"□ On track","Not read")))))) | N58: =IF(OR($A58="",$B58<>"Program"),"","■ "&COUNTIFS($C$6:$C$305,$A58,$M$6:$M$305,"■ Red")&" Red, ◧ "&COUNTIFS($C$6:$C$305,$A58,$M$6:$M$305,"◧ Amber")&" Amber") | O58: =IF(OR($A58="",$E58=""),"",COUNTIFS($E$6:$E$305,$E58,$D$6:$D$305,"Active")+COUNTIFS($E$6:$E$305,$E58,$D$6:$D$305,"Paused")) | P58: =IF($A58="","",IF($AE58=0,"○ Clear",IF($AA58=1,"△ No owner",IF($AC58=1,"△ Check Sits under",IF($AC58=2,"△ Outside the portfolio",IF($AB58=1,"△ No sponsor",IF($AH58=1,"△ Name used twice",IF($AG58=1,"△ Budget only counts under Portfolio","△ No variance note"))))))&IF($AE58>1," (+"&($AE58-1)&" more)",""))) | Q58: =IF(AND($A58<>"",OR($D58="Active",$D58="Paused")),1,0) | R58: =IFERROR(INDEX($A$6:$A$305,MATCH(51,$S$6:$S$305,0)),"") | S58: =IF(AND($A58<>"",$B58="Program"),COUNTIFS($B$6:$B58,"Program",$A$6:$A58,"<>"),"") | T58: =IF(AND($A58<>"",$B58="Program"),SUMPRODUCT(MAX(($C$6:$C$305=$A58)*($B$6:$B$305="Project")*($D$6:$D$305<>"Proposed")*$I$6:$I$305)),0) | U58: =IF($I58<>"",$I58,IF($T58>0,$T58,"")) | V58: =IF(AND($A58<>"",$B58="Program"),SUMIFS($J$6:$J$305,$C$6:$C$305,$A58,$B$6:$B$305,"Project",$D$6:$D$305,"<>Proposed"),0) | W58: =IF(AND($A58<>"",$B58="Program"),COUNTIFS($C$6:$C$305,$A58,$B$6:$B$305,"Project",$D$6:$D$305,"<>Proposed")-COUNTIFS($C$6:$C$305,$A58,$B$6:$B$305,"Project",$D$6:$D$305,"<>Proposed",$J$6:$J$305,">=0"),0) | X58: =IF(OR($Q58=0,$H58="",$AF58="Sprint"),0,IF(AND($B58="Project",$H58<TODAY()),3,IF($U58="",0,IF($U58<=$H58,1,IF(NETWORKDAYS($H58,$U58)-1>IF($B58="Program",Checks!$B$7,Checks!$B$6),3,2))))) | Y58: =IF(OR($Q58=0,$K58="",$K58=0,$AF58="Sprint"),0,IF(AND($B58="Project",$J58=""),0,IF(IF($B58="Program",$V58,$J58)>$K58*(1+Checks!$B$8),3,IF(IF($B58="Program",$V58,$J58)>$K58,2,IF(AND($B58="Program",OR($W58>0,$V58=0)),0,1))))) | Z58: =IF($A58="",0,IF($C58="Portfolio",1,IF(AND($B58="Project",$C58<>"",$C58<>"Outside the portfolio"),IFERROR(IF(AND(INDEX($B$6:$B$305,MATCH($C58,$A$6:$A$305,0))="Program",INDEX($C$6:$C$305,MATCH($C58,$A$6:$A$305,0))="Portfolio"),1,0),0),0))) | AA58: =IF(AND($A58<>"",$E58="",OR($Q58=1,$D58="Proposed")),1,0) | AB58: =IF(AND($A58<>"",$B58="Program",$F58="",$Q58=1),1,0) | AC58: =IF(OR($A58="",$D58="Completed",$D58="Terminated"),0,IF($C58="",1,IF($C58="Portfolio",0,IF($C58="Outside the portfolio",IF($Q58=1,2,0),IF($B58="Project",IF(IFERROR(INDEX($B$6:$B$305,MATCH($C58,$A$6:$A$305,0)),"")="Program",0,1),1))))) | AD58: =IF(AND($A58<>"",OR($M58="■ Red",$M58="◧ Amber"),$L58=""),1,0) | AE58: =$AA58+$AB58+IF($AC58>0,1,0)+$AD58+$AG58+$AH58 | AG58: =IF(AND($A58<>"",$K58<>"",$C58<>"Portfolio",$D58<>"Completed",$D58<>"Terminated"),1,0) | AH58: =IF(AND($A58<>"",COUNTIF($A$6:$A$305,$A58)>1),1,0) | AI58: =IF(AND($A58<>"",$C58="Portfolio"),COUNTIFS($C$6:$C58,"Portfolio",$A$6:$A58,"<>"),"")
M59: =IF($A59="","",IF($D59="","Not read",IF($Q59=0,"Not counted",IF(MAX($X59,$Y59)=3,"■ Red",IF(MAX($X59,$Y59)=2,"◧ Amber",IF(MAX($X59,$Y59)=1,"□ On track","Not read")))))) | N59: =IF(OR($A59="",$B59<>"Program"),"","■ "&COUNTIFS($C$6:$C$305,$A59,$M$6:$M$305,"■ Red")&" Red, ◧ "&COUNTIFS($C$6:$C$305,$A59,$M$6:$M$305,"◧ Amber")&" Amber") | O59: =IF(OR($A59="",$E59=""),"",COUNTIFS($E$6:$E$305,$E59,$D$6:$D$305,"Active")+COUNTIFS($E$6:$E$305,$E59,$D$6:$D$305,"Paused")) | P59: =IF($A59="","",IF($AE59=0,"○ Clear",IF($AA59=1,"△ No owner",IF($AC59=1,"△ Check Sits under",IF($AC59=2,"△ Outside the portfolio",IF($AB59=1,"△ No sponsor",IF($AH59=1,"△ Name used twice",IF($AG59=1,"△ Budget only counts under Portfolio","△ No variance note"))))))&IF($AE59>1," (+"&($AE59-1)&" more)",""))) | Q59: =IF(AND($A59<>"",OR($D59="Active",$D59="Paused")),1,0) | R59: =IFERROR(INDEX($A$6:$A$305,MATCH(52,$S$6:$S$305,0)),"") | S59: =IF(AND($A59<>"",$B59="Program"),COUNTIFS($B$6:$B59,"Program",$A$6:$A59,"<>"),"") | T59: =IF(AND($A59<>"",$B59="Program"),SUMPRODUCT(MAX(($C$6:$C$305=$A59)*($B$6:$B$305="Project")*($D$6:$D$305<>"Proposed")*$I$6:$I$305)),0) | U59: =IF($I59<>"",$I59,IF($T59>0,$T59,"")) | V59: =IF(AND($A59<>"",$B59="Program"),SUMIFS($J$6:$J$305,$C$6:$C$305,$A59,$B$6:$B$305,"Project",$D$6:$D$305,"<>Proposed"),0) | W59: =IF(AND($A59<>"",$B59="Program"),COUNTIFS($C$6:$C$305,$A59,$B$6:$B$305,"Project",$D$6:$D$305,"<>Proposed")-COUNTIFS($C$6:$C$305,$A59,$B$6:$B$305,"Project",$D$6:$D$305,"<>Proposed",$J$6:$J$305,">=0"),0) | X59: =IF(OR($Q59=0,$H59="",$AF59="Sprint"),0,IF(AND($B59="Project",$H59<TODAY()),3,IF($U59="",0,IF($U59<=$H59,1,IF(NETWORKDAYS($H59,$U59)-1>IF($B59="Program",Checks!$B$7,Checks!$B$6),3,2))))) | Y59: =IF(OR($Q59=0,$K59="",$K59=0,$AF59="Sprint"),0,IF(AND($B59="Project",$J59=""),0,IF(IF($B59="Program",$V59,$J59)>$K59*(1+Checks!$B$8),3,IF(IF($B59="Program",$V59,$J59)>$K59,2,IF(AND($B59="Program",OR($W59>0,$V59=0)),0,1))))) | Z59: =IF($A59="",0,IF($C59="Portfolio",1,IF(AND($B59="Project",$C59<>"",$C59<>"Outside the portfolio"),IFERROR(IF(AND(INDEX($B$6:$B$305,MATCH($C59,$A$6:$A$305,0))="Program",INDEX($C$6:$C$305,MATCH($C59,$A$6:$A$305,0))="Portfolio"),1,0),0),0))) | AA59: =IF(AND($A59<>"",$E59="",OR($Q59=1,$D59="Proposed")),1,0) | AB59: =IF(AND($A59<>"",$B59="Program",$F59="",$Q59=1),1,0) | AC59: =IF(OR($A59="",$D59="Completed",$D59="Terminated"),0,IF($C59="",1,IF($C59="Portfolio",0,IF($C59="Outside the portfolio",IF($Q59=1,2,0),IF($B59="Project",IF(IFERROR(INDEX($B$6:$B$305,MATCH($C59,$A$6:$A$305,0)),"")="Program",0,1),1))))) | AD59: =IF(AND($A59<>"",OR($M59="■ Red",$M59="◧ Amber"),$L59=""),1,0) | AE59: =$AA59+$AB59+IF($AC59>0,1,0)+$AD59+$AG59+$AH59 | AG59: =IF(AND($A59<>"",$K59<>"",$C59<>"Portfolio",$D59<>"Completed",$D59<>"Terminated"),1,0) | AH59: =IF(AND($A59<>"",COUNTIF($A$6:$A$305,$A59)>1),1,0) | AI59: =IF(AND($A59<>"",$C59="Portfolio"),COUNTIFS($C$6:$C59,"Portfolio",$A$6:$A59,"<>"),"")
M60: =IF($A60="","",IF($D60="","Not read",IF($Q60=0,"Not counted",IF(MAX($X60,$Y60)=3,"■ Red",IF(MAX($X60,$Y60)=2,"◧ Amber",IF(MAX($X60,$Y60)=1,"□ On track","Not read")))))) | N60: =IF(OR($A60="",$B60<>"Program"),"","■ "&COUNTIFS($C$6:$C$305,$A60,$M$6:$M$305,"■ Red")&" Red, ◧ "&COUNTIFS($C$6:$C$305,$A60,$M$6:$M$305,"◧ Amber")&" Amber") | O60: =IF(OR($A60="",$E60=""),"",COUNTIFS($E$6:$E$305,$E60,$D$6:$D$305,"Active")+COUNTIFS($E$6:$E$305,$E60,$D$6:$D$305,"Paused")) | P60: =IF($A60="","",IF($AE60=0,"○ Clear",IF($AA60=1,"△ No owner",IF($AC60=1,"△ Check Sits under",IF($AC60=2,"△ Outside the portfolio",IF($AB60=1,"△ No sponsor",IF($AH60=1,"△ Name used twice",IF($AG60=1,"△ Budget only counts under Portfolio","△ No variance note"))))))&IF($AE60>1," (+"&($AE60-1)&" more)",""))) | Q60: =IF(AND($A60<>"",OR($D60="Active",$D60="Paused")),1,0) | R60: =IFERROR(INDEX($A$6:$A$305,MATCH(53,$S$6:$S$305,0)),"") | S60: =IF(AND($A60<>"",$B60="Program"),COUNTIFS($B$6:$B60,"Program",$A$6:$A60,"<>"),"") | T60: =IF(AND($A60<>"",$B60="Program"),SUMPRODUCT(MAX(($C$6:$C$305=$A60)*($B$6:$B$305="Project")*($D$6:$D$305<>"Proposed")*$I$6:$I$305)),0) | U60: =IF($I60<>"",$I60,IF($T60>0,$T60,"")) | V60: =IF(AND($A60<>"",$B60="Program"),SUMIFS($J$6:$J$305,$C$6:$C$305,$A60,$B$6:$B$305,"Project",$D$6:$D$305,"<>Proposed"),0) | W60: =IF(AND($A60<>"",$B60="Program"),COUNTIFS($C$6:$C$305,$A60,$B$6:$B$305,"Project",$D$6:$D$305,"<>Proposed")-COUNTIFS($C$6:$C$305,$A60,$B$6:$B$305,"Project",$D$6:$D$305,"<>Proposed",$J$6:$J$305,">=0"),0) | X60: =IF(OR($Q60=0,$H60="",$AF60="Sprint"),0,IF(AND($B60="Project",$H60<TODAY()),3,IF($U60="",0,IF($U60<=$H60,1,IF(NETWORKDAYS($H60,$U60)-1>IF($B60="Program",Checks!$B$7,Checks!$B$6),3,2))))) | Y60: =IF(OR($Q60=0,$K60="",$K60=0,$AF60="Sprint"),0,IF(AND($B60="Project",$J60=""),0,IF(IF($B60="Program",$V60,$J60)>$K60*(1+Checks!$B$8),3,IF(IF($B60="Program",$V60,$J60)>$K60,2,IF(AND($B60="Program",OR($W60>0,$V60=0)),0,1))))) | Z60: =IF($A60="",0,IF($C60="Portfolio",1,IF(AND($B60="Project",$C60<>"",$C60<>"Outside the portfolio"),IFERROR(IF(AND(INDEX($B$6:$B$305,MATCH($C60,$A$6:$A$305,0))="Program",INDEX($C$6:$C$305,MATCH($C60,$A$6:$A$305,0))="Portfolio"),1,0),0),0))) | AA60: =IF(AND($A60<>"",$E60="",OR($Q60=1,$D60="Proposed")),1,0) | AB60: =IF(AND($A60<>"",$B60="Program",$F60="",$Q60=1),1,0) | AC60: =IF(OR($A60="",$D60="Completed",$D60="Terminated"),0,IF($C60="",1,IF($C60="Portfolio",0,IF($C60="Outside the portfolio",IF($Q60=1,2,0),IF($B60="Project",IF(IFERROR(INDEX($B$6:$B$305,MATCH($C60,$A$6:$A$305,0)),"")="Program",0,1),1))))) | AD60: =IF(AND($A60<>"",OR($M60="■ Red",$M60="◧ Amber"),$L60=""),1,0) | AE60: =$AA60+$AB60+IF($AC60>0,1,0)+$AD60+$AG60+$AH60 | AG60: =IF(AND($A60<>"",$K60<>"",$C60<>"Portfolio",$D60<>"Completed",$D60<>"Terminated"),1,0) | AH60: =IF(AND($A60<>"",COUNTIF($A$6:$A$305,$A60)>1),1,0) | AI60: =IF(AND($A60<>"",$C60="Portfolio"),COUNTIFS($C$6:$C60,"Portfolio",$A$6:$A60,"<>"),"")
M61: =IF($A61="","",IF($D61="","Not read",IF($Q61=0,"Not counted",IF(MAX($X61,$Y61)=3,"■ Red",IF(MAX($X61,$Y61)=2,"◧ Amber",IF(MAX($X61,$Y61)=1,"□ On track","Not read")))))) | N61: =IF(OR($A61="",$B61<>"Program"),"","■ "&COUNTIFS($C$6:$C$305,$A61,$M$6:$M$305,"■ Red")&" Red, ◧ "&COUNTIFS($C$6:$C$305,$A61,$M$6:$M$305,"◧ Amber")&" Amber") | O61: =IF(OR($A61="",$E61=""),"",COUNTIFS($E$6:$E$305,$E61,$D$6:$D$305,"Active")+COUNTIFS($E$6:$E$305,$E61,$D$6:$D$305,"Paused")) | P61: =IF($A61="","",IF($AE61=0,"○ Clear",IF($AA61=1,"△ No owner",IF($AC61=1,"△ Check Sits under",IF($AC61=2,"△ Outside the portfolio",IF($AB61=1,"△ No sponsor",IF($AH61=1,"△ Name used twice",IF($AG61=1,"△ Budget only counts under Portfolio","△ No variance note"))))))&IF($AE61>1," (+"&($AE61-1)&" more)",""))) | Q61: =IF(AND($A61<>"",OR($D61="Active",$D61="Paused")),1,0) | R61: =IFERROR(INDEX($A$6:$A$305,MATCH(54,$S$6:$S$305,0)),"") | S61: =IF(AND($A61<>"",$B61="Program"),COUNTIFS($B$6:$B61,"Program",$A$6:$A61,"<>"),"") | T61: =IF(AND($A61<>"",$B61="Program"),SUMPRODUCT(MAX(($C$6:$C$305=$A61)*($B$6:$B$305="Project")*($D$6:$D$305<>"Proposed")*$I$6:$I$305)),0) | U61: =IF($I61<>"",$I61,IF($T61>0,$T61,"")) | V61: =IF(AND($A61<>"",$B61="Program"),SUMIFS($J$6:$J$305,$C$6:$C$305,$A61,$B$6:$B$305,"Project",$D$6:$D$305,"<>Proposed"),0) | W61: =IF(AND($A61<>"",$B61="Program"),COUNTIFS($C$6:$C$305,$A61,$B$6:$B$305,"Project",$D$6:$D$305,"<>Proposed")-COUNTIFS($C$6:$C$305,$A61,$B$6:$B$305,"Project",$D$6:$D$305,"<>Proposed",$J$6:$J$305,">=0"),0) | X61: =IF(OR($Q61=0,$H61="",$AF61="Sprint"),0,IF(AND($B61="Project",$H61<TODAY()),3,IF($U61="",0,IF($U61<=$H61,1,IF(NETWORKDAYS($H61,$U61)-1>IF($B61="Program",Checks!$B$7,Checks!$B$6),3,2))))) | Y61: =IF(OR($Q61=0,$K61="",$K61=0,$AF61="Sprint"),0,IF(AND($B61="Project",$J61=""),0,IF(IF($B61="Program",$V61,$J61)>$K61*(1+Checks!$B$8),3,IF(IF($B61="Program",$V61,$J61)>$K61,2,IF(AND($B61="Program",OR($W61>0,$V61=0)),0,1))))) | Z61: =IF($A61="",0,IF($C61="Portfolio",1,IF(AND($B61="Project",$C61<>"",$C61<>"Outside the portfolio"),IFERROR(IF(AND(INDEX($B$6:$B$305,MATCH($C61,$A$6:$A$305,0))="Program",INDEX($C$6:$C$305,MATCH($C61,$A$6:$A$305,0))="Portfolio"),1,0),0),0))) | AA61: =IF(AND($A61<>"",$E61="",OR($Q61=1,$D61="Proposed")),1,0) | AB61: =IF(AND($A61<>"",$B61="Program",$F61="",$Q61=1),1,0) | AC61: =IF(OR($A61="",$D61="Completed",$D61="Terminated"),0,IF($C61="",1,IF($C61="Portfolio",0,IF($C61="Outside the portfolio",IF($Q61=1,2,0),IF($B61="Project",IF(IFERROR(INDEX($B$6:$B$305,MATCH($C61,$A$6:$A$305,0)),"")="Program",0,1),1))))) | AD61: =IF(AND($A61<>"",OR($M61="■ Red",$M61="◧ Amber"),$L61=""),1,0) | AE61: =$AA61+$AB61+IF($AC61>0,1,0)+$AD61+$AG61+$AH61 | AG61: =IF(AND($A61<>"",$K61<>"",$C61<>"Portfolio",$D61<>"Completed",$D61<>"Terminated"),1,0) | AH61: =IF(AND($A61<>"",COUNTIF($A$6:$A$305,$A61)>1),1,0) | AI61: =IF(AND($A61<>"",$C61="Portfolio"),COUNTIFS($C$6:$C61,"Portfolio",$A$6:$A61,"<>"),"")
M62: =IF($A62="","",IF($D62="","Not read",IF($Q62=0,"Not counted",IF(MAX($X62,$Y62)=3,"■ Red",IF(MAX($X62,$Y62)=2,"◧ Amber",IF(MAX($X62,$Y62)=1,"□ On track","Not read")))))) | N62: =IF(OR($A62="",$B62<>"Program"),"","■ "&COUNTIFS($C$6:$C$305,$A62,$M$6:$M$305,"■ Red")&" Red, ◧ "&COUNTIFS($C$6:$C$305,$A62,$M$6:$M$305,"◧ Amber")&" Amber") | O62: =IF(OR($A62="",$E62=""),"",COUNTIFS($E$6:$E$305,$E62,$D$6:$D$305,"Active")+COUNTIFS($E$6:$E$305,$E62,$D$6:$D$305,"Paused")) | P62: =IF($A62="","",IF($AE62=0,"○ Clear",IF($AA62=1,"△ No owner",IF($AC62=1,"△ Check Sits under",IF($AC62=2,"△ Outside the portfolio",IF($AB62=1,"△ No sponsor",IF($AH62=1,"△ Name used twice",IF($AG62=1,"△ Budget only counts under Portfolio","△ No variance note"))))))&IF($AE62>1," (+"&($AE62-1)&" more)",""))) | Q62: =IF(AND($A62<>"",OR($D62="Active",$D62="Paused")),1,0) | R62: =IFERROR(INDEX($A$6:$A$305,MATCH(55,$S$6:$S$305,0)),"") | S62: =IF(AND($A62<>"",$B62="Program"),COUNTIFS($B$6:$B62,"Program",$A$6:$A62,"<>"),"") | T62: =IF(AND($A62<>"",$B62="Program"),SUMPRODUCT(MAX(($C$6:$C$305=$A62)*($B$6:$B$305="Project")*($D$6:$D$305<>"Proposed")*$I$6:$I$305)),0) | U62: =IF($I62<>"",$I62,IF($T62>0,$T62,"")) | V62: =IF(AND($A62<>"",$B62="Program"),SUMIFS($J$6:$J$305,$C$6:$C$305,$A62,$B$6:$B$305,"Project",$D$6:$D$305,"<>Proposed"),0) | W62: =IF(AND($A62<>"",$B62="Program"),COUNTIFS($C$6:$C$305,$A62,$B$6:$B$305,"Project",$D$6:$D$305,"<>Proposed")-COUNTIFS($C$6:$C$305,$A62,$B$6:$B$305,"Project",$D$6:$D$305,"<>Proposed",$J$6:$J$305,">=0"),0) | X62: =IF(OR($Q62=0,$H62="",$AF62="Sprint"),0,IF(AND($B62="Project",$H62<TODAY()),3,IF($U62="",0,IF($U62<=$H62,1,IF(NETWORKDAYS($H62,$U62)-1>IF($B62="Program",Checks!$B$7,Checks!$B$6),3,2))))) | Y62: =IF(OR($Q62=0,$K62="",$K62=0,$AF62="Sprint"),0,IF(AND($B62="Project",$J62=""),0,IF(IF($B62="Program",$V62,$J62)>$K62*(1+Checks!$B$8),3,IF(IF($B62="Program",$V62,$J62)>$K62,2,IF(AND($B62="Program",OR($W62>0,$V62=0)),0,1))))) | Z62: =IF($A62="",0,IF($C62="Portfolio",1,IF(AND($B62="Project",$C62<>"",$C62<>"Outside the portfolio"),IFERROR(IF(AND(INDEX($B$6:$B$305,MATCH($C62,$A$6:$A$305,0))="Program",INDEX($C$6:$C$305,MATCH($C62,$A$6:$A$305,0))="Portfolio"),1,0),0),0))) | AA62: =IF(AND($A62<>"",$E62="",OR($Q62=1,$D62="Proposed")),1,0) | AB62: =IF(AND($A62<>"",$B62="Program",$F62="",$Q62=1),1,0) | AC62: =IF(OR($A62="",$D62="Completed",$D62="Terminated"),0,IF($C62="",1,IF($C62="Portfolio",0,IF($C62="Outside the portfolio",IF($Q62=1,2,0),IF($B62="Project",IF(IFERROR(INDEX($B$6:$B$305,MATCH($C62,$A$6:$A$305,0)),"")="Program",0,1),1))))) | AD62: =IF(AND($A62<>"",OR($M62="■ Red",$M62="◧ Amber"),$L62=""),1,0) | AE62: =$AA62+$AB62+IF($AC62>0,1,0)+$AD62+$AG62+$AH62 | AG62: =IF(AND($A62<>"",$K62<>"",$C62<>"Portfolio",$D62<>"Completed",$D62<>"Terminated"),1,0) | AH62: =IF(AND($A62<>"",COUNTIF($A$6:$A$305,$A62)>1),1,0) | AI62: =IF(AND($A62<>"",$C62="Portfolio"),COUNTIFS($C$6:$C62,"Portfolio",$A$6:$A62,"<>"),"")
M63: =IF($A63="","",IF($D63="","Not read",IF($Q63=0,"Not counted",IF(MAX($X63,$Y63)=3,"■ Red",IF(MAX($X63,$Y63)=2,"◧ Amber",IF(MAX($X63,$Y63)=1,"□ On track","Not read")))))) | N63: =IF(OR($A63="",$B63<>"Program"),"","■ "&COUNTIFS($C$6:$C$305,$A63,$M$6:$M$305,"■ Red")&" Red, ◧ "&COUNTIFS($C$6:$C$305,$A63,$M$6:$M$305,"◧ Amber")&" Amber") | O63: =IF(OR($A63="",$E63=""),"",COUNTIFS($E$6:$E$305,$E63,$D$6:$D$305,"Active")+COUNTIFS($E$6:$E$305,$E63,$D$6:$D$305,"Paused")) | P63: =IF($A63="","",IF($AE63=0,"○ Clear",IF($AA63=1,"△ No owner",IF($AC63=1,"△ Check Sits under",IF($AC63=2,"△ Outside the portfolio",IF($AB63=1,"△ No sponsor",IF($AH63=1,"△ Name used twice",IF($AG63=1,"△ Budget only counts under Portfolio","△ No variance note"))))))&IF($AE63>1," (+"&($AE63-1)&" more)",""))) | Q63: =IF(AND($A63<>"",OR($D63="Active",$D63="Paused")),1,0) | R63: =IFERROR(INDEX($A$6:$A$305,MATCH(56,$S$6:$S$305,0)),"") | S63: =IF(AND($A63<>"",$B63="Program"),COUNTIFS($B$6:$B63,"Program",$A$6:$A63,"<>"),"") | T63: =IF(AND($A63<>"",$B63="Program"),SUMPRODUCT(MAX(($C$6:$C$305=$A63)*($B$6:$B$305="Project")*($D$6:$D$305<>"Proposed")*$I$6:$I$305)),0) | U63: =IF($I63<>"",$I63,IF($T63>0,$T63,"")) | V63: =IF(AND($A63<>"",$B63="Program"),SUMIFS($J$6:$J$305,$C$6:$C$305,$A63,$B$6:$B$305,"Project",$D$6:$D$305,"<>Proposed"),0) | W63: =IF(AND($A63<>"",$B63="Program"),COUNTIFS($C$6:$C$305,$A63,$B$6:$B$305,"Project",$D$6:$D$305,"<>Proposed")-COUNTIFS($C$6:$C$305,$A63,$B$6:$B$305,"Project",$D$6:$D$305,"<>Proposed",$J$6:$J$305,">=0"),0) | X63: =IF(OR($Q63=0,$H63="",$AF63="Sprint"),0,IF(AND($B63="Project",$H63<TODAY()),3,IF($U63="",0,IF($U63<=$H63,1,IF(NETWORKDAYS($H63,$U63)-1>IF($B63="Program",Checks!$B$7,Checks!$B$6),3,2))))) | Y63: =IF(OR($Q63=0,$K63="",$K63=0,$AF63="Sprint"),0,IF(AND($B63="Project",$J63=""),0,IF(IF($B63="Program",$V63,$J63)>$K63*(1+Checks!$B$8),3,IF(IF($B63="Program",$V63,$J63)>$K63,2,IF(AND($B63="Program",OR($W63>0,$V63=0)),0,1))))) | Z63: =IF($A63="",0,IF($C63="Portfolio",1,IF(AND($B63="Project",$C63<>"",$C63<>"Outside the portfolio"),IFERROR(IF(AND(INDEX($B$6:$B$305,MATCH($C63,$A$6:$A$305,0))="Program",INDEX($C$6:$C$305,MATCH($C63,$A$6:$A$305,0))="Portfolio"),1,0),0),0))) | AA63: =IF(AND($A63<>"",$E63="",OR($Q63=1,$D63="Proposed")),1,0) | AB63: =IF(AND($A63<>"",$B63="Program",$F63="",$Q63=1),1,0) | AC63: =IF(OR($A63="",$D63="Completed",$D63="Terminated"),0,IF($C63="",1,IF($C63="Portfolio",0,IF($C63="Outside the portfolio",IF($Q63=1,2,0),IF($B63="Project",IF(IFERROR(INDEX($B$6:$B$305,MATCH($C63,$A$6:$A$305,0)),"")="Program",0,1),1))))) | AD63: =IF(AND($A63<>"",OR($M63="■ Red",$M63="◧ Amber"),$L63=""),1,0) | AE63: =$AA63+$AB63+IF($AC63>0,1,0)+$AD63+$AG63+$AH63 | AG63: =IF(AND($A63<>"",$K63<>"",$C63<>"Portfolio",$D63<>"Completed",$D63<>"Terminated"),1,0) | AH63: =IF(AND($A63<>"",COUNTIF($A$6:$A$305,$A63)>1),1,0) | AI63: =IF(AND($A63<>"",$C63="Portfolio"),COUNTIFS($C$6:$C63,"Portfolio",$A$6:$A63,"<>"),"")
M64: =IF($A64="","",IF($D64="","Not read",IF($Q64=0,"Not counted",IF(MAX($X64,$Y64)=3,"■ Red",IF(MAX($X64,$Y64)=2,"◧ Amber",IF(MAX($X64,$Y64)=1,"□ On track","Not read")))))) | N64: =IF(OR($A64="",$B64<>"Program"),"","■ "&COUNTIFS($C$6:$C$305,$A64,$M$6:$M$305,"■ Red")&" Red, ◧ "&COUNTIFS($C$6:$C$305,$A64,$M$6:$M$305,"◧ Amber")&" Amber") | O64: =IF(OR($A64="",$E64=""),"",COUNTIFS($E$6:$E$305,$E64,$D$6:$D$305,"Active")+COUNTIFS($E$6:$E$305,$E64,$D$6:$D$305,"Paused")) | P64: =IF($A64="","",IF($AE64=0,"○ Clear",IF($AA64=1,"△ No owner",IF($AC64=1,"△ Check Sits under",IF($AC64=2,"△ Outside the portfolio",IF($AB64=1,"△ No sponsor",IF($AH64=1,"△ Name used twice",IF($AG64=1,"△ Budget only counts under Portfolio","△ No variance note"))))))&IF($AE64>1," (+"&($AE64-1)&" more)",""))) | Q64: =IF(AND($A64<>"",OR($D64="Active",$D64="Paused")),1,0) | R64: =IFERROR(INDEX($A$6:$A$305,MATCH(57,$S$6:$S$305,0)),"") | S64: =IF(AND($A64<>"",$B64="Program"),COUNTIFS($B$6:$B64,"Program",$A$6:$A64,"<>"),"") | T64: =IF(AND($A64<>"",$B64="Program"),SUMPRODUCT(MAX(($C$6:$C$305=$A64)*($B$6:$B$305="Project")*($D$6:$D$305<>"Proposed")*$I$6:$I$305)),0) | U64: =IF($I64<>"",$I64,IF($T64>0,$T64,"")) | V64: =IF(AND($A64<>"",$B64="Program"),SUMIFS($J$6:$J$305,$C$6:$C$305,$A64,$B$6:$B$305,"Project",$D$6:$D$305,"<>Proposed"),0) | W64: =IF(AND($A64<>"",$B64="Program"),COUNTIFS($C$6:$C$305,$A64,$B$6:$B$305,"Project",$D$6:$D$305,"<>Proposed")-COUNTIFS($C$6:$C$305,$A64,$B$6:$B$305,"Project",$D$6:$D$305,"<>Proposed",$J$6:$J$305,">=0"),0) | X64: =IF(OR($Q64=0,$H64="",$AF64="Sprint"),0,IF(AND($B64="Project",$H64<TODAY()),3,IF($U64="",0,IF($U64<=$H64,1,IF(NETWORKDAYS($H64,$U64)-1>IF($B64="Program",Checks!$B$7,Checks!$B$6),3,2))))) | Y64: =IF(OR($Q64=0,$K64="",$K64=0,$AF64="Sprint"),0,IF(AND($B64="Project",$J64=""),0,IF(IF($B64="Program",$V64,$J64)>$K64*(1+Checks!$B$8),3,IF(IF($B64="Program",$V64,$J64)>$K64,2,IF(AND($B64="Program",OR($W64>0,$V64=0)),0,1))))) | Z64: =IF($A64="",0,IF($C64="Portfolio",1,IF(AND($B64="Project",$C64<>"",$C64<>"Outside the portfolio"),IFERROR(IF(AND(INDEX($B$6:$B$305,MATCH($C64,$A$6:$A$305,0))="Program",INDEX($C$6:$C$305,MATCH($C64,$A$6:$A$305,0))="Portfolio"),1,0),0),0))) | AA64: =IF(AND($A64<>"",$E64="",OR($Q64=1,$D64="Proposed")),1,0) | AB64: =IF(AND($A64<>"",$B64="Program",$F64="",$Q64=1),1,0) | AC64: =IF(OR($A64="",$D64="Completed",$D64="Terminated"),0,IF($C64="",1,IF($C64="Portfolio",0,IF($C64="Outside the portfolio",IF($Q64=1,2,0),IF($B64="Project",IF(IFERROR(INDEX($B$6:$B$305,MATCH($C64,$A$6:$A$305,0)),"")="Program",0,1),1))))) | AD64: =IF(AND($A64<>"",OR($M64="■ Red",$M64="◧ Amber"),$L64=""),1,0) | AE64: =$AA64+$AB64+IF($AC64>0,1,0)+$AD64+$AG64+$AH64 | AG64: =IF(AND($A64<>"",$K64<>"",$C64<>"Portfolio",$D64<>"Completed",$D64<>"Terminated"),1,0) | AH64: =IF(AND($A64<>"",COUNTIF($A$6:$A$305,$A64)>1),1,0) | AI64: =IF(AND($A64<>"",$C64="Portfolio"),COUNTIFS($C$6:$C64,"Portfolio",$A$6:$A64,"<>"),"")
M65: =IF($A65="","",IF($D65="","Not read",IF($Q65=0,"Not counted",IF(MAX($X65,$Y65)=3,"■ Red",IF(MAX($X65,$Y65)=2,"◧ Amber",IF(MAX($X65,$Y65)=1,"□ On track","Not read")))))) | N65: =IF(OR($A65="",$B65<>"Program"),"","■ "&COUNTIFS($C$6:$C$305,$A65,$M$6:$M$305,"■ Red")&" Red, ◧ "&COUNTIFS($C$6:$C$305,$A65,$M$6:$M$305,"◧ Amber")&" Amber") | O65: =IF(OR($A65="",$E65=""),"",COUNTIFS($E$6:$E$305,$E65,$D$6:$D$305,"Active")+COUNTIFS($E$6:$E$305,$E65,$D$6:$D$305,"Paused")) | P65: =IF($A65="","",IF($AE65=0,"○ Clear",IF($AA65=1,"△ No owner",IF($AC65=1,"△ Check Sits under",IF($AC65=2,"△ Outside the portfolio",IF($AB65=1,"△ No sponsor",IF($AH65=1,"△ Name used twice",IF($AG65=1,"△ Budget only counts under Portfolio","△ No variance note"))))))&IF($AE65>1," (+"&($AE65-1)&" more)",""))) | Q65: =IF(AND($A65<>"",OR($D65="Active",$D65="Paused")),1,0) | R65: =IFERROR(INDEX($A$6:$A$305,MATCH(58,$S$6:$S$305,0)),"") | S65: =IF(AND($A65<>"",$B65="Program"),COUNTIFS($B$6:$B65,"Program",$A$6:$A65,"<>"),"") | T65: =IF(AND($A65<>"",$B65="Program"),SUMPRODUCT(MAX(($C$6:$C$305=$A65)*($B$6:$B$305="Project")*($D$6:$D$305<>"Proposed")*$I$6:$I$305)),0) | U65: =IF($I65<>"",$I65,IF($T65>0,$T65,"")) | V65: =IF(AND($A65<>"",$B65="Program"),SUMIFS($J$6:$J$305,$C$6:$C$305,$A65,$B$6:$B$305,"Project",$D$6:$D$305,"<>Proposed"),0) | W65: =IF(AND($A65<>"",$B65="Program"),COUNTIFS($C$6:$C$305,$A65,$B$6:$B$305,"Project",$D$6:$D$305,"<>Proposed")-COUNTIFS($C$6:$C$305,$A65,$B$6:$B$305,"Project",$D$6:$D$305,"<>Proposed",$J$6:$J$305,">=0"),0) | X65: =IF(OR($Q65=0,$H65="",$AF65="Sprint"),0,IF(AND($B65="Project",$H65<TODAY()),3,IF($U65="",0,IF($U65<=$H65,1,IF(NETWORKDAYS($H65,$U65)-1>IF($B65="Program",Checks!$B$7,Checks!$B$6),3,2))))) | Y65: =IF(OR($Q65=0,$K65="",$K65=0,$AF65="Sprint"),0,IF(AND($B65="Project",$J65=""),0,IF(IF($B65="Program",$V65,$J65)>$K65*(1+Checks!$B$8),3,IF(IF($B65="Program",$V65,$J65)>$K65,2,IF(AND($B65="Program",OR($W65>0,$V65=0)),0,1))))) | Z65: =IF($A65="",0,IF($C65="Portfolio",1,IF(AND($B65="Project",$C65<>"",$C65<>"Outside the portfolio"),IFERROR(IF(AND(INDEX($B$6:$B$305,MATCH($C65,$A$6:$A$305,0))="Program",INDEX($C$6:$C$305,MATCH($C65,$A$6:$A$305,0))="Portfolio"),1,0),0),0))) | AA65: =IF(AND($A65<>"",$E65="",OR($Q65=1,$D65="Proposed")),1,0) | AB65: =IF(AND($A65<>"",$B65="Program",$F65="",$Q65=1),1,0) | AC65: =IF(OR($A65="",$D65="Completed",$D65="Terminated"),0,IF($C65="",1,IF($C65="Portfolio",0,IF($C65="Outside the portfolio",IF($Q65=1,2,0),IF($B65="Project",IF(IFERROR(INDEX($B$6:$B$305,MATCH($C65,$A$6:$A$305,0)),"")="Program",0,1),1))))) | AD65: =IF(AND($A65<>"",OR($M65="■ Red",$M65="◧ Amber"),$L65=""),1,0) | AE65: =$AA65+$AB65+IF($AC65>0,1,0)+$AD65+$AG65+$AH65 | AG65: =IF(AND($A65<>"",$K65<>"",$C65<>"Portfolio",$D65<>"Completed",$D65<>"Terminated"),1,0) | AH65: =IF(AND($A65<>"",COUNTIF($A$6:$A$305,$A65)>1),1,0) | AI65: =IF(AND($A65<>"",$C65="Portfolio"),COUNTIFS($C$6:$C65,"Portfolio",$A$6:$A65,"<>"),"")
M66: =IF($A66="","",IF($D66="","Not read",IF($Q66=0,"Not counted",IF(MAX($X66,$Y66)=3,"■ Red",IF(MAX($X66,$Y66)=2,"◧ Amber",IF(MAX($X66,$Y66)=1,"□ On track","Not read")))))) | N66: =IF(OR($A66="",$B66<>"Program"),"","■ "&COUNTIFS($C$6:$C$305,$A66,$M$6:$M$305,"■ Red")&" Red, ◧ "&COUNTIFS($C$6:$C$305,$A66,$M$6:$M$305,"◧ Amber")&" Amber") | O66: =IF(OR($A66="",$E66=""),"",COUNTIFS($E$6:$E$305,$E66,$D$6:$D$305,"Active")+COUNTIFS($E$6:$E$305,$E66,$D$6:$D$305,"Paused")) | P66: =IF($A66="","",IF($AE66=0,"○ Clear",IF($AA66=1,"△ No owner",IF($AC66=1,"△ Check Sits under",IF($AC66=2,"△ Outside the portfolio",IF($AB66=1,"△ No sponsor",IF($AH66=1,"△ Name used twice",IF($AG66=1,"△ Budget only counts under Portfolio","△ No variance note"))))))&IF($AE66>1," (+"&($AE66-1)&" more)",""))) | Q66: =IF(AND($A66<>"",OR($D66="Active",$D66="Paused")),1,0) | R66: =IFERROR(INDEX($A$6:$A$305,MATCH(59,$S$6:$S$305,0)),"") | S66: =IF(AND($A66<>"",$B66="Program"),COUNTIFS($B$6:$B66,"Program",$A$6:$A66,"<>"),"") | T66: =IF(AND($A66<>"",$B66="Program"),SUMPRODUCT(MAX(($C$6:$C$305=$A66)*($B$6:$B$305="Project")*($D$6:$D$305<>"Proposed")*$I$6:$I$305)),0) | U66: =IF($I66<>"",$I66,IF($T66>0,$T66,"")) | V66: =IF(AND($A66<>"",$B66="Program"),SUMIFS($J$6:$J$305,$C$6:$C$305,$A66,$B$6:$B$305,"Project",$D$6:$D$305,"<>Proposed"),0) | W66: =IF(AND($A66<>"",$B66="Program"),COUNTIFS($C$6:$C$305,$A66,$B$6:$B$305,"Project",$D$6:$D$305,"<>Proposed")-COUNTIFS($C$6:$C$305,$A66,$B$6:$B$305,"Project",$D$6:$D$305,"<>Proposed",$J$6:$J$305,">=0"),0) | X66: =IF(OR($Q66=0,$H66="",$AF66="Sprint"),0,IF(AND($B66="Project",$H66<TODAY()),3,IF($U66="",0,IF($U66<=$H66,1,IF(NETWORKDAYS($H66,$U66)-1>IF($B66="Program",Checks!$B$7,Checks!$B$6),3,2))))) | Y66: =IF(OR($Q66=0,$K66="",$K66=0,$AF66="Sprint"),0,IF(AND($B66="Project",$J66=""),0,IF(IF($B66="Program",$V66,$J66)>$K66*(1+Checks!$B$8),3,IF(IF($B66="Program",$V66,$J66)>$K66,2,IF(AND($B66="Program",OR($W66>0,$V66=0)),0,1))))) | Z66: =IF($A66="",0,IF($C66="Portfolio",1,IF(AND($B66="Project",$C66<>"",$C66<>"Outside the portfolio"),IFERROR(IF(AND(INDEX($B$6:$B$305,MATCH($C66,$A$6:$A$305,0))="Program",INDEX($C$6:$C$305,MATCH($C66,$A$6:$A$305,0))="Portfolio"),1,0),0),0))) | AA66: =IF(AND($A66<>"",$E66="",OR($Q66=1,$D66="Proposed")),1,0) | AB66: =IF(AND($A66<>"",$B66="Program",$F66="",$Q66=1),1,0) | AC66: =IF(OR($A66="",$D66="Completed",$D66="Terminated"),0,IF($C66="",1,IF($C66="Portfolio",0,IF($C66="Outside the portfolio",IF($Q66=1,2,0),IF($B66="Project",IF(IFERROR(INDEX($B$6:$B$305,MATCH($C66,$A$6:$A$305,0)),"")="Program",0,1),1))))) | AD66: =IF(AND($A66<>"",OR($M66="■ Red",$M66="◧ Amber"),$L66=""),1,0) | AE66: =$AA66+$AB66+IF($AC66>0,1,0)+$AD66+$AG66+$AH66 | AG66: =IF(AND($A66<>"",$K66<>"",$C66<>"Portfolio",$D66<>"Completed",$D66<>"Terminated"),1,0) | AH66: =IF(AND($A66<>"",COUNTIF($A$6:$A$305,$A66)>1),1,0) | AI66: =IF(AND($A66<>"",$C66="Portfolio"),COUNTIFS($C$6:$C66,"Portfolio",$A$6:$A66,"<>"),"")
M67: =IF($A67="","",IF($D67="","Not read",IF($Q67=0,"Not counted",IF(MAX($X67,$Y67)=3,"■ Red",IF(MAX($X67,$Y67)=2,"◧ Amber",IF(MAX($X67,$Y67)=1,"□ On track","Not read")))))) | N67: =IF(OR($A67="",$B67<>"Program"),"","■ "&COUNTIFS($C$6:$C$305,$A67,$M$6:$M$305,"■ Red")&" Red, ◧ "&COUNTIFS($C$6:$C$305,$A67,$M$6:$M$305,"◧ Amber")&" Amber") | O67: =IF(OR($A67="",$E67=""),"",COUNTIFS($E$6:$E$305,$E67,$D$6:$D$305,"Active")+COUNTIFS($E$6:$E$305,$E67,$D$6:$D$305,"Paused")) | P67: =IF($A67="","",IF($AE67=0,"○ Clear",IF($AA67=1,"△ No owner",IF($AC67=1,"△ Check Sits under",IF($AC67=2,"△ Outside the portfolio",IF($AB67=1,"△ No sponsor",IF($AH67=1,"△ Name used twice",IF($AG67=1,"△ Budget only counts under Portfolio","△ No variance note"))))))&IF($AE67>1," (+"&($AE67-1)&" more)",""))) | Q67: =IF(AND($A67<>"",OR($D67="Active",$D67="Paused")),1,0) | R67: =IFERROR(INDEX($A$6:$A$305,MATCH(60,$S$6:$S$305,0)),"") | S67: =IF(AND($A67<>"",$B67="Program"),COUNTIFS($B$6:$B67,"Program",$A$6:$A67,"<>"),"") | T67: =IF(AND($A67<>"",$B67="Program"),SUMPRODUCT(MAX(($C$6:$C$305=$A67)*($B$6:$B$305="Project")*($D$6:$D$305<>"Proposed")*$I$6:$I$305)),0) | U67: =IF($I67<>"",$I67,IF($T67>0,$T67,"")) | V67: =IF(AND($A67<>"",$B67="Program"),SUMIFS($J$6:$J$305,$C$6:$C$305,$A67,$B$6:$B$305,"Project",$D$6:$D$305,"<>Proposed"),0) | W67: =IF(AND($A67<>"",$B67="Program"),COUNTIFS($C$6:$C$305,$A67,$B$6:$B$305,"Project",$D$6:$D$305,"<>Proposed")-COUNTIFS($C$6:$C$305,$A67,$B$6:$B$305,"Project",$D$6:$D$305,"<>Proposed",$J$6:$J$305,">=0"),0) | X67: =IF(OR($Q67=0,$H67="",$AF67="Sprint"),0,IF(AND($B67="Project",$H67<TODAY()),3,IF($U67="",0,IF($U67<=$H67,1,IF(NETWORKDAYS($H67,$U67)-1>IF($B67="Program",Checks!$B$7,Checks!$B$6),3,2))))) | Y67: =IF(OR($Q67=0,$K67="",$K67=0,$AF67="Sprint"),0,IF(AND($B67="Project",$J67=""),0,IF(IF($B67="Program",$V67,$J67)>$K67*(1+Checks!$B$8),3,IF(IF($B67="Program",$V67,$J67)>$K67,2,IF(AND($B67="Program",OR($W67>0,$V67=0)),0,1))))) | Z67: =IF($A67="",0,IF($C67="Portfolio",1,IF(AND($B67="Project",$C67<>"",$C67<>"Outside the portfolio"),IFERROR(IF(AND(INDEX($B$6:$B$305,MATCH($C67,$A$6:$A$305,0))="Program",INDEX($C$6:$C$305,MATCH($C67,$A$6:$A$305,0))="Portfolio"),1,0),0),0))) | AA67: =IF(AND($A67<>"",$E67="",OR($Q67=1,$D67="Proposed")),1,0) | AB67: =IF(AND($A67<>"",$B67="Program",$F67="",$Q67=1),1,0) | AC67: =IF(OR($A67="",$D67="Completed",$D67="Terminated"),0,IF($C67="",1,IF($C67="Portfolio",0,IF($C67="Outside the portfolio",IF($Q67=1,2,0),IF($B67="Project",IF(IFERROR(INDEX($B$6:$B$305,MATCH($C67,$A$6:$A$305,0)),"")="Program",0,1),1))))) | AD67: =IF(AND($A67<>"",OR($M67="■ Red",$M67="◧ Amber"),$L67=""),1,0) | AE67: =$AA67+$AB67+IF($AC67>0,1,0)+$AD67+$AG67+$AH67 | AG67: =IF(AND($A67<>"",$K67<>"",$C67<>"Portfolio",$D67<>"Completed",$D67<>"Terminated"),1,0) | AH67: =IF(AND($A67<>"",COUNTIF($A$6:$A$305,$A67)>1),1,0) | AI67: =IF(AND($A67<>"",$C67="Portfolio"),COUNTIFS($C$6:$C67,"Portfolio",$A$6:$A67,"<>"),"")
M68: =IF($A68="","",IF($D68="","Not read",IF($Q68=0,"Not counted",IF(MAX($X68,$Y68)=3,"■ Red",IF(MAX($X68,$Y68)=2,"◧ Amber",IF(MAX($X68,$Y68)=1,"□ On track","Not read")))))) | N68: =IF(OR($A68="",$B68<>"Program"),"","■ "&COUNTIFS($C$6:$C$305,$A68,$M$6:$M$305,"■ Red")&" Red, ◧ "&COUNTIFS($C$6:$C$305,$A68,$M$6:$M$305,"◧ Amber")&" Amber") | O68: =IF(OR($A68="",$E68=""),"",COUNTIFS($E$6:$E$305,$E68,$D$6:$D$305,"Active")+COUNTIFS($E$6:$E$305,$E68,$D$6:$D$305,"Paused")) | P68: =IF($A68="","",IF($AE68=0,"○ Clear",IF($AA68=1,"△ No owner",IF($AC68=1,"△ Check Sits under",IF($AC68=2,"△ Outside the portfolio",IF($AB68=1,"△ No sponsor",IF($AH68=1,"△ Name used twice",IF($AG68=1,"△ Budget only counts under Portfolio","△ No variance note"))))))&IF($AE68>1," (+"&($AE68-1)&" more)",""))) | Q68: =IF(AND($A68<>"",OR($D68="Active",$D68="Paused")),1,0) | R68: =IFERROR(INDEX($A$6:$A$305,MATCH(61,$S$6:$S$305,0)),"") | S68: =IF(AND($A68<>"",$B68="Program"),COUNTIFS($B$6:$B68,"Program",$A$6:$A68,"<>"),"") | T68: =IF(AND($A68<>"",$B68="Program"),SUMPRODUCT(MAX(($C$6:$C$305=$A68)*($B$6:$B$305="Project")*($D$6:$D$305<>"Proposed")*$I$6:$I$305)),0) | U68: =IF($I68<>"",$I68,IF($T68>0,$T68,"")) | V68: =IF(AND($A68<>"",$B68="Program"),SUMIFS($J$6:$J$305,$C$6:$C$305,$A68,$B$6:$B$305,"Project",$D$6:$D$305,"<>Proposed"),0) | W68: =IF(AND($A68<>"",$B68="Program"),COUNTIFS($C$6:$C$305,$A68,$B$6:$B$305,"Project",$D$6:$D$305,"<>Proposed")-COUNTIFS($C$6:$C$305,$A68,$B$6:$B$305,"Project",$D$6:$D$305,"<>Proposed",$J$6:$J$305,">=0"),0) | X68: =IF(OR($Q68=0,$H68="",$AF68="Sprint"),0,IF(AND($B68="Project",$H68<TODAY()),3,IF($U68="",0,IF($U68<=$H68,1,IF(NETWORKDAYS($H68,$U68)-1>IF($B68="Program",Checks!$B$7,Checks!$B$6),3,2))))) | Y68: =IF(OR($Q68=0,$K68="",$K68=0,$AF68="Sprint"),0,IF(AND($B68="Project",$J68=""),0,IF(IF($B68="Program",$V68,$J68)>$K68*(1+Checks!$B$8),3,IF(IF($B68="Program",$V68,$J68)>$K68,2,IF(AND($B68="Program",OR($W68>0,$V68=0)),0,1))))) | Z68: =IF($A68="",0,IF($C68="Portfolio",1,IF(AND($B68="Project",$C68<>"",$C68<>"Outside the portfolio"),IFERROR(IF(AND(INDEX($B$6:$B$305,MATCH($C68,$A$6:$A$305,0))="Program",INDEX($C$6:$C$305,MATCH($C68,$A$6:$A$305,0))="Portfolio"),1,0),0),0))) | AA68: =IF(AND($A68<>"",$E68="",OR($Q68=1,$D68="Proposed")),1,0) | AB68: =IF(AND($A68<>"",$B68="Program",$F68="",$Q68=1),1,0) | AC68: =IF(OR($A68="",$D68="Completed",$D68="Terminated"),0,IF($C68="",1,IF($C68="Portfolio",0,IF($C68="Outside the portfolio",IF($Q68=1,2,0),IF($B68="Project",IF(IFERROR(INDEX($B$6:$B$305,MATCH($C68,$A$6:$A$305,0)),"")="Program",0,1),1))))) | AD68: =IF(AND($A68<>"",OR($M68="■ Red",$M68="◧ Amber"),$L68=""),1,0) | AE68: =$AA68+$AB68+IF($AC68>0,1,0)+$AD68+$AG68+$AH68 | AG68: =IF(AND($A68<>"",$K68<>"",$C68<>"Portfolio",$D68<>"Completed",$D68<>"Terminated"),1,0) | AH68: =IF(AND($A68<>"",COUNTIF($A$6:$A$305,$A68)>1),1,0) | AI68: =IF(AND($A68<>"",$C68="Portfolio"),COUNTIFS($C$6:$C68,"Portfolio",$A$6:$A68,"<>"),"")
M69: =IF($A69="","",IF($D69="","Not read",IF($Q69=0,"Not counted",IF(MAX($X69,$Y69)=3,"■ Red",IF(MAX($X69,$Y69)=2,"◧ Amber",IF(MAX($X69,$Y69)=1,"□ On track","Not read")))))) | N69: =IF(OR($A69="",$B69<>"Program"),"","■ "&COUNTIFS($C$6:$C$305,$A69,$M$6:$M$305,"■ Red")&" Red, ◧ "&COUNTIFS($C$6:$C$305,$A69,$M$6:$M$305,"◧ Amber")&" Amber") | O69: =IF(OR($A69="",$E69=""),"",COUNTIFS($E$6:$E$305,$E69,$D$6:$D$305,"Active")+COUNTIFS($E$6:$E$305,$E69,$D$6:$D$305,"Paused")) | P69: =IF($A69="","",IF($AE69=0,"○ Clear",IF($AA69=1,"△ No owner",IF($AC69=1,"△ Check Sits under",IF($AC69=2,"△ Outside the portfolio",IF($AB69=1,"△ No sponsor",IF($AH69=1,"△ Name used twice",IF($AG69=1,"△ Budget only counts under Portfolio","△ No variance note"))))))&IF($AE69>1," (+"&($AE69-1)&" more)",""))) | Q69: =IF(AND($A69<>"",OR($D69="Active",$D69="Paused")),1,0) | R69: =IFERROR(INDEX($A$6:$A$305,MATCH(62,$S$6:$S$305,0)),"") | S69: =IF(AND($A69<>"",$B69="Program"),COUNTIFS($B$6:$B69,"Program",$A$6:$A69,"<>"),"") | T69: =IF(AND($A69<>"",$B69="Program"),SUMPRODUCT(MAX(($C$6:$C$305=$A69)*($B$6:$B$305="Project")*($D$6:$D$305<>"Proposed")*$I$6:$I$305)),0) | U69: =IF($I69<>"",$I69,IF($T69>0,$T69,"")) | V69: =IF(AND($A69<>"",$B69="Program"),SUMIFS($J$6:$J$305,$C$6:$C$305,$A69,$B$6:$B$305,"Project",$D$6:$D$305,"<>Proposed"),0) | W69: =IF(AND($A69<>"",$B69="Program"),COUNTIFS($C$6:$C$305,$A69,$B$6:$B$305,"Project",$D$6:$D$305,"<>Proposed")-COUNTIFS($C$6:$C$305,$A69,$B$6:$B$305,"Project",$D$6:$D$305,"<>Proposed",$J$6:$J$305,">=0"),0) | X69: =IF(OR($Q69=0,$H69="",$AF69="Sprint"),0,IF(AND($B69="Project",$H69<TODAY()),3,IF($U69="",0,IF($U69<=$H69,1,IF(NETWORKDAYS($H69,$U69)-1>IF($B69="Program",Checks!$B$7,Checks!$B$6),3,2))))) | Y69: =IF(OR($Q69=0,$K69="",$K69=0,$AF69="Sprint"),0,IF(AND($B69="Project",$J69=""),0,IF(IF($B69="Program",$V69,$J69)>$K69*(1+Checks!$B$8),3,IF(IF($B69="Program",$V69,$J69)>$K69,2,IF(AND($B69="Program",OR($W69>0,$V69=0)),0,1))))) | Z69: =IF($A69="",0,IF($C69="Portfolio",1,IF(AND($B69="Project",$C69<>"",$C69<>"Outside the portfolio"),IFERROR(IF(AND(INDEX($B$6:$B$305,MATCH($C69,$A$6:$A$305,0))="Program",INDEX($C$6:$C$305,MATCH($C69,$A$6:$A$305,0))="Portfolio"),1,0),0),0))) | AA69: =IF(AND($A69<>"",$E69="",OR($Q69=1,$D69="Proposed")),1,0) | AB69: =IF(AND($A69<>"",$B69="Program",$F69="",$Q69=1),1,0) | AC69: =IF(OR($A69="",$D69="Completed",$D69="Terminated"),0,IF($C69="",1,IF($C69="Portfolio",0,IF($C69="Outside the portfolio",IF($Q69=1,2,0),IF($B69="Project",IF(IFERROR(INDEX($B$6:$B$305,MATCH($C69,$A$6:$A$305,0)),"")="Program",0,1),1))))) | AD69: =IF(AND($A69<>"",OR($M69="■ Red",$M69="◧ Amber"),$L69=""),1,0) | AE69: =$AA69+$AB69+IF($AC69>0,1,0)+$AD69+$AG69+$AH69 | AG69: =IF(AND($A69<>"",$K69<>"",$C69<>"Portfolio",$D69<>"Completed",$D69<>"Terminated"),1,0) | AH69: =IF(AND($A69<>"",COUNTIF($A$6:$A$305,$A69)>1),1,0) | AI69: =IF(AND($A69<>"",$C69="Portfolio"),COUNTIFS($C$6:$C69,"Portfolio",$A$6:$A69,"<>"),"")
